Workbook

Sheet Tracker
E2: P0, P1, P2, P3
C4: Page | D4: Bugs Logged | E4: Resolved | F4: Open | G4: Hold
B5: PVT | C5: Homepage | D5: {=SUMPRODUCT(('Home Page'!$G$2:$G$799="PVT") * ('Home Page'!$A$2:$A$799<>"") * (ISNUMBER(SEARCH('Home Page'!$C$2:$C$799, $E$2))))} -> 49 | E5: {=SUMPRODUCT(('Home Page'!$G$2:$G$799="PVT") * ('Home Page'!$Q$2:$Q$799="Resolved") * (ISNUMBER(SEARCH('Home Page'!$C$2:$C$799, $E$2))))} -> 20 | F5: {=SUMPRODUCT(('Home Page'!$G$2:$G$799="PVT") * (('Home Page'!$Q$2:$Q$799="Open") + ('Home Page'!$Q$2:$Q$799="Reopened")) * (ISNUMBER(SEARCH('Home Page'!$C$2:$C$799, $E$2))))} -> 28 | G5: {=SUMPRODUCT(('Home Page'!$G$2:$G$799="PVT") * ('Home Page'!$Q$2:$Q$799="Hold") * (ISNUMBER(SEARCH('Home Page'!$C$2:$C$799, $E$2))))} -> 1
C6: Product | D6: {=SUMPRODUCT(('Product Details Page'!$G$2:$G$800="PVT") * ('Product Details Page'!$A$2:$A$800<>"") * (ISNUMBER(SEARCH('Product Details Page'!$C$2:$C$800, $E$2)))) + SUMPRODUCT(('Credit Card Pages'!$F$2:$F$800="PVT") * ('Credit Card Pages'!$A$2:$A$800<>"") * (ISNUMBER(SEARCH('Credit Card Pages'!$C$2:$C$800, $E$2))))} -> 57 | E6: {=SUMPRODUCT(('Product Details Page'!$G$2:$G$800="PVT") * ('Product Details Page'!$Q$2:$Q$800="Resolved") * (ISNUMBER(SEARCH('Product Details Page'!$C$2:$C$800, $E$2)))) + SUMPRODUCT(('Credit Card Pages'!$F$2:$F$800="PVT") * ('Credit Card Pages'!$R$2:$R$800="Resolved") * (ISNUMBER(SEARCH('Credit Card Pages'!$C$2:$C$800, $E$2))))} -> 34 | F6: {=SUMPRODUCT(('Product Details Page'!$G$2:$G$800="PVT") * (('Product Details Page'!$Q$2:$Q$800="Open") + ('Product Details Page'!$Q$2:$Q$800="Reopened")) * (ISNUMBER(SEARCH('Product Details Page'!$C$2:$C$800, $E$2)))) + SUMPRODUCT(('Credit Card Pages'!$F$2:$F$800="PVT") * (('Credit Card Pages'!$R$2:$R$800="Open") + ('Credit Card Pages'!$R$2:$R$800="Reopened")) * (ISNUMBER(SEARCH('Credit Card Pages'!$C$2:$C$800, $E$2))))} -> 23 | G6: {=SUMPRODUCT(('Product Details Page'!$G$2:$G$800="PVT") * ('Product Details Page'!$Q$2:$Q$800="Hold") * (ISNUMBER(SEARCH('Product Details Page'!$C$2:$C$800, $E$2)))) + SUMPRODUCT(('Credit Card Pages'!$F$2:$F$800="PVT") * ('Credit Card Pages'!$R$2:$R$800="Hold") * (ISNUMBER(SEARCH('Credit Card Pages'!$C$2:$C$800, $E$2))))} -> 0
C7: Catalogue | D7: {=SUMPRODUCT(('Catalogue Page'!$G$2:$G$800="PVT") * ('Catalogue Page'!$A$2:$A$800<>"") * (ISNUMBER(SEARCH('Catalogue Page'!$C$2:$C$800, $E$2))))} -> 69 | E7: {=SUMPRODUCT(('Catalogue Page'!$G$2:$G$800="PVT") * ('Catalogue Page'!$Q$2:$Q$800="Resolved") * (ISNUMBER(SEARCH('Catalogue Page'!$C$2:$C$800, $E$2))))} -> 30 | F7: {=SUMPRODUCT(('Catalogue Page'!$G$2:$G$800="PVT") * (('Catalogue Page'!$Q$2:$Q$800="Open") + ('Catalogue Page'!$Q$2:$Q$800="Reopened")) * (ISNUMBER(SEARCH('Catalogue Page'!$C$2:$C$800, $E$2))))} -> 39 | G7: {=SUMPRODUCT(('Catalogue Page'!$G$2:$G$800="PVT") * ('Catalogue Page'!$Q$2:$Q$800="Hold") * (ISNUMBER(SEARCH('Catalogue Page'!$C$2:$C$800, $E$2))))} -> 0
C8: Header - Footer | D8: {=SUMPRODUCT(('Header & Footer'!$F$2:$F$800="PVT") * ('Header & Footer'!$A$2:$A$800<>"") * (ISNUMBER(SEARCH('Header & Footer'!$C$2:$C$800, $E$2))))} -> 16 | E8: {=SUMPRODUCT(('Header & Footer'!$F$2:$F$799="PVT") * ('Header & Footer'!$R$2:$R$799="Resolved") * (ISNUMBER(SEARCH('Header & Footer'!$C$2:$C$799, $E$2))))} -> 11 | F8: {=SUMPRODUCT(('Header & Footer'!$F$2:$F$799="PVT") * (('Header & Footer'!$R$2:$R$799="Open") + ('Header & Footer'!$R$2:$R$799="Reopened")) * (ISNUMBER(SEARCH('Header & Footer'!$C$2:$C$799, $E$2))))} -> 5 | G8: {=SUMPRODUCT(('Header & Footer'!$F$2:$F$799="PVT") * ('Header & Footer'!$R$2:$R$799="Hold") * (ISNUMBER(SEARCH('Header & Footer'!$C$2:$C$799, $E$2))))} -> 0
C9: Total | D9: =SUM(D5:D8) -> 191 | E9: =SUM(E5:E8) -> 95 | F9: =SUM(F5:F8) -> 95 | G9: =SUM(G5:G8) -> 1
B11: UAT | C11: Homepage | D11: {=SUMPRODUCT(('Home Page'!$G$2:$G$799="UAT") * ('Home Page'!$A$2:$A$799<>"") * (ISNUMBER(SEARCH('Home Page'!$C$2:$C$799, $E$2))))} -> 51 | E11: {=SUMPRODUCT(('Home Page'!$G$2:$G$799="UAT") * ('Home Page'!$Q$2:$Q$799="Resolved") * (ISNUMBER(SEARCH('Home Page'!$C$2:$C$799, $E$2))))} -> 25 | F11: {=SUMPRODUCT(('Home Page'!$G$2:$G$799="UAT") * (('Home Page'!$Q$2:$Q$799="Open") + ('Home Page'!$Q$2:$Q$799="Reopened")) * (ISNUMBER(SEARCH('Home Page'!$C$2:$C$799, $E$2))))} -> 5 | G11: {=SUMPRODUCT(('Home Page'!$G$2:$G$799="UAT") * ('Home Page'!$Q$2:$Q$799="Hold") * (ISNUMBER(SEARCH('Home Page'!$C$2:$C$799, $E$2))))} -> 21
C12: Product | D12: {=SUMPRODUCT(('Product Details Page'!$G$2:$G$800="UAT") * ('Product Details Page'!$A$2:$A$800<>"") * (ISNUMBER(SEARCH('Product Details Page'!$C$2:$C$800, $E$2)))) + SUMPRODUCT(('Credit Card Pages'!$F$2:$F$800="UAT") * ('Credit Card Pages'!$A$2:$A$800<>"") * (ISNUMBER(SEARCH('Credit Card Pages'!$C$2:$C$800, $E$2))))} -> 281 | E12: {=SUMPRODUCT(('Product Details Page'!$G$2:$G$800="UAT") * ('Product Details Page'!$Q$2:$Q$800="Resolved") * (ISNUMBER(SEARCH('Product Details Page'!$C$2:$C$800, $E$2)))) + SUMPRODUCT(('Credit Card Pages'!$F$2:$F$800="UAT") * ('Credit Card Pages'!$R$2:$R$800="Resolved") * (ISNUMBER(SEARCH('Credit Card Pages'!$C$2:$C$800, $E$2))))} -> 239 | F12: {=SUMPRODUCT(('Product Details Page'!$G$2:$G$800="UAT") * (('Product Details Page'!$Q$2:$Q$800="Open") + ('Product Details Page'!$Q$2:$Q$800="Reopened")) * (ISNUMBER(SEARCH('Product Details Page'!$C$2:$C$800, $E$2)))) + SUMPRODUCT(('Credit Card Pages'!$F$2:$F$800="UAT") * (('Credit Card Pages'!$R$2:$R$800="Open") + ('Credit Card Pages'!$R$2:$R$800="Reopened")) * (ISNUMBER(SEARCH('Credit Card Pages'!$C$2:$C$800, $E$2))))} -> 27 | G12: {=SUMPRODUCT(('Product Details Page'!$G$2:$G$800="UAT") * ('Product Details Page'!$Q$2:$Q$800="Hold") * (ISNUMBER(SEARCH('Product Details Page'!$C$2:$C$800, $E$2)))) + SUMPRODUCT(('Credit Card Pages'!$F$2:$F$800="UAT") * ('Credit Card Pages'!$R$2:$R$800="Hold") * (ISNUMBER(SEARCH('Credit Card Pages'!$C$2:$C$800, $E$2))))} -> 15
C13: Catalogue | D13: {=SUMPRODUCT(('Catalogue Page'!$G$2:$G$800="UAT") * ('Catalogue Page'!$A$2:$A$800<>"") * (ISNUMBER(SEARCH('Catalogue Page'!$C$2:$C$800, $E$2))))} -> 40 | E13: {=SUMPRODUCT(('Catalogue Page'!$G$2:$G$800="UAT") * ('Catalogue Page'!$Q$2:$Q$800="Resolved") * (ISNUMBER(SEARCH('Catalogue Page'!$C$2:$C$800, $E$2))))} -> 19 | F13: {=SUMPRODUCT(('Catalogue Page'!$G$2:$G$800="UAT") * (('Catalogue Page'!$Q$2:$Q$800="Open") + ('Catalogue Page'!$Q$2:$Q$800="Reopened")) * (ISNUMBER(SEARCH('Catalogue Page'!$C$2:$C$800, $E$2))))} -> 3 | G13: {=SUMPRODUCT(('Catalogue Page'!$G$2:$G$800="UAT") * ('Catalogue Page'!$Q$2:$Q$800="Hold") * (ISNUMBER(SEARCH('Catalogue Page'!$C$2:$C$800, $E$2))))} -> 18
C14: Header - Footer | D14: {=SUMPRODUCT(('Header & Footer'!$F$2:$F$800="UAT") * ('Header & Footer'!$A$2:$A$800<>"") * (ISNUMBER(SEARCH('Header & Footer'!$C$2:$C$800, $E$2))))} -> 25 | E14: {=SUMPRODUCT(('Header & Footer'!$F$2:$F$799="UAT") * ('Header & Footer'!$R$2:$R$799="Resolved") * (ISNUMBER(SEARCH('Header & Footer'!$C$2:$C$799, $E$2))))} -> 17 | F14: {=SUMPRODUCT(('Header & Footer'!$F$2:$F$799="UAT") * (('Header & Footer'!$R$2:$R$799="Open") + ('Header & Footer'!$R$2:$R$799="Reopened")) * (ISNUMBER(SEARCH('Header & Footer'!$C$2:$C$799, $E$2))))} -> 1 | G14: {=SUMPRODUCT(('Header & Footer'!$F$2:$F$799="UAT") * ('Header & Footer'!$R$2:$R$799="Hold") * (ISNUMBER(SEARCH('Header & Footer'!$C$2:$C$799, $E$2))))} -> 7
C15: Total | D15: =SUM(D11:D14) -> 397 | E15: =SUM(E11:E14) -> 300 | F15: =SUM(F11:F14) -> 36 | G15: =SUM(G11:G14) -> 61
I16: Fixed on HTML | J16: Pending/Reopen | K16: Tested on (Version Name)
B17: HTML/CSS | C17: Homepage | D17: {=SUMPRODUCT(('Home Page'!$G$2:$G$799="HTML/CSS") * ('Home Page'!$A$2:$A$799<>"") * (ISNUMBER(SEARCH('Home Page'!$C$2:$C$799, $E$2))))} -> 12 | E17: {=SUMPRODUCT(('Home Page'!$G$2:$G$799="HTML/CSS") * ('Home Page'!$Q$2:$Q$799="Resolved") * (ISNUMBER(SEARCH('Home Page'!$C$2:$C$799, $E$2))))} -> 7 | F17: {=SUMPRODUCT(('Home Page'!$G$2:$G$799="HTML/CSS") * (('Home Page'!$Q$2:$Q$799="Open") + ('Home Page'!$Q$2:$Q$799="Reopened")) * (ISNUMBER(SEARCH('Home Page'!$C$2:$C$799, $E$2))))} -> 4 | G17: {=SUMPRODUCT(('Home Page'!$G$2:$G$799="HTML/CSS") * ('Home Page'!$Q$2:$Q$799="Hold") * (ISNUMBER(SEARCH('Home Page'!$C$2:$C$799, $E$2))))} -> 1 | I17: {=SUMPRODUCT(('Home Page'!$G$2:$G$800="HTML/CSS") * (('Home Page'!$Q$2:$Q$800="Open") + ('Home Page'!$Q$2:$Q$800="Reopened")) * ('Home Page'!$T$2:$T$800="Fixed") * (ISNUMBER(SEARCH('Home Page'!$C$2:$C$800, $E$2))))} -> 2 | J17: {=SUMPRODUCT(('Home Page'!$G$2:$G$800="HTML/CSS") * (('Home Page'!$Q$2:$Q$800="Open") + ('Home Page'!$Q$2:$Q$800="Reopened")) * (('Home Page'!$T$2:$T$800="Reopen") + ('Home Page'!$T$2:$T$800="Pending")) * (ISNUMBER(SEARCH('Home Page'!$C$2:$C$800, $E$2))))} -> 0 | K17: v50
C18: Product | D18: {=SUMPRODUCT(('Product Details Page'!$G$2:$G$800="HTML/CSS") * ('Product Details Page'!$A$2:$A$800<>"") * (ISNUMBER(SEARCH('Product Details Page'!$C$2:$C$800, $E$2)))) + SUMPRODUCT(('Credit Card Pages'!$F$2:$F$800="HTML/CSS") * ('Credit Card Pages'!$A$2:$A$800<>"") * (ISNUMBER(SEARCH('Credit Card Pages'!$C$2:$C$800, $E$2))))} -> 54 | E18: {=SUMPRODUCT(('Product Details Page'!$G$2:$G$800="HTML/CSS") * ('Product Details Page'!$Q$2:$Q$800="Resolved") * (ISNUMBER(SEARCH('Product Details Page'!$C$2:$C$800, $E$2)))) + SUMPRODUCT(('Credit Card Pages'!$F$2:$F$800="HTML/CSS") * ('Credit Card Pages'!$R$2:$R$800="Resolved") * (ISNUMBER(SEARCH('Credit Card Pages'!$C$2:$C$800, $E$2))))} -> 38 | F18: {=SUMPRODUCT(('Product Details Page'!$G$2:$G$800="HTML/CSS") * (('Product Details Page'!$Q$2:$Q$800="Open") + ('Product Details Page'!$Q$2:$Q$800="Reopened")) * (ISNUMBER(SEARCH('Product Details Page'!$C$2:$C$800, $E$2)))) + SUMPRODUCT(('Credit Card Pages'!$F$2:$F$800="HTML/CSS") * (('Credit Card Pages'!$R$2:$R$800="Open") + ('Credit Card Pages'!$R$2:$R$800="Reopened")) * (ISNUMBER(SEARCH('Credit Card Pages'!$C$2:$C$800, $E$2))))} -> 16 | G18: {=SUMPRODUCT(('Product Details Page'!$G$2:$G$800="HTML/CSS") * ('Product Details Page'!$Q$2:$Q$800="Hold") * (ISNUMBER(SEARCH('Product Details Page'!$C$2:$C$800, $E$2)))) + SUMPRODUCT(('Credit Card Pages'!$F$2:$F$800="HTML/CSS") * ('Credit Card Pages'!$R$2:$R$800="Hold") * (ISNUMBER(SEARCH('Credit Card Pages'!$C$2:$C$800, $E$2))))} -> 0 | I18: {=SUMPRODUCT(('Product Details Page'!$G$2:$G$800="HTML/CSS") * (('Product Details Page'!$Q$2:$Q$800="Open") + ('Product Details Page'!$Q$2:$Q$800="Reopened")) * ('Product Details Page'!$T$2:$T$800="Fixed") * (ISNUMBER(SEARCH('Product Details Page'!$C$2:$C$800, $E$2)))) + SUMPRODUCT(('Credit Card Pages'!$F$2:$F$800="HTML/CSS") * (('Credit Card Pages'!$R$2:$R$800="Open") + ('Credit Card Pages'!$R$2:$R$800="Reopened")) * ('Credit Card Pages'!$U$2:$U$800="Fixed") * (ISNUMBER(SEARCH('Credit Card Pages'!$C$2:$C$800, $E$2))))} -> 0 | J18: {=SUMPRODUCT(('Product Details Page'!$G$2:$G$800="HTML/CSS") * (('Product Details Page'!$Q$2:$Q$800="Open") + ('Product Details Page'!$Q$2:$Q$800="Reopened")) * (('Product Details Page'!$T$2:$T$800="Reopen") + ('Product Details Page'!$T$2:$T$800="Pending")) * (ISNUMBER(SEARCH('Product Details Page'!$C$2:$C$800, $E$2)))) + SUMPRODUCT(('Credit Card Pages'!$F$2:$F$800="HTML/CSS") * (('Credit Card Pages'!$R$2:$R$800="Open") + ('Credit Card Pages'!$R$2:$R$800="Reopened")) * (('Credit Card Pages'!$U$2:$U$800="Reopen") + ('Credit Card Pages'!$U$2:$U$800="Pending")) * (ISNUMBER(SEARCH('Credit Card Pages'!$C$2:$C$800, $E$2))))} -> 4 | K18: v50 - 1
C19: Catalogue | D19: {=SUMPRODUCT(('Catalogue Page'!$G$2:$G$800="HTML/CSS") * ('Catalogue Page'!$A$2:$A$800<>"") * (ISNUMBER(SEARCH('Catalogue Page'!$C$2:$C$800, $E$2))))} -> 50 | E19: {=SUMPRODUCT(('Catalogue Page'!$G$2:$G$800="HTML/CSS") * ('Catalogue Page'!$Q$2:$Q$800="Resolved") * (ISNUMBER(SEARCH('Catalogue Page'!$C$2:$C$800, $E$2))))} -> 26 | F19: {=SUMPRODUCT(('Catalogue Page'!$G$2:$G$800="HTML/CSS") * (('Catalogue Page'!$Q$2:$Q$800="Open") + ('Catalogue Page'!$Q$2:$Q$800="Reopened")) * (ISNUMBER(SEARCH('Catalogue Page'!$C$2:$C$800, $E$2))))} -> 24 | G19: {=SUMPRODUCT(('Catalogue Page'!$G$2:$G$800="HTML/CSS") * ('Catalogue Page'!$Q$2:$Q$800="Hold") * (ISNUMBER(SEARCH('Catalogue Page'!$C$2:$C$800, $E$2))))} -> 0 | I19: {=SUMPRODUCT(('Catalogue Page'!$G$2:$G$800="HTML/CSS") * (('Catalogue Page'!$Q$2:$Q$800="Open") + ('Catalogue Page'!$Q$2:$Q$800="Reopened")) * ('Catalogue Page'!$T$2:$T$800="Fixed") * (ISNUMBER(SEARCH('Catalogue Page'!$C$2:$C$800, $E$2))))} -> 2 | J19: {=SUMPRODUCT(('Catalogue Page'!$G$2:$G$800="HTML/CSS") * (('Catalogue Page'!$Q$2:$Q$800="Open") + ('Catalogue Page'!$Q$2:$Q$800="Reopened")) * (('Catalogue Page'!$T$2:$T$800="Reopen") + ('Catalogue Page'!$T$2:$T$800="Pending")) * (ISNUMBER(SEARCH('Catalogue Page'!$C$2:$C$800, $E$2))))} -> 12 | K19: sbi_card_catalogue-fixes-for-UAT
C20: Header - Footer | D20: {=SUMPRODUCT(('Header & Footer'!$F$2:$F$800="HTML/CSS") * ('Header & Footer'!$A$2:$A$800<>"") * (ISNUMBER(SEARCH('Header & Footer'!$C$2:$C$800, $E$2))))} -> 25 | E20: {=SUMPRODUCT(('Header & Footer'!$F$2:$F$799="HTML/CSS") * ('Header & Footer'!$R$2:$R$799="Resolved") * (ISNUMBER(SEARCH('Header & Footer'!$C$2:$C$799, $E$2))))} -> 10 | F20: {=SUMPRODUCT(('Header & Footer'!$F$2:$F$799="HTML/CSS") * (('Header & Footer'!$R$2:$R$799="Open") + ('Header & Footer'!$R$2:$R$799="Reopened")) * (ISNUMBER(SEARCH('Header & Footer'!$C$2:$C$799, $E$2))))} -> 15 | G20: {=SUMPRODUCT(('Header & Footer'!$F$2:$F$799="HTML/CSS") * ('Header & Footer'!$R$2:$R$799="Hold") * (ISNUMBER(SEARCH('Header & Footer'!$C$2:$C$799, $E$2))))} -> 0 | I20: {=SUMPRODUCT(('Header & Footer'!$F$2:$F$799="HTML/CSS") * (('Header & Footer'!$R$2:$R$799="Open") + ('Header & Footer'!$R$2:$R$799="Reopened")) * ('Header & Footer'!$U$2:$U$799="Fixed") * (ISNUMBER(SEARCH('Header & Footer'!$C$2:$C$799, $E$2))))} -> 0 | J20: {=SUMPRODUCT(('Header & Footer'!$F$2:$F$799="HTML/CSS") * (('Header & Footer'!$R$2:$R$799="Open") + ('Header & Footer'!$R$2:$R$799="Reopened")) * (('Header & Footer'!$U$2:$U$799="Reopen") + ('Header & Footer'!$U$2:$U$799="Pending")) * (ISNUMBER(SEARCH('Header & Footer'!$C$2:$C$799, $E$2))))} -> 9 | K20: v50 - 2
C21: Total | D21: =SUM(D17:D20) -> 141 | E21: =SUM(E17:E20) -> 81 | F21: =SUM(F17:F20) -> 59 | G21: =SUM(G17:G20) -> 1 | I21: =SUM(I17:I20) -> 4 | J21: =SUM(J17:J20) -> 25
C23: Grand Total | D23: =SUM(D9,D15,D21) -> 729 | E23: =SUM(E9,E15,E21) -> 476 | F23: =SUM(F9,F15,F21) -> 190 | G23: =SUM(G9,G15,G21) -> 63

Sheet URLS
A1: Sr No. | B1: Page | C1: PVT URLs | D1: Category | E1: Theme | F1: E-Apply | G1: Network Privileges | H1: UAT URL | I1: devsit URL Received on | J1: Content Testing | K1: Link Redirections | L1: Similar Card | M1: Product Videos | N1: Creatives Testing | O1: End to End Testing | P1: Remarks
A2: 1 | B2: Home Page | C2: https://sbi-pvt.sbicard.com/html/en/home.html | D2: - | E2: - | F2: - | H2: https://sbi-devsit1.sbicard.com/html/en/home.html | J2: Done | K2: Done | L2: - | M2: -
A3: 2 | B3: Product Details Page | D3: - | E3: - | F3: - | H3: https://sbi-devsit1.sbicard.com/html/en/reliancesbicard.html | I3: 24th Dec 2025 | J3: - | K3: - | L3: - | M3: -
A4: 3 | B4: Catalogue Page | C4: https://sbi-pvt.sbicard.com/en/personal/credit-cards.html | D4: - | E4: - | F4: - | H4: https://sbi-devsit1.sbicard.com/en/personal/credit-cards.html | I4: 14th Jan 2026 | J4: Done | K4: Done | L4: - | M4: - | P4: 06/02/2026 - The old pvt link https://sbi-pvt.sbicard.com/html/en/personal/credit-cards.html has been changed to the new catalogue page - https://sbi-pvt.sbicard.com/html/en/product-catalogue.html#featured 29/01/2026 - New link was shared on UAT Discussion call - https://sbi-devsit1.sbicard.com/html/en/personal/credit-cards.html#featured Need a confirmation whether to switch the old link with the new and start testing on the new one or to keep following the old one.
A5: 4 | B5: Tata Neu Plus SBI Card | C5: https://sbi-pvt.sbicard.com/html/en/personal/credit-cards/tata-neu-plus-sbi-card.html | D5: Lifestyle Card | E5: Light | F5: Yes | H5: https://sbi-devsit1.sbicard.com/html/en/personal/credit-cards/tata-neu-plus-sbi-card.html | I5: 17th Jan 2026 | J5: Done | K5: Done | L5: Done | M5: Done | N5: Done | P5: 06/02/2026 - Creative wise testing done op PVT
A6: 5 | B6: SBI Card Elite | C6: https://sbi-pvt.sbicard.com/html/en/personal/credit-cards/sbi-card-elite.html | D6: Lifestyle Card | E6: Dark + Gold ( Elite theme) | F6: Yes | G6: Yes(Mc/Rupay) | H6: https://sbi-devsit1.sbicard.com/html/en/personal/credit-cards/sbi-card-elite.html | I6: 17th Jan 2026 | L6: Done | N6: Done | P6: 06/02/2026 - Creative wise testing done op PVT
A7: 6 | B7: Cashback SBI Card | C7: https://sbi-pvt.sbicard.com/html/en/personal/credit-cards/cashback-sbi-card.html | D7: Reward Cards | E7: Light theme (Cashback theme) | F7: Yes | H7: https://sbi-devsit1.sbicard.com/html/en/personal/credit-cards/cashback-sbi-card.html | I7: 22nd Jan 2026 | L7: Done | N7: Done | P7: 06/02/2026 - Creative wise testing done on PVT
A8: 7 | B8: SBI Card Pulse | C8: https://sbi-pvt.sbicard.com/html/en/personal/credit-cards/sbi-card-pulse.html | D8: Lifestyle Card | E8: Dark (Pulse theme) | F8: Yes | H8: https://sbi-devsit1.sbicard.com/html/en/personal/credit-cards/sbi-card-pulse.html | I8: 17th Jan 2026 | L8: Done | N8: Done | P8: 06/02/2026 - Creative wise testing done op PVT
A9: 8 | B9: Air India SBI Signature Card | C9: https://sbi-pvt.sbicard.com/html/en/personal/credit-cards/air-india-sbi-signature-card.html | D9: Travel & Fuel Card | E9: Light | F9: No | H9: https://sbi-devsit1.sbicard.com/html/en/personal/credit-cards/air-india-sbi-signature-card.html | I9: 22nd Jan 2026 | L9: Done | N9: Done | P9: 06/02/2026 - Creative wise testing done on PVT
A10: 9 | B10: Air India SBI Platinum Card | C10: https://sbi-pvt.sbicard.com/html/en/personal/credit-cards/air-india-sbi-platinum-card.html | D10: Travel & Fuel Card | E10: Light | F10: No | H10: https://sbi-devsit1.sbicard.com/html/en/personal/credit-cards/air-india-sbi-platinum-card.html | I10: 22nd Jan 2026 | L10: Done | N10: Done | P10: 06/02/2026 - Creative wise testing done on PVT
A11: 10 | B11: Apollo SBI Card Select | C11: https://sbi-pvt.sbicard.com/html/en/personal/credit-cards/apollo-sbi-card-select.html | D11: Reward Cards | E11: Light | F11: Yes | H11: https://sbi-devsit1.sbicard.com/html/en/personal/credit-cards/apollo-sbi-card-select.html | I11: 22nd Jan 2026 | L11: Done | N11: Done | P11: 06/02/2026 - Creative wise testing done on PVT
A12: 11 | B12: Flipkart SBI Card | C12: https://sbi-pvt.sbicard.com/html/en/personal/credit-cards/flipkart-sbi-card.html | D12: Reward Cards | E12: Light | F12: Yes | H12: https://sbi-devsit1.sbicard.com/html/en/personal/credit-cards/flipkart-sbi-card.html | I12: 17th Jan 2026 | L12: Done | N12: Done | P12: 06/02/2026 - Creative wise testing done on PVT
A13: 12 | B13: Landmark Rewards SBI Card Select | C13: https://sbi-pvt.sbicard.com/html/en/personal/credit-cards/landmark-sbi-card-select.html | D13: Shopping Card | E13: Light | F13: Yes | H13: https://sbi-devsit1.sbicard.com/html/en/personal/credit-cards/landmark-sbi-card-select.html | I13: 17th Jan 2026 | L13: Done | N13: Done | P13: 06/02/2026 - Creative wise testing done on PVT 29/01/2026 - Chagned to New link shared on Discussion call - https://sbi-devsit1.sbicard.com/html/en/personal/credit-cards/landmark-sbi-card-select.html Old link was - https://sbi-devsit1.sbicard.com/html/en/personal/credit-cards/landmark-rewards-sbi-card-select.html
A14: 13 | B14: Landmark Rewards SBI Card | C14: https://sbi-pvt.sbicard.com/html/en/personal/credit-cards/landmark-sbi-card.html | D14: Shopping Card | E14: Light | F14: Yes | H14: https://sbi-devsit1.sbicard.com/html/en/personal/credit-cards/landmark-rewards-sbi-card.html | L14: Done | N14: Done | P14: 06/02/2026 - The PVT link is not working - https://www.loom.com/share/c46dfd9ce3264fa09bff27fd3737b6f9
A15: 14 | B15: Landmark SBI Card Prime | C15: https://sbi-pvt.sbicard.com/html/en/personal/credit-cards/landmark-sbi-card-prime.html | D15: Shopping Card | E15: Light | F15: Yes | H15: https://sbi-devsit1.sbicard.com/html/en/personal/credit-cards/landmark-sbi-card-prime.html | L15: Done | N15: Done | P15: 06/02/2026 - Creative wise testing done on PVT
A16: 15 | B16: Etihad Guest SBI Card | C16: https://sbi-pvt.sbicard.com/html/en/personal/credit-cards/etihad-guest-sbi-card.html | D16: Travel & Fuel Card | E16: Light | F16: No | G16: Yes(Mc/Rupay) | H16: https://sbi-devsit1.sbicard.com/html/en/personal/credit-cards/etihad-guest-sbi-card.html | I16: 22nd Jan 2026 | L16: Done | N16: Done | P16: 06/02/2026 - Creative wise testing done on PVT
A17: 16 | B17: Doctors SBI Card | C17: https://sbi-pvt.sbicard.com/html/en/personal/credit-cards/doctors-sbi-card.html | D17: Lifestyle Card | E17: Light | F17: No | H17: https://sbi-devsit1.sbicard.com/html/en/personal/credit-cards/doctors-sbi-card.html | I17: 17th Jan 2026 | L17: Done | N17: Done | P17: 06/02/2026 - Creative wise testing done op PVT
A18: 17 | B18: BPCL SBI Card | C18: https://sbi-pvt.sbicard.com/html/en/personal/credit-cards/bpcl-sbi-card.html | D18: Travel & Fuel Card | E18: Dark | F18: Yes | H18: https://sbi-devsit1.sbicard.com/html/en/personal/credit-cards/bpcl-sbi-card.html | I18: 22nd Jan 2026 | L18: Done | N18: Done | P18: 06/02/2026 - Creative wise testing done on PVT
A19: 18 | B19: Etihad Guest SBI Premier Card | C19: https://sbi-pvt.sbicard.com/html/en/personal/credit-cards/etihad-guest-sbi-premier-card.html | D19: Travel & Fuel Card | E19: Dark | F19: No | G19: Yes(Mc/Rupay) | H19: https://sbi-devsit1.sbicard.com/html/en/personal/credit-cards/etihad-guest-sbi-premier-card.html | I19: 22nd Jan 2026 | L19: Done | N19: Done | P19: 06/02/2026 - Creative wise testing done on PVT
A20: 19 | B20: Doctors with IMA SBI Card | C20: https://sbi-pvt.sbicard.com/html/en/personal/credit-cards/doctors-ima-sbi-card.html | D20: Lifestyle Card | E20: Light | F20: No | H20: https://sbi-devsit1.sbicard.com/html/en/personal/credit-cards/doctors-ima-sbi-card.html | I20: 17th Jan 2026 | L20: Done | N20: Done | P20: 06/02/2026 - The PVT URL is not redirecting to the card page - https://www.loom.com/share/112cdc78107d4d928ebff913384b86b7 29/01/2026 - Chagned to New link shared on Discussion call - https://sbi-devsit1.sbicard.com/html/en/personal/credit-cards/doctors-ima-sbi-card.html Old link was - https://sbi-devsit1.sbicard.com/html/en/personal/credit-cards/doctors-with-ima-sbi-card.html
A21: 20 | B21: BPCL SBI Card Octane | C21: https://sbi-pvt.sbicard.com/html/en/personal/credit-cards/bpcl-sbi-card-octane.html | D21: Travel & Fuel Card | E21: Dark | F21: Yes | H21: https://sbi-devsit1.sbicard.com/html/en/personal/credit-cards/bpcl-sbi-card-octane.html | I21: 22nd Jan 2026 | L21: Done | N21: Done | P21: 06/02/2026 - Creative wise testing done on PVT
A22: 21 | B22: Club Vistara SBI Card | C22: https://sbi-pvt.sbicard.com/html/en/personal/credit-cards/club-vistara-sbi-card.html | D22: Travel & Fuel Card | E22: Light | F22: No | H22: https://sbi-devsit1.sbicard.com/html/en/personal/credit-cards/club-vistara-sbi-card.html | I22: 22nd Jan 2026 | L22: Done | N22: Done | P22: 06/02/2026 - Creative wise testing done on PVT
A23: 22 | B23: Apollo SBI Card | C23: https://sbi-pvt.sbicard.com/html/en/personal/credit-cards/apollo-sbi-card.html | D23: Reward Cards | E23: Light | F23: No | H23: https://sbi-devsit1.sbicard.com/html/en/personal/credit-cards/apollo-sbi-card.html | I23: 22nd Jan 2026 | L23: Done | N23: Done | P23: 06/02/2026 - Creative wise testing done on PVT
A24: 23 | B24: Club Vistara SBI Card Prime | C24: https://sbi-pvt.sbicard.com/html/en/personal/credit-cards/club-vistara-sbi-card-prime.html | D24: Travel & Fuel Card | E24: Light | F24: No | H24: https://sbi-devsit1.sbicard.com/html/en/personal/credit-cards/club-vistara-sbi-card-prime.html | I24: 22nd Jan 2026 | L24: Done | N24: Done | P24: 06/02/2026 - Creative wise testing done on PVT
A25: 24 | B25: IRCTC SBI Platinum Card | C25: https://sbi-pvt.sbicard.com/html/en/personal/credit-cards/irctc-sbi-platinum-card.html | D25: Travel & Fuel Card | E25: Light | F25: Yes | G25: Yes(Mc/Rupay) | H25: https://sbi-devsit1.sbicard.com/html/en/personal/credit-cards/irctc-sbi-platinum-card.html | L25: Done | N25: Done | P25: 06/02/2026 - Creative wise testing done on PVT
A26: 25 | B26: IRCTC Premier Card | C26: https://sbi-pvt.sbicard.com/html/en/personal/credit-cards/irctc-premier-card.html | D26: Travel & Fuel Card | E26: Light | F26: Yes | G26: Yes(Mc/Rupay) | H26: https://sbi-devsit1.sbicard.com/html/en/personal/credit-cards/irctc-premier-card.html | I26: 22nd Jan 2026 | L26: Done | N26: Done | P26: 06/02/2026 - Creative wise testing done on PVT
A27: 26 | B27: OLA Money SBI Card | C27: https://sbi-pvt.sbicard.com/html/en/personal/credit-cards/ola-money-sbi-card.html | D27: Reward Cards | E27: Light | F27: No | H27: https://sbi-devsit1.sbicard.com/html/en/personal/credit-cards/ola-money-sbi-card.html | L27: Done | N27: Done | P27: 06/02/2026 - Creative wise testing done on PVT
A28: 27 | B28: Krisflyer SBI Card | C28: https://sbi-pvt.sbicard.com/html/en/personal/credit-cards/krisflyer-sbi-card.html | D28: Travel & Fuel Card | E28: Light | F28: Yes | H28: https://sbi-devsit1.sbicard.com/html/en/personal/credit-cards/krisflyer-sbi-card.html | L28: Done | N28: Done | P28: 06/02/2026 - Creative wise testing done on PVT
A29: 28 | B29: Krisflyer SBI Card Apex | C29: https://sbi-pvt.sbicard.com/html/en/personal/credit-cards/krisflyer-sbi-card-apex.html | D29: Travel & Fuel Card | E29: Dark + Gold | F29: Yes | H29: https://sbi-devsit1.sbicard.com/html/en/personal/credit-cards/krisflyer-sbi-card-apex.html | L29: Done | N29: Done | P29: 06/02/2026 - Creative wise testing done on PVT
A30: 29 | B30: Tata Neu Infinity SBI Card | C30: https://sbi-pvt.sbicard.com/html/en/personal/credit-cards/tata-neu-infinity-sbi-card.html | D30: Lifestyle Card | E30: Light | F30: Yes | H30: https://sbi-devsit1.sbicard.com/html/en/personal/credit-cards/tata-neu-infinity-sbi-card.html | I30: 17th Jan 2026 | L30: Done | N30: Done | P30: 06/02/2026 - Creative wise testing done op PVT
A31: 30 | B31: PhonePe SBI Card Purple | C31: https://sbi-pvt.sbicard.com/html/en/personal/credit-cards/phonepe-sbi-card-purple.html | D31: Reward Cards | E31: Light | F31: No | H31: https://sbi-devsit1.sbicard.com/html/en/personal/credit-cards/phonepe-sbi-card-purple.html | I31: 17th Jan 2026 | L31: Done | N31: Done | P31: 06/02/2026 - Creative wise testing done on PVT
A32: 31 | B32: Paytm SBI Card Select | C32: https://sbi-pvt.sbicard.com/html/en/personal/credit-cards/paytm-sbi-card-select.html | D32: Reward Cards | E32: Dark + Gold | F32: No | H32: https://sbi-devsit1.sbicard.com/html/en/personal/credit-cards/paytm-sbi-card-select.html | I32: 22nd Jan 2026 | L32: Done | N32: Done | P32: 06/02/2026 - Creative wise testing done on PVT
A33: 32 | B33: SBI Card Miles Elite | C33: https://sbi-pvt.sbicard.com/html/en/personal/credit-cards/sbi-card-miles-elite.html | D33: Travel & Fuel Card | E33: Light (Miles Theme) | F33: Yes | H33: https://sbi-devsit1.sbicard.com/html/en/personal/credit-cards/sbi-card-miles-elite.html | L33: Done | N33: Done | P33: 06/02/2026 - Creative wise testing done on PVT
A34: 33 | B34: Indigo SBI Card Elite | C34: https://sbi-pvt.sbicard.com/html/en/personal/credit-cards/indigo-sbi-card-elite.html | D34: Travel & Fuel Card | E34: Light | F34: Yes | H34: https://sbi-devsit1.sbicard.com/html/en/personal/credit-cards/indigo-sbi-card-elite.html | I34: 22nd Jan 2026 | L34: Done | N34: Done | P34: 06/02/2026 - Creative wise testing done on PVT
A35: 34 | B35: Reliance SBI Card | C35: https://sbi-pvt.sbicard.com/html/en/personal/credit-cards/reliance-sbi-card.html | D35: Shopping Card | E35: Light | F35: Yes | G35: Yes(Mc/Rupay) | H35: https://sbi-devsit1.sbicard.com/html/en/personal/credit-cards/reliance-sbi-card.html | I35: 22nd Jan 2026 | L35: Done | N35: Done | P35: 06/02/2026 - Creative wise testing done on PVT
A36: 35 | B36: Indigo SBI Card | C36: https://sbi-pvt.sbicard.com/html/en/personal/credit-cards/indigo-sbi-card.html | D36: Travel & Fuel Card | E36: Light | F36: Yes | H36: https://sbi-devsit1.sbicard.com/html/en/personal/credit-cards/indigo-sbi-card.html | I36: 22nd Jan 2026 | L36: Done | N36: Done | P36: 06/02/2026 - Creative wise testing done on PVT
A37: 36 | B37: Reliance SBI Card Prime | C37: https://sbi-pvt.sbicard.com/html/en/personal/credit-cards/reliance-sbi-card-prime.html | D37: Shopping Card | E37: Dark | F37: Yes | G37: Yes(Mc/Rupay) | H37: https://sbi-devsit1.sbicard.com/html/en/personal/credit-cards/reliance-sbi-card-prime.html | I37: 22nd Jan 2026 | L37: Done | N37: Done | P37: 06/02/2026 - Creative wise testing done on PVT
A38: 37 | B38: PhonePe SBI Card Select Black | C38: https://sbi-pvt.sbicard.com/html/en/personal/credit-cards/phonepe-sbi-card-select-black.html | D38: Reward Cards | E38: Dark | F38: No | H38: https://sbi-devsit1.sbicard.com/html/en/personal/credit-cards/phonepe-sbi-card-select-black.html | I38: 17th Jan 2026 | L38: Done | N38: Done | P38: 06/02/2026 - Creative wise testing done on PVT
A39: 38 | B39: PayTM SBI Card | C39: https://sbi-pvt.sbicard.com/html/en/personal/credit-cards/paytm-sbi-card.html | D39: Reward Cards | E39: Light | F39: No | H39: https://sbi-devsit1.sbicard.com/html/en/personal/credit-cards/paytm-sbi-card.html | L39: Done | N39: Done | P39: 06/02/2026 - Creative wise testing done on PVT
A40: 39 | B40: SBI Card Prime | C40: https://sbi-pvt.sbicard.com/html/en/personal/credit-cards/sbi-card-prime.html | D40: Reward Cards | E40: Dark (Prime theme) | F40: Yes | G40: Yes(Mc/Rupay) | H40: https://sbi-devsit1.sbicard.com/html/en/personal/credit-cards/sbi-card-prime.html | I40: 17th Jan 2026 | L40: Done | N40: Done | P40: 06/02/2026 - Creative wise testing done on PVT
A41: 40 | B41: SBI Card Miles | C41: https://sbi-pvt.sbicard.com/html/en/personal/credit-cards/sbi-card-miles.html | D41: Travel & Fuel Card | E41: Light | F41: Yes | H41: https://sbi-devsit1.sbicard.com/html/en/personal/credit-cards/sbi-card-miles.html | I41: 17th Jan 2026 | L41: Done | N41: Done | P41: 06/02/2026 - Creative wise testing done on PVT
A42: 41 | B42: SBI Card Miles Prime | C42: https://sbi-pvt.sbicard.com/html/en/personal/credit-cards/sbi-card-miles-prime.html | D42: Travel & Fuel Card | E42: Light | F42: Yes | H42: https://sbi-devsit1.sbicard.com/html/en/personal/credit-cards/sbi-card-miles-prime.html | I42: 29th Jan 2026 | L42: Done | N42: Done | P42: 06/02/2026 - Creative wise testing done on PVT
A43: 42 | B43: SBI Card Unnati | C43: https://sbi-pvt.sbicard.com/html/en/personal/credit-cards/sbi-card-unnati.html | D43: Shopping Card | E43: Light | F43: No | H43: https://sbi-devsit1.sbicard.com/html/en/personal/credit-cards/sbi-card-unnati.html | I43: 29nd Jan 2026 | L43: Done | N43: Done | P43: 06/02/2026 - Creative wise testing done on PVT 29/01/2026 - Old link received on 22nd Jan was not functional, new functional link received on 29th Jan
A44: 43 | B44: Credit Card Page | C44: https://sbi-pvt.sbicard.com/en/personal/credit-cards.page | D44: Old Page | E44: - | F44: - | H44: https://sbi-devsit1.sbicard.com/en/personal/credit-cards.page | I44: 22nd Jan 2026
A45: 44 | B45: About Us Page | C45: https://sbi-pvt.sbicard.com/en/who-we-are/about-us.page | D45: Old Page | E45: - | F45: - | H45: https://sbi-devsit1.sbicard.com/en/who-we-are/about-us.page | I45: 22nd Jan 2026
A46: 45 | B46: ESG Page | C46: https://sbi-pvt.sbicard.com/en/who-we-are/esg.page | D46: Old Page | E46: - | F46: - | H46: https://sbi-devsit1.sbicard.com/en/who-we-are/esg.page | I46: 22nd Jan 2026
A47: 46 | B47: Do Not Disturb | C47: https://sbi-pvt.sbicard.com//en/do-not-disturb.page | D47: Old Page | E47: - | F47: - | H47: https://sbi-devsit1.sbicard.com//en/do-not-disturb.page | I47: 22nd Jan 2026
A48: 47 | B48: Benefits Page | C48: https://sbi-pvt.sbicard.com/en/personal/benefits.page | D48: Old Page | E48: - | F48: - | H48: https://sbi-devsit1.sbicard.com/en/personal/benefits.page | I48: 22nd Jan 2026
A49: 48 | B49: SimplyClick SBI Card | C49: https://sbi-pvt.sbicard.com/en/personal/credit-cards/simplyclick-sbi-card.html | D49: Shopping Card | E49: Light (SimplyClick Theme) | F49: Yes | I49: 3rd March 2026 | L49: Done | N49: Done
A50: 49 | B50: SimplySave SBI Card | C50: https://sbi-pvt.sbicard.com/en/personal/credit-cards/simplysave-sbi-card.html | D50: Shopping Card | E50: Light (SimplyClick Theme) | F50: Yes | I50: 3rd March 2026 | L50: Done | N50: Done
A51: 50 | B51: Titan SBI Card | C51: https://sbi-pvt.sbicard.com/en/personal/credit-cards/titan-sbi-card.html | D51: Shopping Card | E51: Light | F51: Yes | I51: 3rd March 2026 | L51: Done | N51: Done
A52: 51 | B52: Shaurya SBI Card | C52: https://sbi-pvt.sbicard.com/en/personal/credit-cards/shaurya-sbi-card.html | D52: Shopping Card | E52: Light | F52: No | I52: 3rd March 2026 | L52: Done | N52: Done
A53: 52 | B53: Shaurya Select SBI Card | C53: https://sbi-pvt.sbicard.com/en/personal/credit-cards/shaurya-select-sbi-card.html | D53: Shopping Card | E53: Light | F53: No | I53: 3rd March 2026 | L53: Done | N53: Done
A54: 53 | B54: BOM SBI Card Elite | C54: https://sbi-pvt.sbicard.com/en/personal/credit-cards/bom-sbi-card-elite.html | D54: Banking & Partnership | E54: Dark | F54: No | I54: 3rd March 2026
A55: 54 | B55: BOM SimplySave SBI Card | C55: https://sbi-pvt.sbicard.com/en/personal/credit-cards/bom-simplysave-sbi-card.html | D55: Banking & Partnership | E55: Light | F55: No | I55: 3rd March 2026
A56: 55 | B56: BOM SBI Card Prime | C56: https://sbi-pvt.sbicard.com/en/personal/credit-cards/bom-sbi-card-prime.html | D56: Banking & Partnership | E56: Dark | F56: No | I56: 3rd March 2026
A57: 56 | B57: PSB SBI Card Elite | C57: https://sbi-pvt.sbicard.com/en/personal/credit-cards/psb-sbi-card-elite.html | D57: Banking & Partnership | E57: Dark | F57: No | I57: 3rd March 2026
A58: 57 | B58: PSB SBI Card Prime | C58: https://sbi-pvt.sbicard.com/en/personal/credit-cards/psb-sbi-card-prime.html | D58: Banking & Partnership | E58: Dark | F58: No | I58: 3rd March 2026
A59: 58 | B59: PSB SimplySave SBI Card | C59: https://sbi-pvt.sbicard.com/en/personal/credit-cards/psb-simplysave-sbi-card.html | D59: Banking & Partnership | E59: Light | F59: No | I59: 3rd March 2026
A60: 59 | B60: UCO Bank SBI Card Elite | C60: https://sbi-pvt.sbicard.com/en/personal/credit-cards/uco-bank-sbi-card-elite.html | D60: Banking & Partnership | E60: Dark | F60: No | I60: 3rd March 2026
A61: 60 | B61: UCO Bank SBI Card Prime | C61: https://sbi-pvt.sbicard.com/en/personal/credit-cards/uco-bank-sbi-card-prime.html | D61: Banking & Partnership | E61: Dark | F61: No | I61: 3rd March 2026
A62: 61 | B62: UCO Bank SimplySave SBI Card | C62: https://sbi-pvt.sbicard.com/en/personal/credit-cards/uco-bank-simplysave-sbi-card.html | D62: Banking & Partnership | E62: Light | F62: No | I62: 3rd March 2026
A63: 62 | B63: Central Bank of India Elite Card | C63: https://sbi-pvt.sbicard.com/en/personal/credit-cards/central-bank-of-india-elite-card.html | D63: Banking & Partnership | E63: Dark | F63: No | I63: 3rd March 2026
A64: 63 | B64: Central Bank of India Prime Card | C64: https://sbi-pvt.sbicard.com/en/personal/credit-cards/central-bank-of-india-prime-card.html | D64: Banking & Partnership | E64: Dark | F64: No | I64: 3rd March 2026
A65: 64 | B65: Central Bank of India SimplySave SBI Card | C65: https://sbi-pvt.sbicard.com/en/personal/credit-cards/central-bank-of-india-simplysave-sbi-card.html | D65: Banking & Partnership | E65: Light | F65: No | I65: 3rd March 2026
... A78: 77 | B78: Karur Vysya Bank SBI Platinum Credit Card | C78: https://sbi-pvt.sbicard.com/en/personal/credit-cards/karur-vysya-bank-sbi-platinum-credit-card.html | D78: Banking & Partnership | E78: Dark | F78: No | I78: 3rd March 2026

Sheet Old Pages
A1: Sr No. | B1: Received on | C1: Page | D1: URLs | E1: Skip or Test | F1: Testing Status | G1: Last Updated On | H1: QA Remark
A2: 1 | B2: 46145 | D2: https://sbi-devsit1.sbicard.com/en/security.page | E2: To be Tested
A3: 2 | B3: 46145 | D3: https://sbi-devsit1.sbicard.com/en/eapply.page | E3: To be Tested
A4: 3 | B4: 46145 | D4: https://sbi-devsit1.sbicard.com/en/most-important-terms-and-conditions.page | E4: To be Tested
A5: 4 | B5: 46145 | D5: https://sbi-devsit1.sbicard.com/en/personal/benefits/encash.page | E5: To be Tested
A6: 5 | B6: 46145 | D6: https:///sbi-devsit1.sbicard.com/en/tokenisation.page | E6: To be Tested
A7: 6 | B7: 46145 | D7: https:///sbi-devsit1.sbicard.com/en/personal/benefits/add-on-card.page | E7: Skip
A8: 7 | B8: 46145 | D8: https:///sbi-devsit1.sbicard.com/en/contact-us/personal.page | E8: Skip
A9: 8 | B9: 46145 | D9: https:///sbi-devsit1.sbicard.com/en/personal/credit-cards/simplyfier.page | E9: Skip
A10: 9 | B10: 46145 | D10: https://sbi-devsit1.sbicard.com/en/faq/flexipay.page | E10: To be Tested
A11: 10 | B11: 46145 | D11: https://sbi-devsit1.sbicard.com/en/faq/kyc-norms.page | E11: To be Tested
A12: 11 | B12: 46145 | D12: https://sbi-devsit1.sbicard.com/en/faq/add-on-card.page | E12: Skip
A13: 12 | B13: 46145 | D13: https://sbi-devsit1.sbicard.com/en/tataneu-eapply.page | E13: Skip
... A132: 131 | B132: 46145 | D132: https://sbi-devsit1.sbicard.com/en/personal/offers.page | E132: Skip
D133: All individual Offer pages
A134: 132 | B134: 46145 | D134: https://sbi-devsit1.sbicard.com/en/home.page | E134: To be Tested
A135: 133 | B135: 46145 | D135: https://sbi-devsit1.sbicard.com/en/personal/visa-offers.page | E135: Skip
A136: 134 | B136: 46145 | D136: https://sbi-devsit1.sbicard.com/en/privacy-policy.page | E136: Skip
A137: 135 | B137: 46145 | D137: https://sbi-devsit1.sbicard.com/en/do-not-disturb.page | E137: Skip
A138: 136 | B138: 46145 | D138: https://sbi-devsit1.sbicard.com/en/cardholder-agreement.page | E138: Skip
A139: 137 | B139: 46145 | D139: https://sbi-devsit1.sbicard.com/en/faq.page | E139: Skip
A140: 138 | B140: 46145 | D140: https://sbi-devsit1.sbicard.com/en/blog/home.page | E140: Skip
A141: 139 | B141: 46145 | D141: https://sbi-devsit1.sbicard.com/en/personal/pay.page | E141: To be Tested
A142: 140 | B142: 46145 | D142: https://sbi-devsit1.sbicard.com/en/personal/credit-cards/compare-cards.page | E142: Skip
A143: 141 | B143: 46145 | D143: https://sbi-devsit1.sbicard.com/en/personal/credit-cards.page | E143: Skip
A144: 142 | B144: 46145 | D144: https://sbi-devsit1.sbicard.com/en/disclaimer.page | E144: Skip
A145: 143 | B145: 46145 | D145: https://sbi-devsit1.sbicard.com/en/offer-terms-conditions.page | E145: Skip
... A149: 147 | B149: 46145 | D149: https://sbi-devsit1.sbicard.com/en/personal/rewards.page | E149: Skip
D150: Also, all individual Rewards pages
A151: 148 | B151: 46145 | D151: https://sbi-devsit1.sbicard.com/en/personal/benefits/card-upgrade.page | E151: To be Tested
A152: 149 | B152: 46145 | D152: https://sbi-devsit1.sbicard.com/en/personal/benefits/money-simplified/atm-cash.page | E152: Skip
A153: 150 | B153: 46145 | D153: https://sbi-devsit1.sbicard.com/en/personal/benefits/utility-bill-payments/visa-bill.page | E153: Skip
A154: 151 | B154: 46145 | D154: https://sbi-devsit1.sbicard.com/en/personal/benefits/utility-bill-payments/auto-bill-pay.page | E154: Skip
A155: 152 | B155: 46145 | D155: https://sbi-devsit1.sbicard.com/en/personal/benefits/utility-bill-payments/pay-fast.page | E155: Skip
A156: 153 | B156: 46145 | D156: https://sbi-devsit1.sbicard.com/en/personal/benefits/easy-access-channels/simply-sms.page | E156: Skip
A157: 154 | B157: 46145 | D157: https://sbi-devsit1.sbicard.com/en/personal/benefits/easy-access-channels/yono.page | E157: Skip
A158: 155 | B158: 46145 | D158: https://sbi-devsit1.sbicard.com/en/personal/benefits/easy-access-channels/missed-call-service.page | E158: Skip
A159: 156 | B159: 46145 | D159: https://sbi-devsit1.sbicard.com/en/personal/benefits/utility-bill-payments/recurring-e-mandates.page | E159: To be Tested
A160: 157 | B160: 46145 | D160: https://sbi-devsit1.sbicard.com/en/personal/benefits/utility-bill-payments/register-and-pay.page | E160: To be Tested
A161: 158 | B161: 46145 | D161: https://sbi-devsit1.sbicard.com/en/personal/benefits/easy-access-channels/chatbot.page | E161: Skip
A162: 159 | B162: 46145 | D162: https://sbi-devsit1.sbicard.com/en/personal/benefits/easy-access-channels/website.page | E162: Skip
... A173: 170 | B173: 46145 | D173: https://sbi-devsit1.sbicard.com/en/personal/benefits/digital-payments/bharat-qr-pay.page | E173: To be Tested
A174: 171 | B174: 46145 | D174: https://sbi-devsit1.sbicard.com/en/personal/rewards/reward-detail.page
A175: 172 | B175: 46145 | D175: https://sbi-devsit1.sbicard.com/en/personal/linking-of-pan-with-aadhaar.page
A176: 173 | B176: 46145 | D176: https://sbi-devsit1.sbicard.com/en/unclaimed-credit-balance.page
A177: 174 | B177: 46145 | D177: https://sbi-devsit1.sbicard.com/en/personal/rewards/reward-reward-detail.page
A178: 175 | B178: 46145 | D178: https://sbi-devsit1.sbicard.com/en/merchant-e-mandate-list.page
A179: 176 | B179: 46145 | D179: https://sbi-devsit1.sbicard.com/en/calculator/irctc/irctc-calculator.page
A180: 177 | B180: 46145 | D180: https://sbi-devsit1.sbicard.com/en/address-change-kyc.page
A181: 178 | B181: 46145 | D181: https://sbi-devsit1.sbicard.com/en/resolution-framework-2-0-policy.page
A182: 179 | B182: 46145 | D182: https://sbi-devsit1.sbicard.com/en/kyc-renewal.page
A183: 180 | B183: 46145 | D183: https://sbi-devsit1.sbicard.com/en/personal/benefits/easy-access-channels/whatsapp.page | E183: To be Tested

Sheet ExclusivePrivileges TextOverlap
A1: Page | B1: Card Face | C1: Privileges | D1: Font Size | E1: SBI Team Remark | F1: Status | G1: Last Tested on | H1: QA Remark
A2: Tata Neu Plus SBI Card | B2: Front | C2: Reward Benefit | D2: Large | F2: Resolved | G2: 46056
A3: Air India SBI Signature Card | B3: Front | C3: Milestone Benefits | D3: Default | F3: Resolved | G3: 46056
A4: Air India SBI Signature Card | B4: Back | C4: Milestone Benefits | D4: Large | F4: Resolved | G4: 46056
A5: Air India SBI Signature Card | B5: Front | C5: Reward Benefits, Milestone Benefits | D5: Large | E5: In reward benefit, we change the order of the points second point we will shift it to 3rd and 3rd to second | F5: Unresolved | G5: 22/02/2026 | H5: 22/02/2026 - We cannot change the order of the bullet points
A6: Air India SBI Platinum Card | B6: Front | C6: Reward Benefits, Milestone Benefits | D6: Large | E6: fuelcharge and welcome benefit also create problem I fixed it | F6: Resolved | G6: 46056
A7: Air India SBI Platinum Card | B7: Back | C7: Reward Benefits | D7: Large | F7: Unresolved | G7: 22/02/2026
A8: Landmark Rewards SBI Card | B8: Front | C8: Reward Benefits | D8: Large | F8: Unresolved | G8: 22/02/2026
A9: Landmark Rewards SBI Card Prime | B9: Front | C9: Reward Benefits | D9: Large | F9: Resolved | G9: 46056
A10: Etihad Guest SBI Card | B10: Front | C10: Reward Benefits | D10: Large | F10: Resolved | G10: 46056
A11: Doctor's SBI Card | B11: Front | C11: Reward Points | D11: Default | F11: Resolved | G11: 46056
A12: Doctor's SBI Card | B12: Front | C12: Reward Points | D12: Large | F12: Unresolved | G12: 22/02/2026
A13: BPCL SBI Card | B13: Front | C13: Reward Benefits | D13: Default | F13: Resolved | G13: 46056
A14: BPCL SBI Card | B14: Front | C14: Reward Benefits | D14: Large | F14: Resolved | G14: 46056
A15: BPCL SBI Card OCTANE | B15: Front | C15: Reward Benefits, Fuel Surcharge Waiver | D15: Large | E15: welcome benefit also create issue , I fixed it | F15: Resolved | G15: 46056
A16: Club Vistara SBI Card | B16: Back | C16: Reward Benefits | D16: Large | F16: Unresolved | G16: 22/02/2026
A17: Club Vistara SBI Card | B17: Front | C17: Milestone Benefits | D17: Large | E17: Shuffle the points 3-1st, 2nd- 2ndrd, 1st -3rd | F17: Unresolved | G17: 22/02/2026 | H17: 22/02/2026 - We cannot change the order of the bullet points
A18: Club Vistara SBI Card | B18: Front | C18: Domestic Lounge Benefits | D18: Default | F18: Resolved | G18: 46056
A19: Club Vistara SBI Card | B19: Back | C19: Domestic Lounge Benefits | D19: Large | F19: Resolved | G19: 46056
A20: Club Vistara SBI Card | B20: Front | C20: Domestic Lounge Benefits | D20: Large | F20: Resolved | G20: 46056
A21: Club Vistara SBI Card | B21: Front | C21: Complimentary Priority Pass Membership | D21: Default | F21: Resolved | G21: 46056
A22: Club Vistara SBI Card | B22: Front | C22: Complimentary Priority Pass Membership | D22: Large | E22: content need to be customized | F22: Unresolved | G22: 46359 | H22: 12/03/2026 - As discussed with Namita ma'am, thecontent of the bullet point at the back of this card should be updated to - "Standard membership of Priority Pass Program is complimentary for 24 months. Usage fee of $27 + applicable taxes will be charged on your Credit Card for visit to the Priority Pass Membership Lounge"
A23: Apollo SBI Card | B23: Back | C23: Welcome Benefits | D23: Default | F23: Resolved | G23: 46056
A24: Club Vistara SBI Card Prime | B24: Front | C24: Milestone Benefits | D24: Default | E24: content need to be customized | F24: Resolved | G24: 13/03/2026 | H24: 13/03/2026 - The issue is resolved on sbi-pvt - https://loom.com/i/a30776291da44dc4b3dc870eb1735cd3
A25: Club Vistara SBI Card Prime | B25: Front | C25: Milestone Benefits | D25: Large | F25: Unresolved | G25: 22/02/2026
A26: Club Vistara SBI Card Prime | B26: Front | C26: Complimentary Priority Pass Membership | D26: Large | E26: Comprehensive car cover was also has some issue , fixed it | F26: Resolved | G26: 46056
A27: IRCTC SBI Platinum Card | B27: Front | C27: Welcome Benefits | D27: Default | F27: Resolved | G27: 46056
A28: IRCTC SBI Platinum Card | B28: Front | C28: Welcome Benefits | D28: Large | F28: Resolved | G28: 46056
A29: IRCTC SBI Platinum Card | B29: Back | C29: Travel Offers from IRCTC | D29: Small | F29: Resolved | G29: 46056
A30: IRCTC SBI Platinum Card | B30: Back | C30: Travel Offers from IRCTC | D30: Default | E30: Content is not same aslo change every tiles not just two | F30: Resolved | G30: 46056
A31: IRCTC SBI Platinum Card | B31: Back | C31: Travel Offers from IRCTC | D31: Large | F31: Unresolved | G31: 22/02/2026
A32: IRCTC SBI Premier | B32: Front | C32: Value Back Benefits | D32: Large | F32: Resolved | G32: 46056
A33: IRCTC SBI Premier | B33: Front | C33: Reward Benefits | D33: Default | F33: Resolved | G33: 46056
A34: IRCTC SBI Premier | B34: Front | C34: Reward Benefits | D34: Large | E34: fuel surcharge waiver was also creating issue, I fixed it | F34: Unresolved | G34: 22/02/2026
A35: KrisFlyer SBI Card APEX | B35: Front | C35: Milestone Benefits | D35: Large | E35: welcome, lounge and fuewlcharge also corrected Also, made 1st point to 3rd in milestone | F35: Unresolved | G35: 22/02/2026
A36: TATA NEU INFINITY SBI CARD | B36: Front | C36: Reward Benefits | D36: Large | F36: Resolved | G36: 46056
A37: PhonePe SBI Card PURPLE | B37: Front | C37: PhonePe Rewards | D37: Large | F37: Resolved | G37: 46056
A38: SBI Card Miles Elite | B38: No Accessibility Bar | C38: No Accessibility Bar | D38: No Accessibility Bar | F38: Resolved | G38: 46056
A39: INDIGO SBI CARD ELITE | B39: Front | C39: Welcome Benefits | D39: Large | E39: welcome, renewal, domestic and insurance also corrected | F39: Resolved | G39: 46056
A40: Reliance SBI Card | B40: Front | C40: Reward Benefits | D40: Large | F40: Resolved | G40: 46056
A41: Indigo SBI Card | B41: Front | C41: Fuel Surcharge Waiver | D41: Large | F41: Resolved | G41: 46056
A42: Reliance SBI Card Prime | B42: Front | C42: Reward Benefits | D42: Large | F42: Resolved | G42: 46056
A43: PHONEPE SBI CARD SELECT BLACK | B43: Front | C43: PhonePe Rewards | D43: Large | F43: Resolved | G43: 46056
A44: Paytm SBI Card | B44: Front | C44: Smart Card Control | D44: Large | E44: cashback also creating issue , fixed it | F44: Resolved | G44: 46056
A45: SBI Card Prime | B45: Front | C45: Prime Rewards | D45: Large | F45: Resolved | G45: 46056
A46: SBI Card Prime | B46: Front | C46: Milestone Benefits | D46: Large | E46: lounge was also creating issue, I fixed it | F46: Resolved | G46: 46056
A47: SBI CARD MILES | B47: Front | C47: Miles Rewards | D47: Large | F47: Resolved | G47: 46056
A48: SBI CARD MILES | B48: Back | C48: Miles Rewards | D48: Large | F48: Resolved | G48: 46056
A49: SBI CARD MILES | B49: Front | C49: International Travel Privileges | D49: Large | F49: Resolved | G49: 46056
A50: Tata Neu SBI Card Plus | B50: Front | C50: Welcome Benefits | D50: Large | F50: Resolved | G50: 46268
A51: Tata Neu SBI Card Plus | B51: Front | C51: Fuel Surcharge Waiver | D51: Large | F51: Resolved | G51: 46268
A52: Air India SBI Signature Card | B52: Front | C52: Welcome Benefits | D52: Large | F52: Resolved | G52: 46268
A53: Air India SBI Signature Card | B53: Back | C53: Welcome Benefits | D53: Default | F53: Unresolved | G53: 22/02/2026 | H53: 11/03/2026 - The issue is still not resolved in default font size - https://www.loom.com/i/c18c31d410dd4c17878a840679d01f08
A54: Air India SBI Signature Card | B54: Back | C54: Welcome Benefits | D54: Large | F54: Unresolved | G54: 22/02/2026
A55: Air India SBI Signature Card | B55: Back | C55: Reward Benefits | D55: Large | F55: Resolved | G55: 46268
A56: Air India SBI Signature Card | B56: Front | C56: Lounge Benefits | D56: Large | F56: Resolved | G56: 46268
A57: Air India SBI Signature Card | B57: Back | C57: Lounge Benefits | D57: Large | F57: Unresolved | G57: 22/02/2026
A58: Air India SBI Signature Card | B58: Front | C58: Fuel Surcharge Waiver | D58: Large | F58: Resolved | G58: 46268
A59: Air India SBI Platinum Card | B59: Front | C59: Welcome Benefits | D59: Large | F59: Resolved | G59: 46268
A60: Landmard Rewards SBI Card | B60: Front | C60: Fuel Surcharge Waiver | D60: Large | F60: Resolved | G60: 46268
A61: Etihad Guest SBI Card | B61: Front | C61: Lounge Benefits | D61: Large | F61: Resolved | G61: 46268
A62: Doctor's SBI Card | B62: Front | C62: Intenational Lounge Program | D62: Large | F62: Resolved | G62: 46268
A63: Doctor's SBI Card | B63: Front | C63: Domestic Lounge Program | D63: Large | F63: Resolved | G63: 46268
A64: Doctor's SBI Card | B64: Front | C64: Fuel Surcharge Waiver | D64: Large | F64: Resolved | G64: 46268
A65: BPCL SBI Card | B65: Front | C65: Value Back Benefits | D65: Large | F65: Resolved | G65: 46268
A66: BPCL SBI Card OCTANE | B66: Back | C66: Milestone Benefits | D66: Large | F66: Resolved | G66: 46268
A67: Club Vistara SBI Card | B67: Back | C67: Renewal Benefits | D67: Large | F67: Resolved | G67: 46268
A68: Club Vistara SBI Card | B68: Back | C68: Complimentary Priority Pass Membership | D68: Large | F68: Unresolved | G68: 22/02/2026
A69: Club Vistara SBI Card | B69: Back | C69: Milestone Benefits | D69: Large | F69: Resolved | G69: 46268
A70: Club Vistara SBI Card Prime | B70: Front | C70: Milestone Benefits | D70: Large | F70: Unresolved | G70: 22/02/2026
A71: Club Vistara SBI Card Prime | B71: Front | C71: Milestone Benefits | D71: Large | F71: Unresolved | G71: 22/02/2026
A72: Club Vistara SBI Card Prime | B72: Back | C72: Milestone Benefits | D72: Default | F72: Resolved | G72: 46268
A73: Club Vistara SBI Card Prime | B73: Back | C73: Milestone Benefits | D73: Large | F73: Resolved | G73: 46268
A74: IRCTC SBI Platinum Card | B74: Front | C74: Reward Benefits | D74: Large | F74: Resolved | G74: 46268
A75: TATA NEU INFINITY SBI CARD | B75: Front | C75: Welcome Benefits | D75: Large | F75: Resolved | G75: 46268
A76: TATA NEU INFINITY SBI CARD | B76: Front | C76: International Lounge Benefits | D76: Large | F76: Resolved | G76: 46268
A77: TATA NEU INFINITY SBI CARD | B77: Front | C77: Fuel Surcharge Waiver | D77: Large | F77: Resolved | G77: 46268
A78: PhonePe SBI Card PURPLE | B78: Front | C78: Fuel Surcharge Waiver | D78: Large | F78: Resolved | G78: 46268
A79: SBI Card Miles ELITE | B79: Front | C79: Insurance Cover | D79: Large | F79: Resolved | G79: 46268
A80: SBI Card Miles ELITE | B80: Back | C80: Reward Benefits | D80: Large | F80: Resolved | G80: 46268
A81: SBI Card Miles ELITE | B81: Back | C81: Milestone Benefits | D81: Large | F81: Resolved | G81: 46298
A82: SBI Card Miles ELITE | B82: Back | C82: International Travel Privileges | D82: Large | F82: Resolved | G82: 46268
A83: SBI Card Miles ELITE | B83: Back | C83: Insurance Cover | D83: Large | F83: Resolved | G83: 46268
... A86: INDIGO SBI CARD | B86: Front | C86: Renewal Benefits | D86: Large | F86: Resolved | G86: 46268
A87: INDIGO SBI CARD | B87: Front | C87: Domestic Lounge Benefits | D87: Large | F87: Unresolved | G87: 22/02/2026
A88: Reliance SBI Card PRIME | B88: Front | C88: International Lounge Benefits | D88: Large | F88: Resolved | G88: 46268
A89: Reliance SBI Card PRIME | B89: Front | C89: Fuel Surcharge Waiver | D89: Large | F89: Resolved | G89: 46268
A90: PHONEPE SBI CARD SELECT BLACK | B90: Front | C90: Fuel Surcharge Waiver | D90: Large | F90: Resolved | G90: 46268
A91: Paytm SBI Card | B91: Front | C91: Fuel Surcharge Waiver | D91: Large | F91: Resolved | G91: 46268
A92: SBI Card Miles | B92: Front | C92: Milestone Benefits | D92: Large | F92: Unresolved | G92: 22/02/2026
A93: SBI Card Miles | B93: Back | C93: International Travel Privileges | D93: Large | F93: Unresolved | G93: 22/02/2026
A94: SBI Card Elite | B94: Front | C94: Welcome Gift | D94: Large | F94: Resolved | G94: 46298
A95: SBI Card Elite | B95: Front | C95: Complementary Movie Ticket | D95: Large | F95: Resolved | G95: 46268
A96: SBI Card Elite | B96: Front | C96: International Lounge Program | D96: Large | F96: Resolved | G96: 46268
A97: SBI Card Elite | B97: Front | C97: Domestic Lounge Program | D97: Large | F97: Resolved | G97: 46268
A98: SBI Card Elite | B98: Front | C98: ITC Silver Tier Membership | D98: Large | F98: Resolved | G98: 46268
A99: SBI Card Elite | B99: Back | C99: Elite Rewards | D99: Large | F99: Resolved | G99: 46268
A100: SBI Card Elite | B100: Back | C100: International Lounge Program | D100: Large | F100: Resolved | G100: 46268
A101: Cashback SBI Card | B101: Front | C101: Fuel Surcharge Waiver | D101: Large | F101: Resolved | G101: 46268
A102: SBI Card Pulse | B102: Front | C102: Health Benefits | D102: Large | F102: Resolved | G102: 46268
...

Sheet Product Videos Test Cases
A1: Card Names | B1: Video Titles | C1: Expected Product Video URLs | D1: Actual Product Video URLs | E1: Video URLs | F1: Video Titles | G1: Video Thumbnails | H1: QA Remark
A2: SBI Card ELITE | B2: 1.) SBI Card Elite Features & Benefits 2.) Unwind in Luxury | SBI Card ELITE 3.) Live a rewarding life with SBI Card ELITE 4.) Comfort and Class in Travel Always | SBI Card ELITE 5.) Elevate your flying experience | SBI Card ELITE 6.) SBI Card Elite | Credit Card Benefits & Rewards | Premium Reward Card | C2: 1.) https://www.youtube.com/watch?v=SxuFU7C5Lxo 2.) https://www.youtube.com/watch?v=7gBHGP99YpU 3.) https://www.youtube.com/watch?v=e5mDpMcXMQs 4.) https://www.youtube.com/watch?v=KKDq1jPKqWM 5.) https://www.youtube.com/watch?v=QGXYDpw45mc 6.) https://www.youtube.com/watch?v=o30QyC6tuiY | D2: 1.) https://www.youtube.com/watch?v=SxuFU7C5Lxo 2.) https://www.youtube.com/watch?v=7gBHGP99YpU 3) https://www.youtube.com/watch?v=e5mDpMcXMQs 4.) https://www.youtube.com/watch?v=KKDq1jPKqWM 5.) https://www.youtube.com/watch?v=QGXYDpw45mc 6.) https://www.youtube.com/watch?v=o30QyC6tuiY | E2: Pass | F2: Pass | G2: Fail | H2: 13/03/2026 - The 4th video thumbnail is breaking the alignemnt - 10/03/2026 - 4th Video still has dummy thumbnail because it was not provided in the thumbnail file shared.
A3: SBI Card PULSE | B3: 1.) Move towards a Fitter You | SBI Card PULSE | C3: 1.) https://www.youtube.com/watch?v=VlUwJtMObJM | D3: 1.) https://www.youtube.com/watch?v=VlUwJtMObJM | E3: Pass | F3: Pass | G3: Pass
A4: Tata Neu Infinity SBI Card | B4: 1.) Welcome Benefit - TATA Neu Infinity SBI Credit Card 2.) Introducing the Tata Neu Infinity SBI Credit Card 3.) Introducing the Tata Neu Infinity SBI Credit Card | C4: 1.) https://www.youtube.com/shorts/9W-yd2nKbIY 2.) https://www.youtube.com/shorts/NFFdaffkdy8 3.) https://www.youtube.com/shorts/NFFdaffkdy8 | D4: 1.) https://www.youtube.com/shorts/9W-yd2nKbIY 2.) https://www.youtube.com/shorts/NFFdaffkdy8 3.) https://www.youtube.com/shorts/NFFdaffkdy8 | E4: Pass | F4: Pass | G4: Pass | H4: 17/03/2026 - The issue is now resolved - https://loom.com/i/aa7316864f084b18ab60190a9d619e2f 16/03/2026 - Thumbnails not yet added.
A5: Tata Neu Plus SBI Card | B5: No Videos Provided | C5: No URLs Provided | D5: - | E5: - | F5: - | G5: -
A6: Doctor's SBI Card (in association with IMA) | B6: 1.) Doctor's SBI Card | Credit Card Benefits & Rewards | SBI Doctors Credit Card 2.) Doctor's SBI Card | Credit Card Benefits & Rewards | SBI Card | C6: 1.) https://www.youtube.com/watch?v=8x2fWFLDk2k 2.) https://www.youtube.com/watch?v=FoZaQr9zHSY | D6: 1.) https://www.youtube.com/watch?v=8x2fWFLDk2k 2.) https://www.youtube.com/watch?v=FoZaQr9zHSY | E6: Pass | F6: Pass | G6: Pass
A7: Doctor's SBI Card | B7: 1.) Doctor's SBI Card | Credit Card Benefits & Rewards | SBI Card 2.) Doctor's SBI Card | Credit Card Benefits & Rewards | SBI Doctors Credit Card | C7: 1.) https://www.youtube.com/watch?v=FoZaQr9zHSY 2.) https://www.youtube.com/watch?v=8x2fWFLDk2k | D7: 1.) https://www.youtube.com/watch?v=FoZaQr9zHSY 2.) https://www.youtube.com/watch?v=8x2fWFLDk2k | E7: Pass | F7: Pass | G7: Pass | H7: 16/03/2026 - The 2nd video now has the thumbnail - https://loom.com/i/311c6cc84ff140c3a7e700314110826b 11/03/2026 - The 2nd Video still has dummy thumbnail - https://www.loom.com/i/eb436efa965e4c6888a21ca8dae571bf
A8: Aurum Card | B8: No Videos Provided | C8: No URLs Provided | D8: - | E8: - | F8: - | G8: -
A9: Flipkart SBI Card | B9: 1.) Flipkart SBI Card is here! 2.) Flipkart SBI Card is here! 3.) Earn 5% Cashback* on your bookings at Cleartrip with Flipkart SBI Credit Card 4.) Shop your favourite styles on Myntra | C9: 1.) https://www.youtube.com/watch?v=0oO5Uyk7B_I 2.) https://www.youtube.com/shorts/j5_DXAYfPic 3.) https://www.youtube.com/shorts/54MnmbjGibA 4.) https://www.youtube.com/shorts/5rK7lnm0qSw | D9: 1.) https://www.youtube.com/watch?v=0oO5Uyk7B_I 2.) https://www.youtube.com/shorts/j5_DXAYfPic 3.) https://www.youtube.com/shorts/54MnmbjGibA 4.) https://www.youtube.com/shorts/5rK7lnm0qSw | E9: Pass | F9: Pass | G9: Pass | H9: 16/03/2026 - The issue is resolved - https://loom.com/i/049a955950844128a2639c2602034b31 10/03/2026 - 3rd Video Title, the asterisk (*) is missing after the word "Cashback" it should be " Earn 5% Cashback* on your bookings" - https://www.loom.com/i/9bf4efb5917c48c9b979be59b143c672
A10: CASHBACK SBI Card | B10: 1.) #CashbackHarBaar with CASHBACK SBI Card | C10: 1.) https://www.youtube.com/watch?v=84yhgRGvJ2c | D10: 1.) https://www.youtube.com/watch?v=84yhgRGvJ2c | E10: Pass | F10: Pass | G10: Pass | H10: 10/03/2026 - The # was exclude because it was not looking appropriate.
A11: SBI Card PRIME | B11: 1.) Live the PRIME Life | SBI Card PRIME 2.) Celebrate milestones with SBI Card PRIME 3.) Make every birthday special | SBI Card PRIME 4.) Live the PRIME Life | SBI Card PRIME 5.) SBI Card PRIME | Credit Card Benefits & Rewards | SBI Reward Card | C11: 1.) https://www.youtube.com/watch?v=5EYmJfjFlUk 2.) https://www.youtube.com/watch?v=jw_Xvdki6vg 3.) https://www.youtube.com/watch?v=9gmlocZ5sF4 4.) https://www.youtube.com/watch?v=u5y_ktXNh_0 5.) https://www.youtube.com/watch?v=FKiazBp1GhQ | D11: 1.) https://www.youtube.com/watch?v=5EYmJfjFlUk 2.) https://www.youtube.com/watch?v=jw_Xvdki6vg 3.) https://www.youtube.com/watch?v=9gmlocZ5sF4 4.) https://www.youtube.com/watch?v=u5y_ktXNh_0 5.) https://www.youtube.com/watch?v=FKiazBp1GhQ | E11: Pass | F11: Pass | G11: Pass
A12: PhonePe SBI Card SELECT BLACK | B12: 1.) Introducing the PhonePe SBI Card 2.) Enjoy up to 10% Value Back as Reward Points on PhonePe spends 3.) Introducing the PhonePe SBI Card SELECT BLACK | C12: 1.) https://www.youtube.com/watch?v=LxXQmOqU5o4 2.) https://www.youtube.com/shorts/TqMJs7LPtyQ 3.) https://www.youtube.com/shorts/766bJ87bxU4 | D12: 1.) https://www.youtube.com/watch?v=LxXQmOqU5o4 2.) https://www.youtube.com/shorts/TqMJs7LPtyQ 3.) https://www.youtube.com/shorts/766bJ87bxU4 | E12: Pass | F12: Pass | G12: Pass | H12: 16/03/2026 - Issue resolved on sbi-pvt - https://loom.com/i/1a329d9ca4d1421093e35d0d157776c6 11/03/2026 - 2nd Video Title --> It should be "Enjoy up to 10%" instead of "Enjoy upto 10%".
A13: PhonePe SBI Card PURPLE | B13: 1.) Introducing the PhonePe SBI Card | C13: 1.) https:/www.youtube.com/watch?v=LxXQmOqU5o4 | D13: 1.) https://www.youtube.com/watch?v=LxXQmOqU5o4 | E13: Pass | F13: Pass | G13: Pass | H13: 16/03/2026 - Thumbnail uploaded - https://loom.com/i/cc4aba6ab66743e1b83a330df755ee40
A14: OLA Money SBI Card | B14: No Videos Provided | C14: No URLs Provided | D14: - | E14: - | F14: - | G14: -
A15: Apollo SBI Card SELECT | B15: 1.) Apollo SBI Card SELECT - up to 25% Value Back 2.) Apollo SBI Card SELECT - Welcome Benefit 3.) Apollo SBI Card SELECT is here! | C15: 1.)https://www.youtube.com/shorts/_qFyxMC_NJ4 2.)https://www.youtube.com/shorts/SC4fDNM7c7U 3.) https://www.youtube.com/shorts/R3NKC2IA7Bw | D15: 1.) https://www.youtube.com/shorts/_qFyxMC_NJ4 2.) https://www.youtube.com/shorts/SC4fDNM7c7U 3.) https://www.youtube.com/shorts/R3NKC2IA7Bw | E15: Pass | F15: Pass | G15: Pass | H15: 16/03/2026 - Thumbnail uploaded - https://loom.com/i/956063a325644803a924653c2cb2d91d
A16: Apollo SBI Card | B16: 1.) Apollo SBI Credit Card - Discover a world of health, Official Launch Event of Apollo SBI Card | C16: 1.) https:/www.youtube.com/watch?v=SmLKhe04oiA | D16: 1.) https://www.youtube.com/watch?v=SmLKhe04oiA | E16: Pass | F16: Pass | G16: Pass | H16: 16/03/2026 - Thumbnial uploaded - https://loom.com/i/2d629360633d403a91de0800804d2780
A17: Paytm SBI Card SELECT | B17: 1.) Make your Paytm spends rewarding with the Paytm SBI Card Select 2.) Make your Paytm spends rewarding with the Paytm SBI Card SELECT | C17: 1.) https://www.youtube.com/watch?v=a_4Bgh0WlZs 2.) https://www.youtube.com/watch?v=p6lzw95Sm1k | D17: 1.) https://www.youtube.com/watch?v=a_4Bgh0WlZs 2.) https://www.youtube.com/watch?v=p6lzw95Sm1k | E17: Pass | F17: Fail | G17: Fail | H17: 16/03/2026 - The 1st video thumbnail is breaking the alignment - https://www.loom.com/i/b6832df5e60b4a6285960d12f4748f7a Also, the capitalizations in the card name should be "Paytm SBI Card SELECT" in both the video titles.
A18: Paytm SBI Card | B18: 1.) Make your Paytm spends rewarding with the Paytm SBI Card | C18: 1.) https:/www.youtube.com/watch?v=cSntakowRMQ | D18: 1.) https://www.youtube.com/watch?v=cSntakowRMQ | E18: Pass | F18: Pass | G18: Pass | H18: 16/03/2026 - Thumbnail uploaded - https://loom.com/i/06ce81c1075848adb00f500bf1e338ae
A19: Tata Card SELECT | B19: No Videos Provided | C19: No URLs Provided | D19: - | E19: - | F19: - | G19: -
A20: Tata Card | B20: No Videos Provided | C20: No URLs Provided | D20: - | E20: - | F20: - | G20: -
A21: SimplyCLICK SBI Card | B21: 1.) Simply CLICK for online shopping | SBI Card 2.) 10X Reward Points With SimplyCLICK SBI Card 3.) The Many Rewards of the SimplyCLICK SBI Card 4.) SimplyCLICK SBI Card: Your perfect online shopping partner 5.) SimplyClick SBI Card - A Credit Card for the Generation that Shops Online 6.) SBI SimplyCLICK Credit Card | Benefits & Rewards | Shopping Card | C21: 1.) https://www.youtube.com/watch?v=tvBOlhfBK-4 2.) https://www.youtube.com/watch?v=bGOgP94NMvk 3.) https://www.youtube.com/watch?v=wesp58Mc9YA 4.) https://www.youtube.com/watch?v=BAPzyCp1J4M 5.) https://www.youtube.com/watch?v=496VxdV3mDM 6.) https://www.youtube.com/watch?v=J9XLdHfKagE | D21: 1.) https://www.youtube.com/watch?v=tvBOlhfBK-4 2.) https://www.youtube.com/watch?v=bGOgP94NMvk 3.) https://www.youtube.com/watch?v=wesp58Mc9YA 4.) https://www.youtube.com/watch?v=BAPzyCp1J4M 5.) https://www.youtube.com/watch?v=496VxdV3mDM 6.) https://www.youtube.com/watch?v=J9XLdHfKagE | E21: Pass | F21: Pass | G21: Fail | H21: 16/03/2026 - 4 videos still have dummy thumbnails - https://www.loom.com/i/172711acfe964033a1fd2b83c34ffa29
A22: SimplySAVE SBI Card | B22: 1.) SimplySAVE SBI Credit Card | Shopping Credit Card Benefits & Rewards 2.) SimplySAVE SBI Card is simply better! 3.) More savings, more Rewards | SimplySAVE SBI Card 4.) Make your spends rewarding with SimplySAVE SBI Card 5.) SimplySAVE SBI Credit Card | Shopping Credit Card Benefits & Rewards 6.) SimplySAVE SBI Card | Shopping Credit Card Benefits & Rewards | C22: 1.) https://www.youtube.com/watch?v=XTwASXOCJWY 2.) https://www.youtube.com/watch?v=MU3gDxkS-K4 3.) https://www.youtube.com/watch?v=VViQI-Pmu1s 4.) https://www.youtube.com/watch?v=hT_VF9fYMiU 5.) https://www.youtube.com/watch?v=vozHBbdKVAQ 6.) https://www.youtube.com/watch?v=QEJHAk_iyuc | D22: 1.) https://www.youtube.com/watch?v=XTwASXOCJWY 2.) https://www.youtube.com/watch?v=MU3gDxkS-K4 3.) https://www.youtube.com/watch?v=VViQI-Pmu1s 4.) https://www.youtube.com/watch?v=hT_VF9fYMiU 5.) https://www.youtube.com/watch?v=vozHBbdKVAQ 6.) https://www.youtube.com/watch?v=QEJHAk_iyuc | E22: Pass | F22: Pass | G22: Pass | H22: 16/03/2026 - Thumbnails uploaded - https://loom.com/i/df8240d597a44fefad30335a83e89434
A23: Landmark Rewards SBI Card PRIME | B23: 1.) Landmark Rewards SBI Card PRIME | C23: 1.) https:/www.youtube.com/shorts/2Mo71jNeo9s | D23: 1.) https://www.youtube.com/shorts/2Mo71jNeo9s | E23: Pass | F23: Pass | G23: Pass | H23: 16/03/2026 - Thumbnail uploaded - https://loom.com/i/6ee05e35662c483dba21da8fb3a91b50
A24: Landmark Rewards SBI Card SELECT | B24: No Videos Provided | C24: No URLs Provided | D24: - | E24: - | F24: - | G24: -
A25: Landmark Rewards SBI Card | B25: No Videos Provided | C25: No URLs Provided | D25: - | E25: - | F25: - | G25: -
A26: Titan SBI Card | B26: 1.) Introducing the TITAN SBI Card 2.) Get ready to receive a warm welcome and even more rewards! 3.) Get up to 7.5% Cashback* by shopping at Titan stores with Titan SBI Card. | C26: 1.) https://www.youtube.com/shorts/lyOux3jo84U 2.) https://www.youtube.com/shorts/0CnmQQZyVsU 3.) https://www.youtube.com/shorts/pmpogAWTGjQ | D26: 1.) https://www.youtube.com/shorts/lyOux3jo84U 2.) https://www.youtube.com/shorts/0CnmQQZyVsU 3.) https://www.youtube.com/shorts/pmpogAWTGjQ | E26: Pass | F26: Pass | G26: Pass | H26: 17/03/2026 - The issue is now resolved - https://loom.com/i/73afe3d9056e45d78cc7d9f42f724b09 16/03/2026 - 2nd Video is still having a dummy thumbnail - https://www.loom.com/i/c5c4cf8e7d5f40089f477cfd9362a7ec
A27: Reliance SBI Card | B27: No Videos Provided | C27: No URLs Provided | D27: - | E27: - | F27: - | G27: -
A28: Reliance SBI Card PRIME | B28: No Videos Provided | C28: No URLs Provided | D28: - | E28: - | F28: - | G28: -
A29: SBI Card Unnati | B29: No Videos Provided | C29: No URLs Provided | D29: - | E29: - | F29: - | G29: -
A30: Shaurya SBI Card | B30: No Videos Provided | C30: No URLs Provided | D30: - | E30: - | F30: - | G30: -
A31: Shaurya Select SBI Card | B31: No Videos Provided | C31: No URLs Provided | D31: - | E31: - | F31: - | G31: -
A32: IndiGo SBI Card | B32: 1.) Unlock Every Benefit with the IndiGo SBI Card ELITE | C32: 1.) https:/www.youtube.com/shorts/EYSkhcM1HQ4 | D32: 1.) https://www.youtube.com/shorts/EYSkhcM1HQ4 | E32: Pass | F32: Pass | G32: Pass | H32: 16/03/2026 - Thumbnail uploaded - https://loom.com/i/a86b8e71720a415298fd217660dbe2c6
A33: IndiGo SBI Card ELITE | B33: 1.) Start every journey on an ELITE note with IndiGo SBI Card ELITE 2.) Unlock Every Benefit with the IndiGo SBI Card ELITE | C33: 1.) https://www.youtube.com/shorts/D5mtu2yXbUM 2.) https://www.youtube.com/shorts/EYSkhcM1HQ4 | D33: 1.) https://www.youtube.com/shorts/D5mtu2yXbUM 2.) https://www.youtube.com/shorts/EYSkhcM1HQ4 | E33: Pass | F33: Pass | G33: Pass | H33: 16/03/2026 - Thumbnail uploaded - https://loom.com/i/6be27063ca794c8fa8fe704e3c485f8c
A34: KrisFlyer SBI Card | B34: No Videos Provided | C34: No URLs Provided | D34: - | E34: - | F34: - | G34: -
A35: KrisFlyer SBI Card Apex | B35: 1.) KrisFlyer SBI Card APEX - 8 domestic & 8 international complimentary lounge visits per year 2.) KrisFlyer SBI Card Apex - 10,000 KrisFlyer miles on an annual spend of ₹5 Lakhs 3.) Krisflyer SBI Card APEX - 10 Miles on Rs.200 4.) Krisflyer SBI Card APEX - Welcome Benefit 5.) KrisFlyer SBI Card APEX is now live! | C35: 1.) https://www.youtube.com/shorts/EM3xH2WZhP4 2.) https://www.youtube.com/shorts/H7rTWOLLpCw 3.) https://www.youtube.com/shorts/9RaZBCtviOE 4.) https://www.youtube.com/shorts/djWK01XEz4s 5.) https://www.youtube.com/shorts/DKvUixvzV-I | D35: 1.) https://www.youtube.com/shorts/EM3xH2WZhP4 2.) https://www.youtube.com/shorts/H7rTWOLLpCw 3.) https://www.youtube.com/shorts/9RaZBCtviOE 4.) https://www.youtube.com/shorts/djWK01XEz4s 5.) https://www.youtube.com/shorts/DKvUixvzV-I | E35: Pass | F35: Pass | G35: Fail | H35: 16/03/2026 - 3rd Video thumbnail still pending (from HTML Team) - https://loom.com/i/4f5aa20f9a914880835ad45ea74482eb
A36: SBI Card MILES PRIME | B36: No Videos Provided | C36: No URLs Provided | D36: - | E36: - | F36: - | G36: -
A37: SBI Card Miles Elite | B37: No Videos Provided | C37: No URLs Provided | D37: - | E37: - | F37: - | G37: -
A38: SBI Card MILES | B38: 1.) SBI Card Miles is here 2.) SBI Card Miles 3.) SBI Card Miles | C38: 1.) https://www.youtube.com/shorts/dqC5RDPPS2Y 2.) https://www.youtube.com/shorts/E8cowsJswJQ 3.) https://www.youtube.com/shorts/HOz2q_T9Grg | D38: 1.) https://www.youtube.com/shorts/dqC5RDPPS2Y 2.) https://www.youtube.com/shorts/E8cowsJswJQ 3.) https://www.youtube.com/shorts/HOz2q_T9Grg | E38: Pass | F38: Pass | G38: Pass | H38: 16/03/2026 - The Title & Thumbnail issues are resolved - https://loom.com/i/ce40c741ac3b4569a0efb26935f955bb 11/03/2026 - The Video Titles for all are "SBI Miles" instead of - 1.) SBI Card Miles is here 2.) SBI Card Miles 3.) SBI Card Miles
A39: BPCL SBI Card OCTANE | B39: 1.) BPCL SBI Card Octane | Credit Card Benefits & Rewards | SBI Fuel Credit Card | C39: 1.) https:/www.youtube.com/watch?v=_pdIp-w70SE | D39: 1.) https://www.youtube.com/watch?v=_pdIp-w70SE | E39: Pass | F39: Pass | G39: Pass | H39: 16/03/2026 - Thumbnail uploaded - https://loom.com/i/8f9d77d0bcb240ccaf04afffefc094f7
A40: IRCTC SBI Card Premier | B40: 1.) IRCTC SBI Card Premier | Credit Card Features, Benefits and Rewards | C40: 1.) https:/www.youtube.com/watch?v=jKtSjf34duQ | D40: 1.) https://www.youtube.com/watch?v=jKtSjf34duQ | E40: Pass | F40: Pass | G40: Pass | H40: 16/03/2026 - Thumbnail uploaded - https://loom.com/i/db2f43400c4444388176b4216e4ff884
A41: Etihad Guest SBI Premier Card | B41: No Videos Provided | C41: No URLs Provided | D41: - | E41: - | F41: - | G41: -
A42: Etihad Guest SBI Card | B42: 1.) Etihad Guest SBI Card | Credit Card Benefits & Rewards | Travel Card | C42: 1.) https:/www.youtube.com/watch?v=99yrQ0ox_5Q | D42: 1.) https://www.youtube.com/watch?v=99yrQ0ox_5Q | E42: Pass | F42: Pass | G42: Pass | H42: 16/03/2026 - Thumbnail uploaded - https://loom.com/i/96bc8acf7d8a478892a07e3a86aa83e2
A43: BPCL SBI Card | B43: 1.) BPCL SBI Card | Credit Card Benefits & Rewards | SBI Fuel Card | C43: 1.) https:/www.youtube.com/watch?v=PecZCFrw6pE | D43: 1.) https://www.youtube.com/watch?v=PecZCFrw6pE | E43: Pass | F43: Pass | G43: Pass | H43: 16/03/2026 - Thumbnail uploaded - https://loom.com/i/f6d5512d08064c34ba6aa5af6ac852c0
A44: IRCTC SBI Platinum Card | B44: 1.) Explore the world | IRCTC SBI Card | C44: 1.) https:/www.youtube.com/watch?v=PdMrY0ccm7Y | D44: 1.) https://www.youtube.com/watch?v=PdMrY0ccm7Y | E44: Pass | F44: Pass | G44: Pass | H44: 16/03/2026 - The thumbnail is uploaded - https://loom.com/i/2dd6cf4575834847b3155660dbc8f5ec 16/03/2026 - Thumbnails sent in the file but not yet uploaded
A45: Club Vistara SBI Card PRIME | B45: 1.) Club Vistara SBI Card PRIME - Credit Card Features, Benefits & Rewards 2.) Flying in Luxury | Club Vistara SBI Card PRIME | C45: 1.) https://www.youtube.com/watch?v=KP8UIBvnidA 2.) https://youtu.be/y6btgRFmkB4 | D45: 1.) https://www.youtube.com/watch?v=KP8UIBvnidA 2.) https://youtu.be/y6btgRFmkB4 | E45: Pass | F45: Pass | G45: Pass | H45: 16/03/2026 - The thumbnails are uploaded - https://loom.com/i/b283e89a3a654a4da15fbf9025b3dca6 16/03/2026 - Thumbnails sent in the file but not yet uploaded
A46: Club Vistara SBI Card | B46: No Videos Provided | C46: No URLs Provided | D46: - | E46: - | F46: - | G46: -
A47: Air India SBI Signature Card | B47: No Videos Provided | C47: No URLs Provided | D47: - | E47: - | F47: - | G47: -
A48: Air India SBI Platinum Card | B48: No Videos Provided | C48: No URLs Provided | D48: - | E48: - | F48: - | G48: -

Sheet Exclusive Privileges Icons
A6: Card Name | B6: Exclusive Privileges | C6: Privilege Heading | D6: Correct Icon | E6: Correct Format - SVG | F6: Last Tested On | G6: QA Remark
A7: Tata Neu Plus SBI Card | B7: Welcome Gift Reward Benefits Domestic Lounge Benefits Fuel Surcharge Waiver Spend Based Reversal | C7: Pass | D7: Pass | E7: Fail | F7: 46329
A8: SBI Card Elite | B8: Welcome Gift Complimentary Movie Tickets Milestone Privileges ELITE Rewards International Lounge Program Domestic Lounge Program Lowest Forex Markup ITC Silver Tier Membership Exclusive Concierge Service | C8: Pass | D8: Pass | E8: Pass | F8: 13/3/2026 | G8: 13/03/2026 - The ITC Silver Tier Membership svg has been updated on sbi-pvt
A9: Cashback SBI Card | B9: Card Cashback Hassle free Spend Based Reversal Fuel Surcharge Waiver | C9: Pass | D9: Pass | E9: Fail | F9: 46329
A10: SBI Card Pulse | B10: Welcome Gift Health Benefits Exclusive Rewards Milestone Benefits Comprehensive Insurance Cover Lounge Benefits | C10: Pass | D10: Pass | E10: Pass | F10: 46329
A11: Air India SBI Signature Card | B11: Welcome Benefit Reward Benefits Milestone Benefits Lounge Benefit Fuel Surcharge Waiver | C11: Pass | D11: Pass | E11: Pass | F11: 46329
A12: Air India SBI Platinum Card | B12: Welcome Benefit Reward Benefits Milestone Benefits Lounge Benefit Fuel Surcharge Waiver | C12: Pass | D12: Pass | E12: Pass | F12: 46329
A13: Apollo SBI Card Select | B13: Welcome Benefits Health Benefits Reward Points Milestone Benefits Lounge Benefits Fuel Surcharge Waiver | C13: Pass | D13: Pass | E13: Pass | F13: 46329
A14: Flipkart SBI Card | B14: Welcome Benefit Card Cashback Spend Based Reversal Fuel Surcharge Waiver | C14: Pass | D14: Pass | E14: Pass | F14: 46329
A15: Landmark Rewards SBI Card Select | B15: Welcome Benefits Milestone Benefits Reward Benefits Fuel Surcharge Waiver | C15: Pass | D15: Pass | E15: Pass | F15: 46329
A16: Landmark Rewards SBI Card | B16: Welcome Benefits Milestone Benefits Reward Benefits Fuel Surcharge Waiver | C16: Pass | D16: Pass | E16: Pass | F16: 46329
A17: Landmark SBI Card Prime | B17: Welcome Benefits Milestone Benefits Reward Benefits Domestic Lounge Program Complimentary Lounge Program Complimentary Priority Pass Membership Fuel Surcharge Waiver | C17: Pass | D17: Pass | E17: Pass | F17: 46329
A18: Etihad Guest SBI Card | B18: Welcome Benefits Renewal Benefits Milestone Benfits Spend-Based Fee Reversal Insurance Lounge Benefit Fuel Surcharge Waiver | C18: Fail | D18: Fail | E18: Fail | F18: 13/03/2026 | G18: 13/03/2026 - The renewal benefits icons is now other benefits icon - https://loom.com/i/5fa12e73844e460c9f29f23b2580fc57
A19: Doctors SBI Card | B19: Professional Indemnity Insurance Welcome Gift Reward Points Milestone Benefits International Lounge Program Domestic Lounge Program Fuel Surcharge Waiver | C19: Pass | D19: Pass | E19: Pass | F19: 13/3/2026 | G19: 13/03/2026 - Professional Indemnity Insurance icon format is now svg
A20: BPCL SBI Card | B20: Welcome Benefits Value Back Benefits Reward Benefits Fuel Surcharge Waiver Other Benefits | C20: Pass | D20: Pass | E20: Pass | F20: 46329
A21: Etihad Guest SBI Premier Card | B21: Welcome Benefits Renewal Benefits Milestone Benefits Spend-Based Fee Reversal Insurance International Lounge Benefits Domestic Lounge Benefits Fuel Surcharge Waiver | C21: Fail | D21: Fail | E21: Fail | F21: 13/03/2026 | G21: 13/03/2026 - The renewal benefits icons is now other benefits icon - https://loom.com/i/9989e3e8db674b35aeeebe34cbd02074
A22: Doctors with IMA SBI Card | B22: Indian Medical Association Professional Indemnity Insurance Welcome Gift Reward Points Milestone Benefits International Lounge Program Domestic Lounge Program Fuel Surcharge Waiver | C22: Pass | D22: Pass | E22: Pass | F22: 17/03/2026 | G22: 17/03/2026 - The issue has been resolved on sbifo-pvt - https://loom.com/i/5cdf10232c634648a6f578008c751524 13/03/2026 - The Indian Medical Association icon is still in png format instead of svg - https://loom.com/i/7d5ca397c5d04b26a6b4b11b7e04fc13
A23: BPCL SBI Card Octane | B23: Welcome Benefits Value Back Benefits Reward Benefits Milestone Benefits Lounge Benefit Fuel Surcharge Waiver Other Benefits | C23: Pass | D23: Pass | E23: Pass | F23: 46329
A24: Club Vistara SBI Card | B24: Renewal Benefits Reward Benefits Milestone Benefits Comprehensive Insurance Cover Domestic Lounge Benefits Complimentary Priority Pass Membership | C24: Pass | D24: Fail | E24: Fail | F24: 13/03/2026 | G24: 13/03/2026 - The renewal benefits icons is now other benefits icon - https://loom.com/i/533667050e05453eba3b82e9956fb5db
A25: Apollo SBI Card | B25: Welcome Benefits Reward Benefits Spend Based Reversal Fuel Surcharge Waiver | C25: Pass | D25: Pass | E25: Pass | F25: 46329
A26: Club Vistara SBI Card Prime | B26: Renewal Benefits Reward Benefits Milestone Benefits Comprehensive Insurance Cover Domestic Lounge Benefits Complimentary Priority Pass Membership | C26: Pass | D26: Fail | E26: Fail | F26: 13/03/2026 | G26: 13/03/2026 - The renewal benefits icons is now other benefits icon - https://loom.com/i/a99b49d06b24415b8e7c18fcd7314c40
A27: IRCTC SBI Platinum Card | B27: Welcome Benefit Value Back Benefits Reward Benefits Milestone Benefits Travel Offers from IRCTC Fuel Surcharge Waiver Railway Lounge Program | C27: Pass | D27: Pass | E27: Pass | F27: 46329
A28: IRCTC Premier Card | B28: Welcome Benefit Value Back Benefits Reward Benefits Milestone Benefits Complimentary Insurance Cover Travel Offers from IRCTC Fuel Surcharge Waiver Railway Lounge Program | C28: Pass | D28: Pass | E28: Pass | F28: 46329
A29: OLA Money SBI Card | B29: First Year Free Reward Benefits Fuel Surcharge Waiver | C29: Pass | D29: Pass | E29: Pass | F29: 46329
A30: Krisflyer SBI Card | B30: Welcome Benefits Reward Benefits Milestone Benefits Lounge Benefits Fuel Surcharge Waiver Insurance Coverage | C30: Pass | D30: Pass | E30: Pass | F30: 46329
A31: Krisflyer SBI Card Apex | B31: Welcome Benefits Reward Benefits Milestone Benefits Lounge Benefits Fuel Surcharge Waiver Insurance Coverage | C31: Pass | D31: Pass | E31: Pass | F31: 46329
A32: Tata Neu Infinity SBI Card | B32: Welcome Gift Reward Benefits Domestic Lounge Benefits International Lounge Benefits Fuel Surcharge Waiver Spend Based Reversal Lowest Forex Markup | C32: Pass | D32: Pass | E32: Pass | F32: 46329
A33: PhonePe SBI Card Purple | B33: Welcome Benefits PhonePe Rewards Exclusive Milestone Benefits Annual Fee Reversal Fuel Surcharge Waiver | C33: Pass | D33: Pass | E33: Pass | F33: 13/03/2026 | G33: 13/03/2026 - The issue has been resolved - https://loom.com/i/b76a27a9b8cf4f9c857d6c3289f4c0be
A34: Paytm SBI Card Select | B34: Welcome Benefit Cashback Cyber Fraud Insurance Milestone Benefits International Lounge Program Domestic Lounge Program Fuel Surcharge Waiver Smart Card Control | C34: Pass | D34: Pass | E34: Pass | F34: 13/03/2026 | G34: 13/03/2026 - The smart card control icon has been corrected - https://loom.com/i/9a606d0067c843e992fa81fa98ac9a04
A35: SBI Card Miles Elite | B35: Welcome Benefit Reward Benefits Milestone Benefits International Travel Privileges Domestic Privileges Insurance Cover Low Forex Markup | C35: Fail | D35: Pass | E35: Pass | F35: 46329
A36: Indigo SBI Card Elite | B36: Welcome Benefits Renewal Benefits Reward Benefits Milestone Benefits Domestic Lounge Benefit International Lounge Benefit Fuel Surcharge Waiver Insurance | C36: Pass | D36: Fail | E36: Pass | F36: 13/03/2026 | G36: 13/03/2026 - The renewal benefits icons is now other benefits icon - https://loom.com/i/79ebab072817491799e8d0c7111bbe6a
A37: Reliance SBI Card | B37: Welcome Benefit Milestone Benefits Reward Benefits Fuel Surcharge Waiver Other Benefits | C37: Pass | D37: Pass | E37: Pass | F37: 46329
A38: Indigo SBI Card | B38: Welcome Benefit Renewal Benefits Reward Benefits Milestone Benefits Domestic Lounge Benefits Fuel Surcharge Waiver | C38: Pass | D38: Fail | E38: Pass | F38: 13/03/2026 | G38: 13/03/2026 - The renewal benefits icons is now other benefits icon - https://loom.com/i/097a9898159640a995cc8f2095c9b7f5
A39: Reliance SBI Card Prime | B39: Welcome Benefit Milestone Benefit Reward Benefits Complimentary Movie Ticket International Lounge Program Domestic Lounge Program Fuel Surcharge Waiver Other Benefits | C39: Pass | D39: Pass | E39: Pass | F39: 46329
A40: PhonePe SBI Card Select Black | B40: Welcome Benefits PhonePe Rewards Exclusive Milestone Benefits International Lounge Program Domestic Lounge Program Annual Fee Reversal Fuel Surcharge Waiver | C40: Pass | D40: Fail | E40: Pass | F40: 13/03/2026 | G40: 13/03/2026 - The issue has been resolved - https://loom.com/i/f70004986adf40fabb77ac67640f8c9d
A41: PayTM SBI Card | B41: Welcome Benefit Cashback Cyber Fraud Insurance Milestone Benefits Fuel Surcharge Waiver Smart Control | C41: Pass | D41: Pass | E41: Pass | F41: 46329 | G41: 13/03/2026 - The smart card control icon has been corrected - https://loom.com/i/8681896e9fc64af18a92ddd95e210c09
A42: SBI Card Prime | B42: Welcome Gift Prime Rewards Milestone Benefits Lounge Access ITC Silver Tier Membership Birthday Benefit | C42: Pass | D42: Pass | E42: Pass | F42: 13/03/2026 | G42: 13/03/2026 - The ITC Silver Tier Membership svg has been updated on sbi-pvt
A43: SBI Card Miles | B43: Welcome Gift Miles Rewards Milestone Benefits International Travel Privileges Domestic Travel Privileges Low Forex Markup | C43: Fail | D43: Fail | E43: Pass | F43: 13/03/2026 | G43: 13/03/2026 - The Miles Rewards icon is still incorrect - https://loom.com/i/34c52c08d1884e65bf0c9d5696d7e384
A44: SBI Card Miles Prime | B44: Welcome Benefit Reward Benefits Milestone Benefits International Travel Privileges Domestic Travel Privileges Insurance Cover Low Forex Markup | C44: Fail | D44: Pass | E44: Pass | F44: 46329
A45: SBI Card Unnati | B45: Zero Fee Card Milestone Benefit REward Benefits Fuel Surcharge Waiver Secure Card | C45: Pass | D45: Pass | E45: Pass | F45: 46329
A46: SimplyClick SBI Card | B46: Welcome Gift E-Shopping Rewards Milestone Benefits Fuel Surcharge Waiver Spend Based Reversal | C46: Pass | D46: Pass | E46: Pass | F46: 46329
A47: SimplySave SBI Card | B47: Extravaganza Offer Reward Benefits Fuel Surcharge Waiver Spend Based Reversal | C47: Pass | D47: Pass | E47: Pass | F47: 46329
A48: Titan SBI Card | B48: Welcome Benefit Exclusive Milestone Benefits Exclusive Titan Instore Benefits Reward Benefits Lounge Benefits | C48: Pass | D48: Pass | E48: Pass | F48: 46329
A49: Shaurya SBI Card | B49: Welcome Benefits Waiver of Renewal Fee Reward Benefits Fuel Surcharge Waiver Insurance Benefits | C49: Pass | D49: Pass | E49: Pass | F49: 46329
A50: Shaurya Select SBI Card | B50: Milestone Rewards Reward Benefits Renewal Benefits Insurance Benefits Fuel Surcharge Waiver Additional Benefits Domestic Airport Lounge Program | C50: Fail | D50: Fail | E50: Pass | F50: 13/03/2026 | G50: 13/03/2026 - The renewal benefits icons is now other benefits icon - https://loom.com/i/10aa8bd3e5ab4ecbacb09ecb3d3eeb9b

Sheet Explore Rewards TextOverlap
A1: Page | B1: Priority | C1: Device | D1: Issue Type | E1: Annual Spent | F1: Benefit | G1: Font Size | H1: Assigned To | I1: SBI Team Remark | J1: Vector3 Remark | K1: Status
A2: SBI Card Elite | B2: P2 | C2: - | D2: Content Not Provided | E2: Rs. 4, 8 Lakhs | F2: - | G2: - | H2: Namita | K2: Resolved
A3: SBI Card Elite | B3: P2 | C3: - | D3: Formatting | E3: Rs. 3, 4, 5, 8 lakhs | F3: Reward Points | G3: - | H3: Neha Jain | J3: 02/03/2026 - comma before the 3 zeros missing as per the Number system formatting- https://www.loom.com/i/2b35a7edc03c40d493e73aee5183e0bd | K3: Resolved
A4: SBI Card Elite | B4: P3 | C4: Desktops | D4: Overlap | E4: Rs. 10 Lakhs | F4: Annual Fee Reversal | G4: Small | H4: Neha Jain | J4: 09/03/2026 - Word "Annual" needs to be in the title and "Fee Reversal" in the sub title element. 06/03/2026 - As discussed with Namita ma'am, the whole benefit is authored in the title itself. Instead title should only have 1 or 2 words and the rest should go in the sub-title. Therefore this needs to be done by the content authoring team, hence assigning to Neha Jain | K4: Resolved
A5: SBI Card Elite | B5: P3 | C5: Galazy Z Fold | D5: Overlap | E5: Rs. 10 Lakhs | F5: Annual Fee Reversal | G5: Large | H5: Neha Jain | J5: 09/03/2026 - Word "Annual" needs to be in the title and "Fee Reversal" in the sub title element. 06/03/2026 - As discussed with Namita ma'am, the whole benefit is authored in the title itself. Instead title should only have 1 or 2 words and the rest should go in the sub-title. Therefore this needs to be done by the content authoring team, hence assigning to Neha Jain | K5: Resolved
A6: SBI Card Elite | B6: P2 | C6: iPad Mini | D6: Overlap | E6: Rs. 10 Lakhs | F6: Annual Fee Reversal | G6: Small | H6: Neha Jain | J6: 09/03/2026 - Word "Annual" needs to be in the title and "Fee Reversal" in the sub title element. 06/03/2026 - As discussed with Namita ma'am, the whole benefit is authored in the title itself. Instead title should only have 1 or 2 words and the rest should go in the sub-title. Therefore this needs to be done by the content authoring team, hence assigning to Neha Jain | K6: Resolved
A7: Cashback SBI Card | B7: P2 | C7: iPad Pro | D7: Overlap | E7: Rs. 2 Lakhs | F7: Waiver of Renewal Fee | G7: Small | H7: Neha Jain | J7: 09/03/2026 - The word "Waiver" needs to be in the title and "of Renewal Fee" in the sub-title element 06/03/2026 - As discussed with Namita ma'am, the whole benefit is authored in the title itself. Instead title should only have 1 or 2 words and the rest should go in the sub-title. Therefore this needs to be done by the content authoring team, hence assigning to Neha Jain | K7: Resolved
A8: Cashback SBI Card | B8: P3 | C8: iPad Pro | D8: Overlap | E8: Rs. 2 Lakhs | F8: Waiver of Renewal Fee | G8: Largest | H8: Neha Jain | J8: 09/03/2026 - The word "Waiver" needs to be in the title and "of Renewal Fee" in the sub-title element 06/03/2026 - As discussed with Namita ma'am, the whole benefit is authored in the title itself. Instead title should only have 1 or 2 words and the rest should go in the sub-title. Therefore this needs to be done by the content authoring team, hence assigning to Neha Jain | K8: Resolved
A9: Cashback SBI Card | B9: P3 | C9: iPad Mini | D9: Overlap | E9: Rs. 2 Lakhs | F9: Waiver of Renewal Fee | G9: Small | H9: Neha Jain | J9: 09/03/2026 - The word "Waiver" needs to be in the title and "of Renewal Fee" in the sub-title element 06/03/2026 - As discussed with Namita ma'am, the whole benefit is authored in the title itself. Instead title should only have 1 or 2 words and the rest should go in the sub-title. Therefore this needs to be done by the content authoring team, hence assigning to Neha Jain | K9: Resolved
A10: SBI Card Pulse | B10: P2 | C10: Desktops | D10: Overlap | E10: Rs. 2 Lakhs | F10: Waiver of Renewal Fee | G10: Small | H10: Neha Jain | J10: 09/03/2026 - The word "Waiver" needs to be in the title and "of Renewal Fee" in the sub-title element 06/03/2026 - As discussed with Namita ma'am, the whole benefit is authored in the title itself. Instead title should only have 1 or 2 words and the rest should go in the sub-title. Therefore this needs to be done by the content authoring team, hence assigning to Neha Jain | K10: Resolved
A11: SBI Card Pulse | B11: P3 | C11: Desktops | D11: Overlap | E11: Rs. 2 Lakhs | F11: Waiver of Renewal Fee | G11: Large | H11: Neha Jain | J11: 09/03/2026 - The word "Waiver" needs to be in the title and "of Renewal Fee" in the sub-title element 06/03/2026 - As discussed with Namita ma'am, the whole benefit is authored in the title itself. Instead title should only have 1 or 2 words and the rest should go in the sub-title. Therefore this needs to be done by the content authoring team, hence assigning to Neha Jain | K11: Resolved
A12: SBI Card Pulse | B12: P2 | C12: iPads / Tablets | D12: Overlap | E12: Rs. 2 Lakhs | F12: Waiver of Renewal Fee | G12: Small | H12: Neha Jain | J12: 09/03/2026 - The word "Waiver" needs to be in the title and "of Renewal Fee" in the sub-title element 06/03/2026 - As discussed with Namita ma'am, the whole benefit is authored in the title itself. Instead title should only have 1 or 2 words and the rest should go in the sub-title. Therefore this needs to be done by the content authoring team, hence assigning to Neha Jain | K12: Resolved
A13: SBI Card Pulse | B13: P3 | C13: iPads / Tablets | D13: Overlap | E13: Rs. 2 Lakhs | F13: Waiver of Renewal Fee | G13: Default | H13: Neha Jain | J13: 09/03/2026 - The word "Waiver" needs to be in the title and "of Renewal Fee" in the sub-title element 06/03/2026 - As discussed with Namita ma'am, the whole benefit is authored in the title itself. Instead title should only have 1 or 2 words and the rest should go in the sub-title. Therefore this needs to be done by the content authoring team, hence assigning to Neha Jain | K13: Resolved
A14: SBI Card Pulse | B14: P2 | C14: iPads / Tablets | D14: Overlap | E14: Rs. 2 Lakhs | F14: Waiver of Renewal Fee | G14: Large | H14: Neha Jain | J14: 09/03/2026 - The word "Waiver" needs to be in the title and "of Renewal Fee" in the sub-title element 06/03/2026 - As discussed with Namita ma'am, the whole benefit is authored in the title itself. Instead title should only have 1 or 2 words and the rest should go in the sub-title. Therefore this needs to be done by the content authoring team, hence assigning to Neha Jain | K14: Resolved
... A66: Club Vistara SBI Card Prime | B66: P1 | C66: Desktops, Mobile Phones | D66: Truncated Content | E66: Rs. 1.5 Lakh | F66: 1 Premium Economy Ticket* | G66: Default | H66: Neha Jain | J66: 09/03/2026 - "1 Premium" needs to be in the Title & "Economy Ticket*" in the sub-title element. 06/03/2026 - As discussed with Namita ma'am, the whole benefit is authored in the title itself. Instead title should only have 1 or 2 words and the rest should go in the sub-title. Therefore this needs to be done by the content authoring team, hence assigning to Neha Jain | K66: Open
A67: IRCTC SBI Platinum Card | B67: P1 | C67: - | D67: Content Not Provided | F67: - | G67: - | H67: Namita | J67: 06/03/2026 - As discussed with Namita ma'am on SBI Daily Connect Call, if there are no milestones mentioned in the master sheet then no text animation or bar is required. Therefore marking this instance as closed. 02/03/2026 - Content - milestone & benefit not present in the master sorting sheet. | K67: Resolved
A68: IRCTC SBI Card Premier | B68: P3 | C68: Desktops | D68: Overlap | E68: Rs. 2 Lakhs | F68: Annual Fee Reversal | G68: Small | H68: Neha Jain | J68: 09/03/2026 - Word "Annual" needs to be in the title and "Fee Reversal" in the sub title element. 06/03/2026 - As discussed with Namita ma'am, the whole benefit is authored in the title itself. Instead title should only have 1 or 2 words and the rest should go in the sub-title. Therefore this needs to be done by the content authoring team, hence assigning to Neha Jain | K68: Resolved
A69: IRCTC SBI Card Premier | B69: P3 | C69: Galazy Z Fold | D69: Overlap | E69: Rs. 2 Lakhs | F69: Annual Fee Reversal | G69: Large | H69: Neha Jain | J69: 09/03/2026 - Word "Annual" needs to be in the title and "Fee Reversal" in the sub title element. 06/03/2026 - As discussed with Namita ma'am, the whole benefit is authored in the title itself. Instead title should only have 1 or 2 words and the rest should go in the sub-title. Therefore this needs to be done by the content authoring team, hence assigning to Neha Jain | K69: Resolved
A70: IRCTC SBI Card Premier | B70: P2 | C70: iPad Mini | D70: Overlap | E70: Rs. 2 Lakhs | F70: Annual Fee Reversal | G70: Small | H70: Neha Jain | J70: 09/03/2026 - Word "Annual" needs to be in the title and "Fee Reversal" in the sub title element. 06/03/2026 - As discussed with Namita ma'am, the whole benefit is authored in the title itself. Instead title should only have 1 or 2 words and the rest should go in the sub-title. Therefore this needs to be done by the content authoring team, hence assigning to Neha Jain | K70: Resolved
A71: IRCTC SBI Card Premier | B71: P2 | C71: - | D71: Formatting | E71: Rs. 50k | F71: 2,500 Reward Points | G71: - | H71: Neha Jain | J71: 02/03/2026 - comma before the 3 zeros missing as the Number System Formatting | K71: Resolved
A72: IRCTC SBI Card Premier | B72: P2 | C72: - | D72: Formatting | E72: Rs. 1 Lakh | F72: 5,000 Reward Points | G72: - | H72: Neha Jain | J72: 02/03/2026 - comma before the 3 zeros missing as the Number System Formatting | K72: Resolved
A73: KrisFlyer SBI Card | B73: P2 | C73: - | D73: Formatting | E73: Rs. 3 Lakhs | F73: 3,000 KrisFlyer Miles | G73: - | H73: Neha Jain | J73: 02/03/2026 - comma before the 3 zeros missing as the Number System Formatting | K73: Open
A74: KrisFlyer SBI Card | B74: P3 | C74: Desktops | D74: Overlap | E74: Rs. 2.5 Lakhs | F74: Tier upgrade to KrisFlyer Elite Silver Membship | G74: Default | H74: Namita | J74: 09/03/2026 - As discussed with Arun sir, this is one of the instance that cannot be handled by breaking it and adjusting into titles & sub-titles therefore it needs to be shortened. Hence changing the Assigned to column value from Neha Jain ma'am to Arun sir in order to discussion and get a confirmation. 06/03/2026 - As discussed with Namita ma'am, the whole benefit is authored in the title itself. Instead title should only have 1 or 2 words and the rest should go in the sub-title. Therefore this needs to be done by the content authoring team, hence assigning to Neha Jain | K74: Open
A75: KrisFlyer SBI Card | B75: P3 | C75: Desktops | D75: Overlap | E75: Rs. 2.5 Lakhs | F75: Tier upgrade to KrisFlyer Elite Silver Membship | G75: Large | H75: Namita | J75: 09/03/2026 - As discussed with Arun sir, this is one of the instance that cannot be handled by breaking it and adjusting into titles & sub-titles therefore it needs to be shortened. Hence changing the Assigned to column value from Neha Jain ma'am to Arun sir in order to discussion and get a confirmation. 06/03/2026 - As discussed with Namita ma'am, the whole benefit is authored in the title itself. Instead title should only have 1 or 2 words and the rest should go in the sub-title. Therefore this needs to be done by the content authoring team, hence assigning to Neha Jain | K75: Open
A76: KrisFlyer SBI Card | B76: P2 | C76: iPads / Tablets | D76: Overlap | E76: Rs. 2.5 Lakhs | F76: Tier upgrade to KrisFlyer Elite Silver Membship | G76: Default | H76: Namita | J76: 09/03/2026 - As discussed with Arun sir, this is one of the instance that cannot be handled by breaking it and adjusting into titles & sub-titles therefore it needs to be shortened. Hence changing the Assigned to column value from Neha Jain ma'am to Arun sir in order to discussion and get a confirmation. 06/03/2026 - As discussed with Namita ma'am, the whole benefit is authored in the title itself. Instead title should only have 1 or 2 words and the rest should go in the sub-title. Therefore this needs to be done by the content authoring team, hence assigning to Neha Jain | K76: Open
A77: KrisFlyer SBI Card | B77: P2 | C77: iPads / Tablets | D77: Overlap | E77: Rs. 2.5 Lakhs | F77: Tier upgrade to KrisFlyer Elite Silver Membship | G77: Default | H77: Namita | J77: 09/03/2026 - As discussed with Arun sir, this is one of the instance that cannot be handled by breaking it and adjusting into titles & sub-titles therefore it needs to be shortened. Hence changing the Assigned to column value from Neha Jain ma'am to Arun sir in order to discussion and get a confirmation. 06/03/2026 - As discussed with Namita ma'am, the whole benefit is authored in the title itself. Instead title should only have 1 or 2 words and the rest should go in the sub-title. Therefore this needs to be done by the content authoring team, hence assigning to Neha Jain | K77: Open
A78: KrisFlyer SBI Card Apex | B78: P2 | C78: - | D78: Content Not Provided | E78: Rs. 10 Lakhs | F78: - | G78: - | H78: Namita | J78: 02/03/2026 - Benefit not provided for 10 Lakh Milestone in master sorting sheet, currently 3,000 KrisFlyer Miles appears on 10 Lakh Milestone | K78: Resolved
A79: KrisFlyer SBI Card Apex | B79: P2 | C79: - | D79: Formatting | E79: Rs. 5 Lakhs | F79: 10,000 KrisFlyer Miles | G79: - | H79: Neha Jain | J79: 02/03/2026 - comma before the 3 zeros missing as the Number System Formatting | K79: Open
... A96: Indigo SBI Card Elite | B96: P2 | C96: - | D96: Formatting | E96: Rs. 3 Lakhs | F96: 6,000 Indigo Bluchips | G96: - | H96: Neha Jain | J96: 02/03/2026 - comma before the 3 zeros missing as the Number System Formatting | K96: Resolved
A97: Indigo SBI Card Elite | B97: P2 | C97: - | D97: Content Not Provided | E97: Rs. 6 Lakhs | F97: - | G97: - | H97: Namita | K97: Resolved
A98: Indigo SBI Card Elite | B98: P2 | C98: - | D98: Content Not Provided | E98: Rs. 9 Lakhs | F98: - | G98: - | H98: Namita | K98: Resolved
A99: Indigo SBI Card Elite | B99: P2 | C99: - | D99: Content Not Provided | E99: Rs. 12 Lakhs | F99: - | G99: - | H99: Namita | K99: Resolved
A100: Reliance SBI Card | B100: P2 | C100: Desktops | D100: Overlap | E100: Rs. 1 Lakh | F100: Waiver of Renewal Fee | G100: Small | H100: Neha Jain | J100: 09/03/2026 - The word "Waiver" needs to be in the title and "of Renewal Fee" in the sub-title element 06/03/2026 - As discussed with Namita ma'am, the whole benefit is authored in the title itself. Instead title should only have 1 or 2 words and the rest should go in the sub-title. Therefore this needs to be done by the content authoring team, hence assigning to Neha Jain | K100: Open
A101: Reliance SBI Card | B101: P3 | C101: Desktops | D101: Overlap | E101: Rs. 1 Lakh | F101: Waiver of Renewal Fee | G101: Large | H101: Neha Jain | J101: 09/03/2026 - The word "Waiver" needs to be in the title and "of Renewal Fee" in the sub-title element 06/03/2026 - As discussed with Namita ma'am, the whole benefit is authored in the title itself. Instead title should only have 1 or 2 words and the rest should go in the sub-title. Therefore this needs to be done by the content authoring team, hence assigning to Neha Jain | K101: Open
A102: Reliance SBI Card | B102: P2 | C102: iPads / Tablets | D102: Overlap | E102: Rs. 1 Lakh | F102: Waiver of Renewal Fee | G102: Small | H102: Neha Jain | J102: 09/03/2026 - The word "Waiver" needs to be in the title and "of Renewal Fee" in the sub-title element 06/03/2026 - As discussed with Namita ma'am, the whole benefit is authored in the title itself. Instead title should only have 1 or 2 words and the rest should go in the sub-title. Therefore this needs to be done by the content authoring team, hence assigning to Neha Jain | K102: Open
A103: Reliance SBI Card | B103: P3 | C103: iPads / Tablets | D103: Overlap | E103: Rs. 1 Lakh | F103: Waiver of Renewal Fee | G103: Default | H103: Neha Jain | J103: 09/03/2026 - The word "Waiver" needs to be in the title and "of Renewal Fee" in the sub-title element 06/03/2026 - As discussed with Namita ma'am, the whole benefit is authored in the title itself. Instead title should only have 1 or 2 words and the rest should go in the sub-title. Therefore this needs to be done by the content authoring team, hence assigning to Neha Jain | K103: Open
A104: Reliance SBI Card | B104: P2 | C104: iPads / Tablets | D104: Overlap | E104: Rs. 1 Lakh | F104: Waiver of Renewal Fee | G104: Large | H104: Neha Jain | J104: 09/03/2026 - The word "Waiver" needs to be in the title and "of Renewal Fee" in the sub-title element 06/03/2026 - As discussed with Namita ma'am, the whole benefit is authored in the title itself. Instead title should only have 1 or 2 words and the rest should go in the sub-title. Therefore this needs to be done by the content authoring team, hence assigning to Neha Jain | K104: Open
A105: Reliance SBI Card | B105: P2 | C105: Galazy Z Fold | D105: Overlap | E105: Rs. 1 Lakh | F105: Waiver of Renewal Fee | G105: Large | H105: Neha Jain | J105: 09/03/2026 - The word "Waiver" needs to be in the title and "of Renewal Fee" in the sub-title element 06/03/2026 - As discussed with Namita ma'am, the whole benefit is authored in the title itself. Instead title should only have 1 or 2 words and the rest should go in the sub-title. Therefore this needs to be done by the content authoring team, hence assigning to Neha Jain | K105: Open
A106: Reliance SBI Card | B106: P3 | C106: Galazy Z Fold | D106: Overlap | E106: Rs. 1 Lakh | F106: Waiver of Renewal Fee | G106: Default | H106: Neha Jain | J106: 09/03/2026 - The word "Waiver" needs to be in the title and "of Renewal Fee" in the sub-title element 06/03/2026 - As discussed with Namita ma'am, the whole benefit is authored in the title itself. Instead title should only have 1 or 2 words and the rest should go in the sub-title. Therefore this needs to be done by the content authoring team, hence assigning to Neha Jain | K106: Open
A107: Reliance SBI Card | B107: P2 | C107: Mobile Phones (width >= 360px) | D107: Overlap | E107: Rs. 1 Lakh | F107: Waiver of Renewal Fee | G107: Small | H107: Neha Jain | J107: 09/03/2026 - The word "Waiver" needs to be in the title and "of Renewal Fee" in the sub-title element 06/03/2026 - As discussed with Namita ma'am, the whole benefit is authored in the title itself. Instead title should only have 1 or 2 words and the rest should go in the sub-title. Therefore this needs to be done by the content authoring team, hence assigning to Neha Jain | K107: Open
A108: Reliance SBI Card | B108: P2 | C108: - | D108: Formatting | E108: Rs. 80K | F108: Rs. 1,000 Reliance Retail Voucher | G108: - | H108: Neha Jain | J108: 02/03/2026 - The symbol ₹ needs to be used and comma before the 3 zeros missing as the Number System Formatting | K108: Open
A109: Reliance SBI Card | B109: P2 | C109: - | D109: Formatting | E109: Rs. 50K | F109: Rs. 750 Reliance Retail Voucher | G109: - | H109: Neha Jain | J109: 02/03/2026 - The symbol ₹ needs to be used | K109: Open
A110: Reliance SBI Card | B110: P2 | C110: - | D110: Formatting | E110: Rs. 25K | F110: Rs. 500 Reliance Retail Voucher | G110: - | H110: Neha Jain | J110: 02/03/2026 - The symbol ₹ needs to be used | K110: Open
A111: Reliance SBI Card | B111: P3 | C111: iPad Pro | D111: Overlap | E111: Rs. 25K, 50K, 80K | F111: Reliance Retail Voucher | G111: All Sizes | H111: Namita | J111: 09/03/2026 - As discussed with Arun sir, this is one of the instance that cannot be handled by breaking it and adjusting into titles & sub-titles therefore it needs to be shortened. Hence changing the Assigned to column value from Neha Jain ma'am to Arun sir in order to discussion and get a confirmation. 06/03/2026 - As discussed with Namita ma'am, the whole benefit is authored in the title itself. Instead title should only have 1 or 2 words and the rest should go in the sub-title. Therefore this needs to be done by the content authoring team, hence assigning to Neha Jain | K111: Open
A112: Indigo SBI Card | B112: P2 | C112: - | D112: Content Not Provided | E112: Rs. 4 Lakhs | F112: - | G112: - | H112: Namita | K112: Resolved
A113: Indigo SBI Card | B113: P2 | C113: - | D113: Formatting | E113: Rs. 2 Lakhs | F113: 2,500 Indigo Bluchips | G113: - | H113: Neha Jain | J113: 02/03/2026 - comma before the 3 zeros missing as the Number System Formatting | K113: Resolved
A114: Reliance SBI Card Prime | B114: P2 | C114: - | D114: Formatting | E114: Rs. 75K | F114: Rs. 1,500 Reliance Retail Voucher | G114: - | H114: Neha Jain | J114: 02/03/2026 - The symbol ₹ needs to be used and comma before the 3 zeros missing as the Number System Formatting | K114: Open
A115: Reliance SBI Card Prime | B115: P2 | C115: - | D115: Formatting | E115: Rs. 150K | F115: Rs. 2,250 Reliance Retail Voucher | G115: - | H115: Neha Jain | J115: 02/03/2026 - The symbol ₹ needs to be used and comma before the 3 zeros missing as the Number System Formatting | K115: Open
A116: Reliance SBI Card Prime | B116: P2 | C116: - | D116: Formatting | E116: Rs. 3 Lakhs | F116: Rs. 5000 Reliance Retail Voucher | G116: - | H116: Neha Jain | J116: 02/03/2026 - The symbol ₹ needs to be used and comma before the 3 zeros missing as the Number System Formatting | K116: Open
A117: Reliance SBI Card Prime | B117: P3 | C117: iPad Pro | D117: Overlap | E117: Rs. 75K, 150K, 3 Lakhs | F117: Reliance Retail Voucher | G117: All Sizes | H117: Namita | J117: 09/03/2026 - As discussed with Arun sir, this is one of the instance that cannot be handled by breaking it and adjusting into titles & sub-titles therefore it needs to be shortened. Hence changing the Assigned to column value from Neha Jain ma'am to Arun sir in order to discussion and get a confirmation. 06/03/2026 - As discussed with Namita ma'am, the whole benefit is authored in the title itself. Instead title should only have 1 or 2 words and the rest should go in the sub-title. Therefore this needs to be done by the content authoring team, hence assigning to Neha Jain | K117: Open
A118: Reliance SBI Card Prime | B118: P1 | C118: - | D118: Repeated Milestone | E118: Rs. 3 Lakhs | F118: - | G118: - | H118: Neha Jain | J118: 02/03/2026 - The 3 Lakhs milestone appears before Rs. 75K & Rs. 150K even though being a greater amount and also appears thrice - https://www.loom.com/i/11c8ad67653d49de824bb23f3c270b26 | K118: Open
A119: Reliance SBI Card Prime | B119: P2 | C119: iPad Mini | D119: Overlap | E119: Rs. 3 Lakhs | F119: Annual Fee Reversal | G119: Small | H119: Neha Jain | J119: 09/03/2026 - Word "Annual" needs to be in the title and "Fee Reversal" in the sub title element. 06/03/2026 - As discussed with Namita ma'am, the whole benefit is authored in the title itself. Instead title should only have 1 or 2 words and the rest should go in the sub-title. Therefore this needs to be done by the content authoring team, hence assigning to Neha Jain | K119: Open
A120: PhonePe SBI Card Select Black | B120: P2 | C120: - | D120: Formatting | E120: Rs. 5 Lakhs | F120: Rs. 5,000 Yatra Voucher | G120: - | H120: Neha Jain | J120: 02/03/2026 - The symbol ₹ needs to be used and comma before the 3 zeros missing as the Number System Formatting | K120: Resolved
A121: PhonePe SBI Card Select Black | B121: P3 | C121: Desktops | D121: Overlap | E121: Rs. 3 Lakhs | F121: Annual Fee Reversal | G121: Small | H121: Neha Jain | J121: 09/03/2026 - Word "Annual" needs to be in the title and "Fee Reversal" in the sub title element. 06/03/2026 - As discussed with Namita ma'am, the whole benefit is authored in the title itself. Instead title should only have 1 or 2 words and the rest should go in the sub-title. Therefore this needs to be done by the content authoring team, hence assigning to Neha Jain | K121: Resolved
A122: PhonePe SBI Card Select Black | B122: P3 | C122: Galazy Z Fold | D122: Overlap | E122: Rs. 3 Lakhs | F122: Annual Fee Reversal | G122: Large | H122: Neha Jain | J122: 09/03/2026 - Word "Annual" needs to be in the title and "Fee Reversal" in the sub title element. 06/03/2026 - As discussed with Namita ma'am, the whole benefit is authored in the title itself. Instead title should only have 1 or 2 words and the rest should go in the sub-title. Therefore this needs to be done by the content authoring team, hence assigning to Neha Jain | K122: Resolved
A123: PhonePe SBI Card Select Black | B123: P2 | C123: iPad Mini | D123: Overlap | E123: Rs. 3 Lakhs | F123: Annual Fee Reversal | G123: Small | H123: Neha Jain | J123: 09/03/2026 - Word "Annual" needs to be in the title and "Fee Reversal" in the sub title element. 06/03/2026 - As discussed with Namita ma'am, the whole benefit is authored in the title itself. Instead title should only have 1 or 2 words and the rest should go in the sub-title. Therefore this needs to be done by the content authoring team, hence assigning to Neha Jain | K123: Resolved
A124: PayTM SBI Card | B124: P3 | C124: All Devices | D124: Overlap | E124: Rs. 1 Lakh | F124: e-Voucher - Paytm First Membership Renewal | G124: Small, Default | H124: Namita | J124: 09/03/2026 - As discussed with Arun sir, this is one of the instance that cannot be handled by breaking it and adjusting into titles & sub-titles therefore it needs to be shortened. Hence changing the Assigned to column value from Neha Jain ma'am to Namita Ma'am in order to discussion and get a confirmation. 06/03/2026 - As discussed with Namita ma'am, the whole benefit is authored in the title itself. Instead title should only have 1 or 2 words and the rest should go in the sub-title. Therefore this needs to be done by the content authoring team, hence assigning to Neha Jain | K124: Open
... A156: Shaurya SBI Card Select | B156: P2 | C156: iPad Mini | D156: Overlap | E156: Rs. 1.5 Lakh | F156: Waiver of Renewal Fee | G156: Small | H156: Neha Jain | J156: 09/03/2026 - The word "Waiver" needs to be in the title and "of Renewal Fee" in the sub-title element 06/03/2026 - As discussed with Namita ma'am, the whole benefit is authored in the title itself. Instead title should only have 1 or 2 words and the rest should go in the sub-title. Therefore this needs to be done by the content authoring team, hence assigning to Neha Jain | K156: Open

Sheet Fees & Charges Heading & Label
A1: Credit Card Page | B1: Section Heading - "Fee & Charges" to be changed to "Fees and Charges" | C1: Tab label to be changed from "FAQ" to "FAQs" | D1: Tab label to be changed from "Fees" to "Fees & Charges" | E1: Tab label to be changed from "Fee & Charges" to "Fees & Charges" | F1: Space needs to be added between "Rs." & the Price of the card. For ex: "Rs. 499" instead of "Rs.499"
A2: Air India SBI Platinum Card | B2: Yes | C2: Yes | F2: Yes
A3: Air India SBI Signature Card | C3: Yes | F3: Yes
A4: Apollo SBI Card | B4: Yes | C4: Yes | F4: Yes
A5: Apollo SBI Card Select | B5: Yes | C5: Yes | F5: Yes
A6: BPCL SBI Card | B6: Yes | F6: Yes
A7: Club Vistara SBI Card | B7: Yes | F7: Yes
A8: Club Vistara SBI Card Prime | B8: Yes | C8: Yes | F8: Yes
A9: Etihad Guest SBI Card | B9: Yes | C9: Yes | E9: Yes | F9: Yes
A10: Etihad Guest SBI Premier Card | B10: Yes | C10: Yes | E10: Yes | F10: Yes
A11: Flipkart SBI Card | B11: Yes | C11: Yes | E11: Yes | F11: Yes
A12: IRCTC Premier Card | C12: Yes | D12: Yes | F12: Yes
A13: IRCTC SBI Platinum Card | C13: Yes | D13: Yes | F13: Yes
A14: Indigo SBI Card | D14: Yes | F14: Yes
A15: Indigo SBI Card Elite | D15: Yes | F15: Yes
A16: Landmark SBI Card Prime | B16: Yes | C16: Yes | F16: Yes
A17: Landmark SBI Card Select | C17: Yes | E17: Yes | F17: Yes
A18: Ola Money SBI Card | B18: Yes | C18: Yes | F18: Yes
A19: Paytm SBI Card | B19: Yes | C19: Yes | F19: Yes
A20: Paytm SBI Card Select | B20: Yes | C20: Yes | F20: Yes
A21: PhonePe SBI Card Purple | B21: Yes | D21: Yes | F21: Yes
A22: PhonePe SBI Card Select Black | D22: Yes | F22: Yes
A23: Reliance SBI Card | B23: Yes | C23: Yes | F23: Yes
A24: Reliance SBI Card Prime | C24: Yes | F24: Yes
A25: SBI Card Miles | B25: Yes | F25: Yes
A26: SBI Card Miles Elite | B26: Yes | C26: Yes | F26: Yes
A27: SBI Card Miles Prime | C27: Yes | F27: Yes
A28: SBI Card Prime | B28: Yes | F28: Yes
A29: SBI Card Pulse | B29: Yes | D29: Yes | F29: Yes
A30: SBI Card Unnati | D30: Yes | F30: Yes
A31: Shaurya SBI Card | B31: Yes | C31: Yes | F31: Yes
A32: Shaurya Select SBI Card | B32: Yes | C32: Yes | F32: Yes
A33: SimplyClick SBI Card | C33: Yes | F33: Yes
A34: SimplySave SBI Card | C34: Yes | F34: Yes
A35: Titan SBI Card | B35: Yes | D35: Yes | F35: Yes

Sheet Home Page
A1: Defect No | B1: Date | C1: Priority | D1: Browser | E1: Device | F1: Font Size | G1: Stage | H1: Defect Type | I1: Steps to Reproduce | J1: Description | K1: Issue Screenshot/Recording | L1: Expected Result/ Design Reference | M1: Reported By | N1: Assigned To | O1: Dev Status | P1: Dev Remark | Q1: QA Status | R1: Last Updated | S1: QA Remark | T1: HTML QA Status
A2: UAT_HP_001 | B2: 28/12/2025 | C2: P2 | D2: All Browsers | E2: All Devices | F2: - | G2: UAT | H2: Content | I2: Hero Section --> 3rd Slide --> Apply Button | J2: The button label is "Apply More" instead of "Apply Now" | K2: https://www.loom.com/i/639996bc50564a43a90d170ae2d29ef3 | L2: https://www.loom.com/i/fb314dbf047d49f9aae513fdc6c19f6d | M2: Sampreet | Q2: Resolved | R2: 46143 | S2: Content related issue. Hence on Hold 23/01/2026 - Resolved on call
A3: UAT_HP_002 | B3: 28/12/2025 | C3: P2 | D3: All Browsers | E3: All Devices | F3: - | G3: UAT | H3: Content | I3: Hero Section --> All Slides --> CTA buttons (Apply now, See benefits) | J3: The button labels are not capitalized. | K3: https://www.loom.com/i/1535338797a640818268f54c45502abe | L3: https://www.loom.com/i/7e6a7962e45b47d2aa3e92bb4e937575 | M3: Sampreet | Q3: Hold | R3: 46143 | S3: Content related issue. Hence on Hold
A4: UAT_HP_003 | B4: 28/12/2025 | C4: P1 | D4: All Browsers | E4: All Devices | F4: - | G4: UAT | H4: Content | I4: Hero Section --> First Slide --> Heading | J4: Slide heading - "Welcome to the world of amazing cashback" font color needs to be yellow | K4: https://www.loom.com/i/e8b4f2b1f78648929e16bb6c178ae667 | L4: https://www.loom.com/i/2e59ef7046a94dcfae326052b9e99505 | M4: Sampreet | Q4: Hold | R4: 46143 | S4: Content related issue. Hence on Hold
A5: UAT_HP_004 | B5: 28/12/2025 | C5: P2 | D5: All Browsers | E5: All Devices | F5: - | G5: UAT | H5: Content | I5: Hero Section --> 3rd Slide --> Heading | J5: The word "Card" in the heading "Best Travel Card" needs to be capitalized | K5: https://www.loom.com/i/1dc7142a6c724ef99605d571e9212c01 | L5: https://www.loom.com/i/0992af6606c2460e868e1e4a3c3e2211 | M5: Sampreet | Q5: Hold | R5: 46143 | S5: Content related issue. Hence on Hold
A6: UAT_HP_005 | B6: 28/12/2025 | C6: P2 | D6: All Browsers | E6: All Devices | F6: - | G6: UAT | H6: Content | I6: Accessibility Bar --> Limited Offer | J6: The word "Default" appears before "Limited Offer" | K6: https://www.loom.com/i/82e5bf95e8844c63bf46b835f71fd14d | L6: - | M6: Sampreet | Q6: Hold | R6: 46143 | S6: Content related issue. Hence on Hold
A7: UAT_HP_006 | B7: 28/12/2025 | C7: P2 | D7: All Browsers | E7: All Devices | F7: - | G7: UAT | H7: Content | I7: Accessibility Bar -->Limited Offer | J7: The gift card worth "₹5" is mentioned instead of "₹500*" | K7: https://www.loom.com/i/6a9e0b6b469343ea8e4054c10d311181 | L7: - | M7: Sampreet | Q7: Hold | R7: 46143 | S7: Content related issue. Hence on Hold
A8: UAT_HP_007 | B8: 28/12/2025 | C8: P2 | D8: All Browsers | E8: All Devices | F8: - | G8: UAT | H8: Content | I8: Accessibility Bar --> Skip to the main menu | J8: The hyphen "-" appears twice before "Skip to the main menu" | K8: https://www.loom.com/i/2c94f61d86f64978b40ca8a7c458cbe2 | L8: - | M8: Sampreet | Q8: Hold | R8: 46143 | S8: Content related issue. Hence on Hold
A9: UAT_HP_008 | B9: 28/12/2025 | C9: P1 | D9: All Browsers | E9: All Devices | F9: - | G9: UAT | H9: Version | I9: Get More with SBI card --> Click on any of the 4 tabs on the left | J9: Clicking on any of the 4 tabs on the left should only change the content & image but it also takes the user to the top of the page | K9: https://www.loom.com/share/bf4392f7317348f1abffc55e9c80a4f9 | L9: - | M9: Sampreet | Q9: Resolved | R9: 29/1/2026 | S9: 5/1/2026 - When the UAT gets updated to v54
A10: UAT_HP_009 | B10: 28/12/2025 | C10: P1 | D10: All Browsers | E10: All Devices | F10: - | G10: UAT | H10: Content | I10: Get More with SBI card --> 2nd & 3rd & 4th tabs on the left | J10: The "Learn More" hyperlink is missing. | K10: https://www.loom.com/i/8600e596fee8408b86ebb80afaf9d66b | L10: https://www.loom.com/i/f2b3570ea5384656ae18443a1d74a5c8 | M10: Sampreet | Q10: Hold | R10: 46143 | S10: Content related issue. Hence on Hold
A11: UAT_HP_010 | B11: 28/12/2025 | C11: P1 | D11: All Browsers | E11: All Devices | F11: - | G11: UAT | H11: Content | I11: Footer --> Important Links | J11: 3 Hyperlinks missing - Credit Card Issuance & Conduct Policy, Fair Practice Code, Forms Central | K11: https://www.loom.com/i/0fbd3f45a9224042a11bc65b05792b52 | L11: https://www.loom.com/i/bc368accb1b943a9b2f0b15fd8d68453 | M11: Sampreet | Q11: Hold | R11: 46143 | S11: Content related issue. Hence on Hold
A12: UAT_HP_011 | B12: 28/12/2025 | C12: P2 | D12: All Browsers | E12: All Devices | F12: - | G12: UAT | H12: Content | I12: Language Hindi --> Sub Navigation Pane below the Hero section --> Utility Bills Payment icon | J12: When language is changed to hindi, the utility bills payment CTA starts to show Rs. icon instead of its own icon. | K12: https://www.loom.com/i/2829e877e37f4dd291ba21cc57f34a1d | L12: https://www.loom.com/i/346ad77bb3c446189e36810cbfa03b9b | M12: Sampreet | Q12: Hold | R12: 46143 | S12: Content related issue. Hence on Hold
A13: UAT_HP_012 | B13: 28/12/2025 | C13: P1 | D13: All Browsers | E13: All Devices | F13: - | G13: UAT | H13: Content | I13: Language Hindi --> Secondary Header --> Tabs with drop down arrows | J13: Hover above each drop down tab to check the content is not translated to Hindi and is also missing content | K13: https://www.loom.com/share/eac148037b914cbd9eec7212438fa8f4 | L13: - | M13: Sampreet | Q13: Hold | R13: 46143 | S13: Content related issue. Hence on Hold
A14: UAT_HP_013 | B14: 28/12/2025 | C14: P2 | D14: All Browsers | E14: All Devices | F14: - | G14: HTML/CSS | H14: Padding | I14: Language Hindi --> Hero Section --> सर्वश्रेष्ठ ट्रैवल कार्ड | J14: When in hindi, the heading "सर्वश्रेष्ठ ट्रैवल कार्ड" is too close to the image above | K14: https://www.loom.com/i/01d085c9b09f46f5bc174e6755603939 | L14: - | M14: Sampreet | N14: Bharat | Q14: Hold | R14: 46143 | S14: 06/02/2026 - Hindi page issues are not being addressed in this release therefore kept on hold. 5/1/2026 - Also occurring in the benchmark HTML. Hence, On Hold | T14: Pending
A15: UAT_HP_014 | B15: 28/12/2025 | C15: P1 | D15: All Browsers | E15: All Devices | F15: - | G15: UAT | H15: Content | I15: Language Hindi --> EMI & More | J15: "ATM Cash" card & 5th - 6th card doesn't remain when user changes the language to hindi | K15: https://www.loom.com/share/22501c7eb8a44162beeb8d6e41eb2ee3 | L15: - | M15: Sampreet | Q15: Hold | R15: 46143 | S15: Content related issue. Hence on Hold
A16: UAT_HP_015 | B16: 28/12/2025 | C16: P2 | D16: All Browsers | E16: All Devices | F16: - | G16: UAT | H16: Content | I16: Language Hindi --> Logo Menus (below accessibility bar) --> Login --> Fogot password & New User? Register Now buttons & Hyperlinks below | J16: Fogot password & New User? Register Now buttons & Hyperlinks below do not get translated to hindi | K16: https://www.loom.com/i/b06f7779551a45ea95c40fa802cc38df | L16: - | M16: Sampreet | Q16: Hold | R16: 46143 | S16: Content related issue. Hence on Hold
A17: UAT_HP_016 | B17: 28/12/2025 | C17: P2 | D17: All Browsers | E17: All Devices | F17: - | G17: UAT | H17: Content | I17: Logo Menus (below accessibility bar) --> Help | J17: The help drop down is missing the following hyperlinks - Terms & Conditions, Raise a Dispute, Request For Card Closure, Report Lost Card, Digital Platform Updates, Link PAN with Adhaar, Contact Us. Also, the "Contact Us" hyperlink doesn't get translated to hindi | K17: https://www.loom.com/i/8ffe8404b9a448b98c08b71e62fc6180 | L17: https://www.loom.com/i/3d2cb3beb01b4d628f240567295ab062 | M17: Sampreet | Q17: Hold | R17: 46143 | S17: Content related issue. Hence on Hold
A18: UAT_HP_017 | B18: 28/12/2025 | C18: P2 | D18: All Browsers | E18: All Devices | F18: - | G18: UAT | H18: Content | I18: Why SBI Card? --> Heading | J18: The heading "Why SBI Card?" has 2 question marks instead of 1 | K18: https://www.loom.com/i/bcd7751566004a89b70d982ab67fb7d5 | L18: - | M18: Sampreet | Q18: Hold | R18: 46143 | S18: Content related issue. Hence on Hold
A19: UAT_HP_018 | B19: 28/12/2025 | C19: P2 | D19: All Browsers | E19: All Devices | F19: - | G19: UAT | H19: Content | I19: Header secondary menu --> Pay Card Bills | J19: The drop down label needs to be "Pay Card Bills" instead of "Pay Cards Bill" | K19: https://www.loom.com/i/b790d08b26fe4b6ca95c5a94cc678f9a | L19: https://www.loom.com/i/2f310b6193f7458c90c8cc96268dd8a9 | M19: Sampreet | Q19: Hold | R19: 46143 | S19: Content related issue. Hence on Hold
A20: UAT_HP_019 | B20: 28/12/2025 | C20: P2 | D20: All Browsers | E20: Desktops | F20: - | G20: UAT | H20: Content | I20: Language Hindi -->Section position | J20: When the language is Hindi, the Why SBI Card? section appears above the "EMI & More" section | K20: https://www.loom.com/i/581b541551e64b71af595c91ae7a8e45 | L20: - | M20: Sampreet | Q20: Hold | R20: 46143 | S20: Content related issue. Hence on Hold
A21: UAT_HP_020 | B21: 28/12/2025 | C21: P1 | D21: All Browsers | E21: Mobile Phones | F21: - | G21: HTML/CSS | H21: Layout | I21: Language English --> Why SBI Card? --> Card - Active Credit Card Users | J21: The card "Active Credit Card Users" overflows because of the card having extra content than it can have. | K21: https://www.loom.com/i/a0dd5753ba1049348f2ee49d453a2cf5 | L21: https://www.loom.com/i/a5d03755f6054d99b0b58836285286c1 | M21: Sampreet | N21: Arun | Q21: Resolved | R21: 19/01/2026 | S21: 06/02/2026 - As the design and content is changed, this bug is no longer valid. Therefore closing this and adding a new bug. 29/01/2026 - As per discussion with Namita ma'am, purple card's content needs to be updated. 27+ Yrs - Of Making Life Simple 19/01/2026 - As per Neha ma'am on call, the content needs to be reduced and therefore this needs to be assigned to Vijaita 05/01/2026 - Also occurring in the benchmark HTML. Hence, Closed.
A22: UAT_HP_021 | B22: 28/12/2025 | C22: P1 | D22: All Browsers | E22: Mobile Phones | F22: - | G22: UAT | H22: Link | I22: Why SBI Card? --> All Cards --> Extra Link | J22: The extra link was decided to be removed from the cards but it is still present | K22: https://www.loom.com/i/484f454f70c14e6c8d08e53e091434cc | L22: - | M22: Sampreet | N22: Sampreet | O22: Rejected | P22: Design got changed | Q22: Resolved | R22: 46144 | S22: 05/02/2026 - The extra link no longer visible in case of mobile phones as well therefore closing this issue. But the anchor is still present in the element which gets focused when navigating through keyboard tab and a separate bug with accessibility tagging is already on Hold for it for the time being because all accessibility bugs are decided to be fixed in the next release. 05/01/2026 - As per Dheeraj - When the UAT gets updated to v54 this would get fixed. v54 is to be deployed in next release
A23: UAT_HP_022 | B23: 28/12/2025 | C23: P2 | D23: All Browsers | E23: All Devices | F23: - | G23: UAT | H23: W3C Validation | I23: Entire Website | J23: The website has 53 HTML errors as per the W3C validator - https://validator.w3.org/nu/ | K23: https://www.loom.com/i/3e5e557e289949cba05e13ebfb056923 | L23: - | M23: Sampreet | N23: Neha Jain | P23: 24/02/2026 - This issue is already resolved | Q23: Open | R23: 24/02/2026 | S23: 24/02/2026 - As discussed on call, SBI team will check and identify why the doctype instance fails on the validator but get cleared in case of new HTML 06/02/2026 - Fixed on HTML, need to be implemented on UAT 29/01/2026 - As of now, only 1 error left - HTML Doctype missing. 05/01/2026 - Exists in the HTML v49 | T23: Fixed
A24: UAT_HP_023 | B24: 28/12/2025 | C24: P2 | D24: All Browsers | E24: All Devices | F24: - | G24: UAT | H24: Accessibility | I24: Entire Website | J24: 37 accessibility instances failed when tested with automated accessibility checker plug in - https://accessibilityinsights.io/ | K24: https://www.loom.com/i/6c36f4f670804c0d925e80afc1b84959 | L24: - | M24: Sampreet | Q24: Hold | R24: 30/01/2026 | S24: 30/01/2026 - As discussed on call, accessibility issues are to be kept on hold for now and to be picked in the next release. 28/01/2026 - Apart from the header and footer accessibility instance fails, 13 instances still fail that are related to page sections - https://www.loom.com/i/b8fcf1e57fe241199fa4758ad33778f4 https://www.loom.com/i/ed047e37e91341e7ae0eedf3a2844f41 https://www.loom.com/i/2e31f54a41e54c60853b16e94c4e0e75 5/1/2026 - Exists in the HTML v49
A25: UAT_HP_024 | B25: 28/12/2025 | C25: P2 | D25: All Browsers | E25: Desktops | F25: - | G25: UAT | H25: Accessibility | I25: Windows Narrator --> EMI & More --> Focus on each card | J25: When in focus it just narrates the card index and mentions it as "group" instead of mentioning it as "Link" and then proceeding to read the heading & sub headings of the card. Check the actual vs expected result recordings attached | K25: https://www.loom.com/share/85e0f9dfd7564da9805b1d0f6bff3777 | L25: https://www.loom.com/share/006cd6d170f543d69c537db3521839ca | M25: Sampreet | Q25: Hold | R25: 30/01/2026 | S25: 30/01/2026 - As discussed on call, accessibility issues are to be kept on hold for now and to be picked in the next release. 29/01/2026 - Javascrip has been provided to Dheeraj for arias that need to 05/01/2026 - When the UAT gets updated to v54
A26: UAT_HP_025 | B26: 28/12/2025 | C26: P2 | D26: All Browsers | E26: Desktops | F26: - | G26: HTML/CSS | H26: Accessibility | I26: Windows Narrator --> Get More with SBI card --> Focus on each Tab on the left | J26: When any of the left side tab is focused, its name is narrated twice. | K26: https://www.loom.com/share/3f5775bf043e4d63987a231a5817eb39 | L26: https://www.loom.com/share/0ae4a5e75624469aacd7ccad0328f559 | M26: Sampreet | N26: Bharat | Q26: Resolved | R26: 29/01/2026 | S26: 29/01/2026 - As discussed on call with Namita ma'am, Neha Laddha ma'am and Dheeraj, it is not actually reading the tab twice but it is reading the alt text for the icon present with the tab which is intended behaviour. Hence closing this issue. 5/1/2026 - When the UAT gets updated to v54
A27: UAT_HP_026 | B27: 46143 | C27: P1 | D27: All Browsers | E27: Touch Screen Devices | F27: - | G27: UAT | H27: Interaction | I27: Open UAT url on a touch screen device --> Use the pinch gesture to zoom in or out on the page | J27: Touch screen users unable to zoom in or out on the page using the pinch gesture. This happens for all pages. | K27: https://www.loom.com/share/7ebb6a8eba124d14a7982e709aebabf5 | L27: - | M27: Sampreet | N27: Neha Jain | O27: Fixed | P27: No discussion required | Q27: Resolved | R27: 46267 | S27: 09/02/2026 - Issue Resolved - https://www.loom.com/share/9e991917b2004bc9a44d190a21d0f907
A28: UAT_HP_027 | B28: 46174 | C28: P1 | D28: All Browsers | E28: Desktops / iPads / Tablets | F28: - | G28: UAT | H28: Interaction | I28: Why SBI Card? ---> Scroll over the last card --> Check if instead of the next section appearing, blank space appears and the Why SBI card? section appears again with | J28: While scrolling down the "Why SBI Card?" section, the next section should appear as user scroll down through the last card but instead empty space is noticed with the same section appearing again with all the cards clipped together. User as to scroll through again to reach the next section. Check the recording for better understanding. | K28: https://www.loom.com/share/c77b77f98b9641d1a8cf54a94e85706e | L28: - | M28: Sampreet | Q28: Resolved | R28: 16/02/2026 | S28: 16/02/2026 - Bug no longer valid as the design is now changed. 29/01/2026 - For the time being mobile view will be used even in case of desktop the issue is unable to get fixed. As per the discussion on call with Namita ma'am, this bug is therefore kept on hold.
A29: UAT_HP_028 | B29: 46174 | C29: P2 | D29: All Browsers | E29: Desktops | F29: - | G29: UAT | H29: Accessibility | I29: Keyboard Accessibility / Windows Narrator --> Why SBI Card? | J29: While navigating through keyboard tab, the focus gets on Why SBI Card? section and the narrator mentions "link" even though their is no specific element like link or button that should be in the logical order of the keyboard tab. | K29: https://www.loom.com/share/35d75fe354f24896ac1633ab903d5a14 | L29: - | M29: Sampreet | Q29: Hold | R29: 30/01/2026 | S29: 30/01/2026 - As discussed on call, accessibility issues are to be kept on hold for now and to be picked in the next release. 29/01/2026 - As demonstrated on call, the focus shifts to each of the cards in the stack of "Why SBI Card?" even if there is no focusable element visible on the card. Dheeraj checked and confirmed there is no anchor tab that is hidden and getting focused on but sampreet mentioned that keyboard tab does get the cards in focus and windows narrator as well announces something. Team will check and update.
A30: UAT_HP_029 | B30: 46174 | C30: P2 | D30: All Browsers | E30: Touch Screen Devices | F30: - | G30: UAT | H30: Interaction | I30: Touch Devices --> Explore our cards --> Slide through swipe gesture on the credit card images. | J30: On the touch screen devices, when user swipes on the credit card images to change slides, sometimes the card doesn't get uplifted when the slide is changed. | K30: https://www.loom.com/share/a3c08127bd6b4925b6367a00cb81af41 | L30: - | M30: Sampreet | N30: Neha Jain | O30: Rejected | P30: 16/02/2026 - Fixed on devsit1 | Q30: Resolved | R30: 17/02/2026 | S30: 17/02/2026 - The issue is now resolved on devsit1 - https://www.loom.com/share/f732e6a737c94427a7294c15dd32e679 17/02/2026 - This was marked as fixed on Devsit1 but when checked (even on incognito mode) this issue is still not resolved. 09/02/2026 - Make sure to perform the swipe gesture slowly on the card image itself instead of anywhere else and sometimes the slide will swipe but the card will not uplift. This is a valid bug as observed by Namita ma'am as well. 05/02/2026 - Make sure to perform the swipe gesture slowly on the card image itself instead of anywhere else and sometimes the slide will swipe but the card will not uplift. This is a valid bug as observed by Namita ma'am as well. 04/02/2026 - Make sure to perform the swipe gesture slowly on the card image itself instead of anywhere else and sometimes the slide will swipe but the card will not uplift. This is a valid bug as observed by Namita ma'am as well. 21/01/2026 - Swipe the card images and see 1 out of 5 times the slider gets changed but the card image doesn't get uplifted.
A31: UAT_HP_030 | B31: 46174 | C31: P2 | D31: All Browsers | E31: All Devices | F31: - | G31: UAT | H31: Margin | I31: Explore our cards --> Card content block --> Gap between each bullet point | J31: The gap between each bullet point is less than required. In HTML v49, mb-2 class is used to get a bottom margin below the bullet points. | K31: https://www.loom.com/i/863baa9243d345638053e66e53270c89 | L31: https://loom.com/i/3008f106ed3f4d4d9217e6447a9e2b49 | M31: Sampreet | N31: Neha Jain | O31: Fixed | P31: 09-02-2026 Verified, please verify with version 54 | Q31: Resolved | R31: 46267 | S31: 10/02/2026 - Issue Resolved - https://loom.com/i/fc6199bae2b6453e9d5889565939ada3 09/02/2026 - The mb-2 class is present for the element even in the v54. Please get this fixed 05/02/2026 - The mb-2 class is present for the element even in the v54. Please get this fixed 29/01/2026 - The issue also found in the HTML v54 therefore changed the tagging to HTML/CSS
A32: UAT_HP_031 | B32: 46235 | C32: P3 | D32: Firefox | E32: All Devices | F32: - | G32: UAT | H32: Missing | I32: Access any page (Home/Product Details) in firefox browser --> Notice if the SBI card splash screen appears | J32: In case of firefox browser, the SBI logo on the splash screen doesn't appear before every page load/reload. | K32: https://www.loom.com/share/025756db13e64e34a34e9eaff97ec898 | L32: - | M32: Sampreet | Q32: Resolved | R32: 23/02/2026 | S32: 23/02/2026 - Another issue already logged UAT_HP_60 for the loader. It is also reopened because the loader is working in correctly in case of firefox browser therefore closing this issue. 16/02/2026 - The loader has been provided and needs to be implemented. Once its done and it starts working fine on firefox as well, will close this issue. 14/01/2026 - Splash screen needs to be developed and shared, therefore the bug is on hold for now.
A33: UAT_HP_032 | B33: 46357 | C33: P1 | D33: All Browsers | E33: All Devices | F33: - | G33: UAT | H33: Version | I33: EMI & More section --> Left & Right slider buttons | J33: The left & right slider buttons are now appearing on top of the cards. | K33: https://www.loom.com/i/e857ce20a8cf4000b4045bf7d1aabc18 | L33: https://www.loom.com/i/1873e807643b46f0ac070479fbe65bd8 | M33: Sampreet | Q33: Resolved | R33: 13/01/2026 | S33: Issue no longer appearing, hence closing.
A34: UAT_HP_033 | B34: 46357 | C34: P2 | D34: All Browsers | E34: All Devices | F34: - | G34: UAT | H34: Version | I34: All Slider sections (EMI & More, SBI Credit Card mobile App) --> Slider dot colours | J34: EMI & More section & SBI Card Mobile App section slider dots no longer have the same colour they used to have. Instead of unselected and selected slides having - #636363 & #9f9494, they have #000000 & #007aff | K34: https://www.loom.com/i/7eafab8959874d71a5ef09ec36fa3065 | L34: https://www.loom.com/i/fa8b46f9971c408485832567392263f6 | M34: Sampreet | Q34: Resolved | R34: 13/01/2026 | S34: Issue no longer appearing, hence closing.
A35: UAT_HP_034 | B35: 46357 | C35: P1 | D35: All Browsers | E35: All Devices | F35: - | G35: UAT | H35: Version | I35: Explore Our Cards --> Left & Right slider buttons | J35: The left & right slider buttons are now appearing on top of the cards. | K35: https://www.loom.com/i/b30517249e0849009c1eeae64a16455c | L35: https://www.loom.com/i/8f972c2c00f840f3a9241a2d4931592e | M35: Sampreet | Q35: Resolved | R35: 13/01/2026 | S35: Issue no longer appearing, hence closing.
A36: UAT_HP_035 | B36: 46357 | C36: P3 | D36: All Browsers | E36: Mobile Devices | F36: - | G36: UAT | H36: Gap | I36: Explore Our Cards --> Card Image Container: tab-cards-item-block | J36: The gap between the tab headings and the card image is more than required because of static 250px height set for the card in focus. | K36: https://www.loom.com/i/e6fb2d266b874b6f92bf27983fe03722 | L36: https://www.loom.com/i/3959031ca198497082f1a2d4e17be648 | M36: Sampreet | N36: Neha Jain | O36: Rejected | P36: 09-02-2026 Verified, please verify with version 54 | Q36: Resolved | R36: 46267 | S36: 09/02/2026 - As discussed on SBI Qucik HTML discussion call, the images size was increased intentionally therefore this is not a bug. 09/02/2026 - Need to discuss, the card image size is larger when compared with v54 and therefore the gap between the tabs and the card images seems less then required - UAT/PVT - https://www.loom.com/i/f4aea9073986403faddc8d848ecd3639 HTML - https://www.loom.com/i/3d37929e50ea4caa875edd50ed80bab2 05/02/2026 - The issue is still the same - https://www.loom.com/i/fcd27786839040f997b183c99dd33aa2 https://www.loom.com/i/64a3bc9c25b84c12b0257a1b996409b9 04/02/2026 - The height should have been set to auto as it is in the HTML instead of being fixed at 185px. https://www.loom.com/i/aef5df14c0b5480db573272b1dd693d9
A37: UAT_HP_036 | B37: 46357 | C37: P2 | D37: All Browsers | E37: Mobile Devices | F37: - | G37: UAT | H37: Gap | I37: Explore Our Cards --> Gap between the selected card images | J37: The gap between the selected card image & the image prior to it seems less. | K37: https://www.loom.com/i/da829f531c194a189ad1b06751332106 | L37: https://www.loom.com/i/2140543c3a454da5ad22b97f637348c6 | M37: Sampreet | N37: Neha Jain | O37: Fixed | P37: 16/02/2026 - Fixed on devsit1 09-02-2026 Verified, please verify with version 54 | Q37: Resolved | R37: 17/02/2026 | S37: 17/02/2026 - As discussed on UAT, regarding the orientation (horizontal/vertical) a separate bug needs to be logged as the gap is no longer a problem as reviewed on the call.Bug - UAT_HP_083 logged for this specific issue 17/02/2026 - In the mobile view, the card images that should appear horizontally still appear vertical. Another discussion was held to keep the images diagonal even in mobile view but that as well seems not yet implemented. 09/02/2026 - The card image size issue is also mentioned in UAT_HP_035 bug. But the landscape mode that needs to be followed for some of the card images is still not being followed as identified by Namita ma'am 04/02/2026 - Not sure if this is a content issue. Also, the credit card images are larger when compared with HTML. Card image (horizontal or vertical) is not handled - all card images are vertical - https://www.loom.com/i/66473808852a4fa9950bc541858a2b53
A38: UAT_HP_037 | B38: 46357 | C38: P1 | D38: All Browsers | E38: Mobile Devices | F38: - | G38: UAT | H38: Version | I38: Explore Our Cards --> Rotate to change to landscape mode --> null appears between the 2 cards. | J38: On a real device when user rotates the phone from portrait to landscape, null appears between the cards. It only disappears when user refreshes the page or turns back to portrait mode. This issue also appears on product details page's "Similar Cards" | K38: https://www.loom.com/share/0ff02178b38247419bc35ff623b2dc8f | L38: - | M38: Sampreet | Q38: Resolved | R38: 14/01/2026 | S38: No longer occurring.
A39: UAT_HP_038 | B39: 13/01/2026 | C39: P2 | D39: All Browsers | E39: Desktops | F39: - | G39: UAT | H39: Accessibility | I39: Explore Our Cards --> Left & Right slider buttons --> Keyboard focus | J39: User remains unable to focus on the left & right slider buttons using keyboard. Same issue is faced in the similar cards section of the product details page | K39: https://www.loom.com/share/1813107823a94ecf84cadf43cb4c6035 | L39: https://www.loom.com/i/b9aaa4ba83ce452196a852cf8b384f2e | M39: Sampreet | Q39: Hold | R39: 30/01/2026 | S39: 30/01/2026 - As discussed on call, accessibility issues are to be kept on hold for now and to be picked in the next release. 29/01/2026 - As per Dheeraj, even if focus doesn't go to the slider buttons it doesn't cause any issue because user c
A40: UAT_HP_039 | B40: 14/01/2026 | C40: P1 | D40: All Browsers | E40: All Devices | F40: - | G40: UAT | H40: Missing | I40: Explore Our Cards --> All Cards in the slider | J40: Benefits missing for the cards in the slider along with CTA like Apply Now & See more Benefits for some of the cards. | K40: https://www.loom.com/i/77441823919944959862bbffbf5f1bb9 | L40: - | M40: Sampreet | P40: Not able to reproduce | Q40: Resolved | R40: 21/01/2026 | S40: The issue no appearing, hence resolved
A41: UAT_HP_040 | B41: 14/01/2026 | C41: P1 | D41: All Browsers | E41: All Devices | F41: - | G41: UAT | H41: Image | I41: Explore Our Cards --> Landmark Rewards SBI Card Select --> Image | J41: The image's aspect ratio is inconsistent with the other credit card images used. As a result the CTA positioning gets affected. | K41: https://www.loom.com/i/d9a8ebde62a24fa88e87d51901da9397 | L41: - | M41: Sampreet | N41: Sampreet | O41: Rejected | P41: Not able to reproduce | Q41: Resolved | R41: 46114 | S41: 04/02/2026 - This bug was occurring earlier as evident in the screenshots. Marking this as resolved as this is no longer occurring.
A42: UAT_HP_041 | B42: 14/01/2026 | C42: P1 | D42: All Browsers | E42: Desktops / iPads / Tablets | F42: - | G42: UAT | H42: Interaction | I42: EMI & More Section --> Slowly scroll Down the whole section | J42: While slowly scrolling down the EMI & More section, instead of the page going down normally and"Why SBI Card" section appearing slowly, it appears in an instant flash. Check the screen recording for better understanding. | K42: https://www.loom.com/share/ccdc86ff4f684b80b7413253787ca8df | L42: - | M42: Sampreet | N42: Sampreet | O42: Rejected | P42: Design get changed | Q42: Resolved | R42: 16/02/2026 | S42: 16/02/2026 - Bug no longer valid as the design is now changed. 04/02/2026 - For the time being we are following the mobile layout for desktops and ipads/ tablets as well. Because we are unable to solve the issues in desktop version of this section. Hence keeping the bug on hold
A43: UAT_HP_042 | B43: 16/01/2026 | C43: P1 | D43: All Browsers | E43: Desktops / iPads / Tablets | F43: - | G43: UAT | H43: Interaction | I43: Why SBI Card --> Scroll down | J43: While scrolling down the entire page slowly, the WHY SBI Card section sticks to the top and the rest of the page gets scrolled down. Therefore, in case of higher resolution systems (4K or Ultra HD screens) the Cards in the section do not stack completely up to 5 and in case of mid to small size screens the other screens can be seens scrolling down from the bottom (below the WHY SBI Card section) Check the recording for better understanding. | K43: https://www.loom.com/share/bad4caeb20c64073b55dfe88e8dd3dc7 | L43: - | M43: Sampreet | N43: Sampreet | O43: Rejected | P43: Design get changed | Q43: Resolved | R43: 16/02/2026 | S43: 16/02/2026 - Bug no longer valid as the design is now changed. 04/02/2026 - For the time being we are following the mobile layout for desktops and ipads/ tablets as well. Because we are unable to solve the issues in desktop version of this section. Hence keeping the bug on hold
A44: UAT_HP_043 | B44: 27/01/2026 | C44: P3 | D44: All Browsers | E44: Desktops / iPads / Tablets | F44: - | G44: HTML/CSS | H44: Padding | I44: Get More with SBI card --> Tabs on the Left --> Credit Card Eligibility Criteria | J44: The tab label gets too close to the vertical gridline on the right. A certain gap/margin/padding should be maintained between the label and the vertical gridline | K44: https://www.loom.com/i/5969a50519904960ac4cdd7e386c84bd | L44: https://www.loom.com/i/8352a6da1cda46c29316598af1c0e83f | M44: Sampreet | N44: Bharat | O44: Rejected | Q44: Resolved | R44: 18/02/2026 | S44: 18/02/2026 - The issue is resolved on devsit1 - https://loom.com/i/068ad23a9ccb4d8c8c0782c56845c589 06/02/2026 - verified it on the v3 HTML build but the issue still persists - https://www.loom.com/i/5fd12c4c8e5b4ef49d9bb92e2b61fef4 04/02/2026 - Content has been changed therefore this bug is no longer occurring by default. But if the content is increased, it does occur and it is also present in the benchmark HTML version therefore changing its tagging to HTML/CSS - https://www.loom.com/i/97b1260bd0f344a4b4cbe16e9dea0351 | T44: Fixed
A45: UAT_HP_044 | B45: 29/01/2026 | C45: P2 | D45: All Browsers | E45: Desktops / iPads / Tablets | F45: - | G45: UAT | H45: Missing | I45: Explore our Cards --> Each Card Benefits --> Benefit icons | J45: In case of desktops & ipad/tablets, the benefit sentences are missing their respective icons. | K45: https://www.loom.com/i/c8d88adb160a4b54923abd27077bc0ea | L45: - | M45: Sampreet | N45: Sampreet | O45: Rejected | P45: Not able to reproduce | Q45: Resolved | R45: 46114 | S45: 04/02/2026 - This bug was occurring earlier as evident in the screenshots. Marking this as resolved as this is no longer occurring.
A46: UAT_HP_045 | B46: 29/01/2026 | C46: P3 | D46: All Browsers | E46: Mobile Devices | F46: - | G46: HTML/CSS | H46: Alignment | I46: Explore our Cards --> Each Card Benefits --> 1st Benefit icon | J46: The first benefit icon is not vertically center aligned with its sentence on the right. | K46: https://www.loom.com/i/dae1d0d1d8954e04bb1aa2a9226c2452 | L46: - | M46: Sampreet | N46: Bharat | Q46: Resolved | R46: 18/02/2026 | S46: 18/02/2026 - The issue is resolved on devsit1 - https://loom.com/i/f979e1668b474667b929d937f9c672bc 06/02/2026 - The issue is still not resolved - https://www.loom.com/i/6ac6692d79534172a62cb867cfc20da1 04/02/2026 - Tagging changed to HTML because issue also occurring in our HTML as well. | T46: Fixed
A47: UAT_HP_046 | B47: 29/01/2026 | C47: P2 | D47: All Browsers | E47: All Devices | F47: - | G47: HTML/CSS | H47: Gap | I47: Explore our Cards --> Each Card --> Gap between benefits & CTAs below | J47: More than necessary gap found between the Benefit bullet points and the CTAs | K47: https://www.loom.com/i/927d9b387b964e8b8bd9ec368004fb42 | L47: - | M47: Sampreet | N47: Bharat | O47: Fixed | Q47: Resolved | R47: 23/02/2026 | S47: 23/02/2026 - The issue is resolved on devsit1 (In case of desktops & iPads) - https://loom.com/i/2d91bffa1b2b4db08574cf712e35de4e As discussed with Bharat on call, the issues is not fixed on mobile phones because of the height property still taking 130px height. He has fixed it and will be sending it across to get it implemented. Marking this issue as resolved for now and informing Arun sir. 06/02/2026 - The issue is only fixed in case of desktops & iPads, need to be fixed for mobile phones as well 04/02/2026 - The bug is no longer occurring in case of large font. But as the font size is reduced to default or smallest, the gap between benefit bullet points and CTAs is noticeable and it is also present in the benchmark HTML version therefore changing its tagging to HTML/CSS - https://www.loom.com/i/cc389fd3f6764c22b59c43fed43665f7 | T47: Reopen
A48: UAT_HP_047 | B48: 29/01/2026 | C48: P2 | D48: All Browsers | E48: All Devices | F48: - | G48: UAT | H48: Style | I48: Explore our Cards --> Recommended Cards & Latest Launches Tab --> Refresh the page | J48: Whenever user refreshes the page, increased font weight of both the tabs is noticed instead of only the one that is currently active. This goes normal as soon as user himself clicks or changes the tab. | K48: https://www.loom.com/share/f75e9662c33d499496e96647a351f15b | L48: - | M48: Sampreet | N48: Sampreet | O48: Fixed | Q48: Resolved | R48: 46114
A49: UAT_HP_048 | B49: 29/01/2026 | C49: P2 | D49: All Browsers | E49: All Devices | F49: - | G49: PVT | H49: Style | I49: All Pages --> Text with Roboto as Font-Family | J49: Across all the pages through the websites, where ever the text font-family was Roboto, now has sans-sarif | K49: https://www.loom.com/i/bb1afaf2795d400fb82c66f4781330ea | L49: - | M49: Sampreet | N49: Neha Laddha | O49: Fixed | P49: 11/03/2026 - Fixed on devsit1 23/02/2026 - Due to chatbot css 17/02/2026 - This is again, unresolved due to chatbot class 16/02/2026 - Fixed on devsit1 | Q49: Open | R49: 46329 | S49: 11/03/2026 - The issue is resolved on devsit1 for all pages- https://www.loom.com/share/e8ff311bedaf4dfc86349dac5f3a83ce Will close this issue once it gets resolved on sbi-pvt 23/02/2026 - Will close this issue as soon as roboto font appears back instead of sans-sarif 17/02/2026 - The issue is still not resolved. Still font family sans-sarif in place of Roboto 04/02/2026 - When first verified this fix, it was resolved but then noticed again after some time that is has started reocurring.
A50: UAT_HP_049 | B50: 29/01/2026 | C50: P3 | D50: All Browsers | E50: All Devices | F50: - | G50: UAT | H50: Accessibility | I50: Keyboard Navigation ---> Explore our Cards --> Recommended Cards & Latest Launches Tab | J50: When user navigates through keyboard tab and focuses on the mentioned tabs, the focus border doesn't appear. | K50: https://www.loom.com/i/df05d851e94e495bb7775bef18514ea0 | L50: - | M50: Sampreet | Q50: Hold | R50: 30/01/2026 | S50: 30/01/2026 - As discussed on call, accessibility issues are to be kept on hold for now and to be picked in the next release. 29/01/2026 - This issue also occurs on product details page's "Similar Card" section and the team needs to check and update what could be the reason for it as it is working in other environments.
A51: UAT_HP_050 | B51: 46114 | C51: P3 | D51: All Browsers | E51: Desktops | F51: - | G51: HTML/CSS | H51: Accessibility | I51: Keyboard Navigation ---> EMI & More --> Change card focus until slider slides --> Notice the position of the slider dots at the bottom | J51: While navigating through keyboard, user moves forward to next card focus and as soon as the slide is changed, the slider dot position goes to the left instead of remaining in the center. As a result, after all the cards, the focus never goes to the slider dots and they get skipped. Arrow & dots should not be present for any slider if not more than 1 slide is in the section. | K51: https://www.loom.com/share/306f639482044f4a9903fc0117ffb4ba | L51: - | M51: Sampreet | N51: Bharat | O51: Fixed | Q51: Resolved | R51: 18/02/2026 | S51: 18/02/2026 - The issue is resolved on devsit1 - https://loom.com/i/9cbe3e630ce44aada0ce58321ae63814 06/02/2026 - Fixed on HTML, need to be implemented on UAT | T51: Fixed
A52: UAT_HP_051 | B52: 46114 | C52: P2 | D52: All Browsers | E52: Desktops | F52: - | G52: HTML/CSS | H52: Functional | I52: Get More with SBI card --> Mobile Phones --> Expand different accordion tabs --> Check the image below the section title. | J52: In case of mobile phones, the Image below the section title doesn't change as the user expands different accordions then the first one. | K52: https://www.loom.com/i/3259934058874ddea44bf261d4b14673 | L52: - | M52: Sampreet | N52: Bharat | Q52: Resolved | R52: 46114 | S52: 04/02/2026 - As per the discuss with the developer & designer, it is confirmed that in case of mobile phones, same image was to be used. Therefore closing this issue.
A53: UAT_HP_052 | B53: 46114 | C53: P2 | D53: All Browsers | E53: Desktops / iPads / Tablets | F53: - | G53: UAT | H53: Gap | I53: Why SBI Card --> Stacked Cards -->Left & Right Slider buttons | J53: In case of desktops & ipad/tablets, more than required gap between the card stack and the slider buttons can be observed. | K53: https://www.loom.com/i/427df69b61ba4710a2d6f67408b5c180 | L53: https://www.loom.com/i/b00f5dea19e1416b83ffc0ea81bbf397 | M53: Sampreet | N53: Neha Jain | O53: Fixed | P53: 09-02-2026 Verified, please verify with version 54 | Q53: Resolved | R53: 46267 | S53: 09/02/2026 - The slider buttons are now closer in case of desktops & iPads / Tablets - https://loom.com/i/133aef44d3f44d43b4b45ab1162d8de8
A54: UAT_HP_053 | B54: 46175 | C54: P3 | D54: All Browsers | E54: iPads Pro, iPad Air | F54: - | G54: PVT | H54: Content | I54: PVT --> iPad Pro/ iPad Air --> Header sub navigation wrap --> button labels | J54: The button label are lengthy and get to close together. | K54: https://www.loom.com/i/856607508af74c31804d30321fdcc054 | L54: - | M54: Sampreet | N54: Neha Jain | O54: Fixed | P54: 16/02/2026 - Fixed on pvt | Q54: Resolved | R54: 17/02/2026 | S54: 17/02/2026 - As discussed on call with Namita ma'am (UAT discussion call). The button labels had to be shortened like - "Card Payments" to "Payments" & "Utility Bill Payment" to "Easy Bill Pay". This has created some breathing space between the labels in case of iPads. Although if font size is increased, the still get too close to each other but as confirmed on call, no further changes can be done on this HTML/CSS wise or content wise therefore closing this - https://loom.com/i/0ee4ee59780d462482b7fefd5d289e02
A55: UAT_HP_054 | B55: 46175 | C55: P3 | D55: All Browsers | E55: iPads / Tablets | F55: - | G55: UAT | H55: Truncated Content | I55: iPads / Tablets --> Get More with SBI Card section --> Left side tabs | J55: The 4 tab labels on the left side get truncated. | K55: https://www.loom.com/i/6d57455155d446e2823deb349a16340a | L55: - | M55: Sampreet | N55: Neha Jain | O55: Fixed | P55: 16/02/2026 - Fixed on devsit1 | Q55: Resolved | R55: 23/02/2026 | S55: 23/02/2026 - This issue was already resolved on 17/02/2026 but came in the list to verify again 17/02/2026 - The issue is resolved on devsit1 - https://loom.com/i/58bf2993318b43c7b619409ef827a2a4 But as it is still not resolved on pvt as mentioned in the observation sheet, therefore couldn't close it as it is a PVT bug - https://www.loom.com/i/76569c7771ca42f582db8c9b985e4f85
A56: UAT_HP_055 | B56: 46175 | C56: P2 | D56: All Browsers | E56: All Devices | F56: - | G56: PVT | H56: W3C Validation | I56: PVT --> Nu HTML Validator --> https://validator.unl.edu/ | J56: 4 extra HTML error can be observed apart from the doctype error that was already in the devsit link | K56: https://www.loom.com/i/8ff99cc7b8834a00b4f72083b9289831 | L56: - | M56: Sampreet | N56: Neha Jain | P56: 23/02/2026 - We will pick this after the release as discussed on the call. | Q56: Hold | R56: 23/02/2026 | S56: 23/02/2026 - As discussed on call, we will pick this after current release therefore putting this call on hold for now.
A57: UAT_HP_056 | B57: 21/01/2026 | C57: P2 | D57: All Browsers | E57: Mobile Phones | F57: - | G57: UAT | H57: Gap | I57: Mobile Footer Menu --> Card Payment Tab | J57: The card payment tab appears close to the "Apply Now" button. This may be because each tab's width depends on the content size and the space between them is distributed evenly. | K57: https://www.loom.com/i/aa84c333aaa04b559ccd572223ed60d8 | L57: - | M57: Sampreet | N57: Neha Jain | Q57: Open | R57: 46267 | S57: 13/02/2026 - Icon & button position changed on HTML and screenshot shared. Rs. Icon shared as well. 09/02/2026 - Rs. symbol needs to be used instead of the current icon. | T57: Fixed
A58: UAT_HP_057 | B58: 46267 | C58: P3 | D58: All Browsers | E58: All Devices | F58: - | G58: HTML/CSS | H58: Interaction | I58: Explore our Cards, EMI & More Section --> Auto Slide | J58: Both the mentioned sections do not auto slide. Also, in case of desktop, not only should they auto slide but should also pause if mouse is hovered on any of the slide/card and in case of mobile if tapped and holded | K58: https://www.loom.com/share/4bee97879c714c7d8fa72ac3b7a9370e | L58: - | M58: Namita | N58: Bharat | P58: 24/02/2026 - As discussed on call, this issue is not in any of the doc received till 16th Feb and as we are only picking fixes received till 16th Feb therefore the issue is not picked. | Q58: Open | R58: 24/02/2026 | S58: 24/02/2026 - Need to discuss with Arun sir/Namita ma'am in context to the dev remark | T58: Fixed
A59: UAT_HP_058 | B59: 46328 | C59: P2 | D59: All Browsers | E59: All Devices | F59: - | G59: UAT | H59: Slider Dots | I59: Hero Section --> Banner slider dots | J59: The Banner slider dots new css style has not yet been implemented -check the expected vs actual result. Bug logged as requested by Namita ma'am | K59: https://www.loom.com/i/ddcaf26c43cc42988e6020e1aa070218 | L59: https://www.loom.com/i/20687d24b37a462e85cd0bc9f7f74dda | M59: Namita | N59: Neha Jain | O59: Fixed | P59: 16/02/2026 - Fixed on devsit1 | Q59: Resolved | R59: 17/02/2026 | S59: 17/02/2026 - Issue resolved on devsit1. As confirmed on mail, functional or UI/UX issues to be checked on closed on devsit1, therefore closing this - https://www.loom.com/i/d6888a79577f4004b8a837978b1e8d74
A60: UAT_HP_059 | B60: 46328 | C60: P1 | D60: All Browsers | E60: All Devices | F60: - | G60: UAT | H60: Hero Banner | I60: Hero Section --> Banner slides --> Title & T&Cs | J60: The Banner slider titles still appear in all caps, the font size still not reduced and the T&Cs at the right hand side is missing. Also need to have a browsable image option in case of Tablet background image - for the font size and caps. - check expected vs actual result - Bug logged as requested by Namita ma'am | K60: https://www.loom.com/i/2b28fc5dcd494ad1941c24d458a76d80 | L60: https://www.loom.com/i/d35eb320b0164a7ba6d9535589da4f98 | M60: Namita | N60: Neha Jain | O60: Fixed | P60: 16/02/2026 - Fixed on devsit1 | Q60: Resolved | R60: 17/02/2026 | S60: 17/02/2026 - Issue resolved on devsit1. As confirmed on mail, functional or UI/UX issues to be checked on closed on devsit1, therefore closing this - https://loom.com/i/1d333109220949fe9d93545e6742bba2 https://loom.com/i/727ca7519bcc458cab5a39edde32eded Also, as informed by Bharat on call, Namita ma'am decided that in case of desktop & ipad, the hero section's title doesn't doesn't have to change its size when user increases or decreases the font size because it is already large enough to be readable. So, it's size is not set in rem and in pixel instead and it not adjusting its size is intentional behaviour
A61: UAT_HP_060 | B61: 46328 | C61: P2 | D61: All Browsers | E61: All Devices | F61: - | G61: UAT | H61: Loader | I61: Refresh or Load any page in the entire platform | J61: New Loader needs to be implemented as it is already sent on 2nd Feb - Bug logged as requested by Prajjwal | K61: - | L61: - | M61: Namita | N61: Neha Jain | O61: Fixed | P61: 23/02/2026 - Fixed on devsit 16/02/2026 - Fixed on devsit1 | Q61: Reopened | R61: 23/02/2026 | S61: 23/02/2026 - In case of mobile phones, the loader credit card slightly changes its position after appearing. In case of firefox, "Front" & "Back" alt text appear instead of the credit card for a brief moment before the credit card animation loads. Plus, the credit card animation doesn't appear to be smooth https://www.loom.com/share/c20d4233aa7e4346ad9bd45cf63b45e0 17/02/2026 - The new loader with the glassmorphism effect and credit card image size slightly reduced is not yet implemented. In case of mobile phones, the loader credit card slightly changes its position after appearing. In case of firefox, "Front" & "Back" alt text appear instead of the credit card for a brief moment before the credit card animation loads. Plus, the credit card animation doesn't appear to be smooth https://www.loom.com/share/c20d4233aa7e4346ad9bd45cf63b45e0
A62: UAT_HP_061 | B62: 46328 | C62: P1 | D62: All Browsers | E62: All Devices | F62: - | G62: UAT | H62: Hero Banner | I62: Hero Section --> Banner slides | J62: Add Background stacking class option for each slide as informed on HTML discussion call, the author should have an option to add a class to each banner slide in the Home hero banner. | K62: - | L62: - | M62: Namita | N62: Neha Jain | Q62: Resolved | R62: 23/02/2026 | S62: 23/02/2026 - This issues was already resolved on 20/02/2026 20/02/2026 - As demonstrated by Neha Jain ma'am on call, the author is able to add background class from CMS. Therefore, closing this issue. 17/02/2026 - As discussed with Bharat on call, this bug was regarding stacking the class on the hero section slide div. For ex: bg-bottom. This is now implemented - https://www.loom.com/i/42175b81993e4a20a17bb5c47676c611 However, as the bug was not marked as fixed in the observation sheet therefore not closing it until its received for verification.
A63: UAT_HP_062 | B63: 13/02/2026 | C63: P2 | D63: All Browsers | E63: Desktops / iPads / Tablets | F63: - | G63: PVT | H63: Auto Tab switch | I63: PVT --> Get more with SBI Card -> Left side Tabs | J63: On the PVT environment, the "Get more with SBI Card" tabs do not auto switch like they do in the devsit1 environment. Check the actual vs expected result screenshot. | K63: https://www.loom.com/share/f99b37eb669c4af495d55cc87948d185 | L63: https://www.loom.com/share/6294cf1f89af4c4dbd1661f7f98aa754 | M63: Sampreet | P63: 23/02/2026 - Once we deployed the build on PVT it will get fixed, till now you can verify on devsit | Q63: Resolved | R63: 25/02/2026 | S63: 25/02/2026 - This is resolved on sbi-pvt - https://www.loom.com/share/a9939364d5964f019a8bf1682bf908a8 23/02/2026 - This is working fine on devsit1, once it also works the same way in pvt, will close this issue. 20/02/2026 - This is working fine on devsit1, once it also works the same way in pvt, will close this issue.
A64: UAT_HP_063 | B64: 16/02/2026 | C64: P2 | D64: All Browsers | E64: All Devices | F64: - | G64: PVT | H64: Content | I64: PVT --> Hero Section --> 1st, 3rd & 4th Slide --> Banner's sub line above title | J64: The Banner's sub line above the text is missing the font style (Dancing script) its colour (white) & it's size | K64: https://www.loom.com/i/e3dca667271a40498d27e312bdcaef6a | L64: - | M64: Sampreet | P64: 23/02/2026 - Verify on devsit1 | Q64: Resolved | R64: 25/02/2026 | S64: 25/02/2026 - This issue is resolved on PVT - https://loom.com/i/f0c37bddd24c4b959dc16d469b712fb4 23/02/2026 - This issue has been fixed on devsit1 - https://loom.com/i/1fe26ef809804b02977020cfe166f3da Will close this as soon as it gets forwarded to pvt and works fine there as it is a pvt issue
A65: UAT_HP_064 | B65: 16/02/2026 | C65: P2 | D65: All Browsers | E65: All Devices | F65: - | G65: PVT | H65: Content | I65: PVT --> Hero Section --> 3rd Slide ( Presenting Indigo SBI cards ) | J65: As per the content file, this slide doesn't have a sub title. Currently, its sub line text is being used as a title and the title is being used as sub title. | K65: https://www.loom.com/i/3f42df8244f844e2bc3652099c42f925 | L65: - | M65: Sampreet | N65: Arun | P65: 23/02/2026 - Need Discussion - Sampreet need to clarify this with the content Team | Q65: Resolved | R65: 23/02/2026 | S65: 23/02/2026 - As confirmed by Arun sir on call, this banner doesn't have a subtitle therefore subtitle not being there is not a bug. Hence closing this issue.
A66: UAT_HP_065 | B66: 16/02/2026 | C66: P3 | D66: All Browsers | E66: All Devices | F66: - | G66: PVT | H66: Content | I66: PVT --> Discover Our Cards --> Recent Launches --> Card Titles --> Capitalizations | J66: Except for Flipkart SBI Card, rest of the card titles are in "All Caps" instead of only each word in the card title having capitalization | K66: https://www.loom.com/i/67305defc68c43289bc5e4b0d7530b36 | L66: - | M66: Sampreet | N66: Neha Jain | O66: Fixed | P66: 23/02/2026 - Card Name- follow excel | Q66: Reopened | R66: 46145 | S66: 05/03/2026 - The word "Neu" should not be all caps as per the master sorting sheet - https://www.loom.com/i/209a6c9a0b314a5092338ed4aa7099e0 23/02/2026 - As discussed with Arun sir, Namita ma'am has confirmed that the card name casing needs to be exactly like the master sheet that has been shared with the team
A67: UAT_HP_066 | B67: 16/02/2026 | C67: P3 | D67: All Browsers | E67: All Devices | F67: - | G67: PVT | H67: Content | I67: PVT --> Discover Our Cards --> Featured Cards --> Card Titles --> Capitalizations | J67: The card title capitalization (lower case/upper case) of each letter doesn't exactly match when compared with the content file | K67: https://www.loom.com/i/306db704e66b40bca44fce12a086e84d | L67: - | M67: Sampreet | N67: Neha Jain | P67: 23/02/2026 - Card Name- follow excel | Q67: Reopened | R67: 46145 | S67: 05/03/2026 - As per the master sorting excel sheet - Cashback SBI Card - The word "Cashback" should be in all caps SimplyCLICK SBI Card - Both words "Simply" & "CLICK" should be together as a single word. SBI Card Miles Elite - The word "Elite" should not be in all caps. https://www.loom.com/i/f4f21c240ff040d2ba92ef6c10559790 23/02/2026 - As discussed with Arun sir, Namita ma'am has confirmed that the card name casing needs to be exactly like the master sheet that has been shared with the team
A68: UAT_HP_067 | B68: 16/02/2026 | C68: P3 | D68: All Browsers | E68: All Devices | F68: - | G68: PVT | H68: Content | I68: PVT --> Get more with SBI Card --> Credit Card Security Tips --> Paragraph above bullet points | J68: The word "Financial" is spelled incorrectly - "Finacial". Also, in the content file it is "Loss" instead of "Losses" | K68: https://www.loom.com/i/00878465f6e648c8874d2a37563c421c | L68: - | M68: Sampreet | P68: 23/02/2026 - fixed on pvt | Q68: Resolved | R68: 23/02/2026 | S68: 23/02/2026 - The issue is resolved on sbi-pvt - https://loom.com/i/143e0a8f66254dad82c497a85708fed6
A69: UAT_HP_068 | B69: 16/02/2026 | C69: P3 | D69: All Browsers | E69: All Devices | F69: - | G69: PVT | H69: Content | I69: PVT --> Get more with SBI Card --> Credit Card Security Tips --> Tips to Secure your Card --> 2nd Tip sentence | J69: The 2nd Tips sentence doesn't exactly match with the one present in the content file. The sentence should be "Protect your credit card’s confidential details like PIN, Card Expiry Date, and Card Verification Value (CVV). Never share them with anyone through phone call or E-mail." | K69: https://www.loom.com/i/d6530acb55cc40749b435ecce71c3f8a | L69: - | M69: Sampreet | P69: 23/02/2026 - fixed on pvt | Q69: Resolved | R69: 23/02/2026 | S69: 23/02/2026 - The issue is resolved on sbi-pvt - https://loom.com/i/143e0a8f66254dad82c497a85708fed6
A70: UAT_HP_069 | B70: 16/02/2026 | C70: P3 | D70: All Browsers | E70: All Devices | F70: - | G70: PVT | H70: Content | I70: PVT --> Get more with SBI Card --> Credit Card Interest Rates --> Understanding Credit Card Interest Rates (Paragraph) | J70: In the entire paragraph, "Interest rates" written instead of "Interest rate" as written in the content file and therefore instead of "Interest rates are" it should be "Interest rate is" | K70: https://www.loom.com/i/c0e01c8bf5e44cca9a1dbcf75f2b61ea | L70: - | M70: Sampreet | N70: Neha Jain | P70: 23/02/2026 - fixed on pvt | Q70: Resolved | R70: 46145 | S70: 05/03/2026 - The issue is resolved on sbi-pvt 23/02/2026 - In the 2nd line "Credit card interest rate are also known as credit card finance charges." the word "are" needs to be "is" - https://loom.com/i/8ea56319bd404a8c8f290d1ac5602888
A71: UAT_HP_070 | B71: 16/02/2026 | C71: P2 | D71: All Browsers | E71: All Devices | F71: - | G71: PVT | H71: Content | I71: PVT --> Get more with SBI Card --> Credit Card Interest Rates --> When is the interest on a credit card charged? --> Each bullet point title | J71: Each of the pointer's title instead of being bold and in a separate line. It appears with <br> tags in it. | K71: https://www.loom.com/i/1806bd5eabd645f3b121b0d1b0064800 | L71: - | M71: Sampreet | P71: 23/02/2026 - Verify on devsit1 | Q71: Resolved | R71: 25/02/2026 | S71: 25/02/2026 - This issue is resolved on PVT - https://loom.com/i/09fd2c4c68ef4c258ccb955c0412d018 23/02/2026 - The issue is resolved on devsit1 - https://loom.com/i/9ac23c20b6074226bc0f8a91fb653300 As this is a pvt bug, will close this issue once it is also resolved on pvt
A72: UAT_HP_071 | B72: 16/02/2026 | C72: P3 | D72: All Browsers | E72: All Devices | F72: - | G72: HTML/CSS | H72: Content | I72: PVT --> Get more with SBI Card --> Credit Card Usage -->Top Paragraph | J72: Last line "Hence, it is important that you are aware of their terms and conditions when you sign up for them to avail maximum benefits" instead of being included in the paragraph, it is used a sub title. | K72: https://www.loom.com/i/035b537bd2594cc6a6b57832d3d53539 | L72: - | M72: Sampreet | N72: Bharat | P72: 23/02/2026 - Sampreet need to check with the content team. A list heading from the CMS is a mandatory field, and we don’t have the list heading in the content doc that’s why we put the last line in a list heading field | Q72: Open | R72: 46056 | S72: 02/03/2026 - The subheading that is mandatory, needs to be fixed. Nothing is supposed to mandatory. Needs to be fixed by Bharat 23/02/2026 - Needs to be discussed/confirmed/approved by Namita ma'am. Need to wait for her to be available again.
A73: UAT_HP_072 | B73: 16/02/2026 | C73: P2 | D73: All Browsers | E73: All Devices | F73: - | G73: PVT | H73: Content | I73: PVT --> Get more with SBI Card --> Credit Card Usage --> Bullet Points | J73: Each of the pointer's title instead of being bold and in a separate line. It appears with <br> tags in it. | K73: https://www.loom.com/i/cd241fcbffb4427d8c8e25e14ca8a62b | L73: - | M73: Sampreet | P73: 23/02/2026 - Verify on devsit1 | Q73: Resolved | R73: 25/02/2026 | S73: 25/02/2026 - The issue is resolved on pvt - https://loom.com/i/84229b420de3478c9637a158c3247daf 23/02/2026 - The issue is resolved on devsit1 - https://loom.com/i/b6ba48f44afa421cbd76778aba9d439b As this is a pvt bug, will close this issue once it is also resolved on pvt
A74: UAT_HP_073 | B74: 16/02/2026 | C74: P3 | D74: All Browsers | E74: All Devices | F74: - | G74: PVT | H74: Content | I74: PVT --> Get more with SBI Card --> Your Credit Score --> Top Paragraph | J74: Instead of words "credit" & "worthiness" , a single word "creditworthiness" needs to be used. | K74: https://www.loom.com/i/f198086095f94599a48f31f7d659a703 | L74: - | M74: Sampreet | P74: 23/02/2026 - fixed on pvt | Q74: Resolved | R74: 23/02/2026 | S74: 23/02/2026 - The issue is resolved on sbi-pvt - https://loom.com/i/c4f7f6d1f75743efbb63dfab95434b56
A75: UAT_HP_074 | B75: 16/02/2026 | C75: P3 | D75: All Browsers | E75: All Devices | F75: - | G75: PVT | H75: Content | I75: PVT --> Get more with SBI Card --> Your Credit Score --> Top Paragraph | J75: The sentence "Whereas a low score below..." needs to match with the content file to be "Whereas a low score below 600 is considered poor and places you in a risk zone, making it difficult to secure an approval. Having said that, people with lower scores can also be eligible for a credit card" | K75: https://www.loom.com/i/022bccaa2a92471a9a6bb707b697d188 | L75: - | M75: Sampreet | P75: 23/02/2026 - fixed on pvt | Q75: Resolved | R75: 23/02/2026 | S75: 23/02/2026 - The issue is resolved on sbi-pvt - https://loom.com/i/6e8ffe9faecd4dfd85938e2088124719
A76: UAT_HP_075 | B76: 16/02/2026 | C76: P2 | D76: All Browsers | E76: All Devices | F76: - | G76: PVT | H76: Content | I76: PVT --> Get more with SBI Card --> Your Credit Score --> Key Factors Affecting Your Credit Score --> 3rd Bullet point | J76: " credit card balance above" in the 3rd bullet point gets repeated twice | K76: https://www.loom.com/i/6a6905fe10b144aea721b95ca38f103c | L76: - | M76: Sampreet | P76: 23/02/2026 - fixed on pvt | Q76: Resolved | R76: 23/02/2026 | S76: 23/02/2026 - The issue is resolved on sbi-pvt - https://loom.com/i/5986f54e57c44b21bc330dc77a07c7e8
A77: UAT_HP_076 | B77: 16/02/2026 | C77: P2 | D77: All Browsers | E77: All Devices | F77: - | G77: PVT | H77: Content | I77: PVT --> Get more with SBI Card --> Credit Card Security tips & Card Eligibility Criteria Tabs --> Tab image on the right side | J77: In case of both the mentioned tabs in the steps to reproduce section, the tab images that appear are the same. | K77: https://www.loom.com/i/1a335e4dc7c4483a89235977aa84bb55 | L77: - | M77: Sampreet | N77: Neha Jain | P77: 23/02/2026 - Need the image from the content team | Q77: Resolved | R77: 46145 | S77: 05/03/2026 - The issue is resolved on sbi-pvt - https://www.loom.com/i/54a1386d0fc845b6afdde4369dd893b1 25/02/2026 - The issue is not resolved on sbi-pvt - https://loom.com/i/05dc392a70d14dc9ba38a3402a34ddb1 23/02/2026 - The issue is resolved on devsit1 - https://loom.com/i/6bdf18ffdcbe48aa98032312ccf35182 As this is a PVT issues, will close this if it gets resolved on PVT as well.
A78: UAT_HP_077 | B78: 16/02/2026 | C78: P3 | D78: All Browsers | E78: Galaxy Z Fold, Galaxy S8+ | F78: Large | G78: UAT | H78: Content Cropped | I78: EMI & More Section --> Devices less than 375px width --> Large Font | J78: "Flexi Payments" & "Balance Transfer on EMI" card sub title in the "EMI & More" section gets cropped by the image/animation present at the bottom of it. | K78: https://www.loom.com/i/24df780a55cd41279f29ae75a8eb3e77 | L78: - | M78: Sampreet | N78: Arun | P78: 03-03-2026 please check again | Q78: Open | R78: 46145 | S78: 05/03/2026 - The Balance Transfer on EMI card's sub title still gets cropped from the bottom in case of samsung galaxy z fold when the font size is largest - https://loom.com/i/8f4432a462ca4f798a18af410d60fd98 Issue assigned to Arun sir because for now only the content can be reduced.
A79: UAT_HP_078 | B79: 16/02/2026 | C79: P3 | D79: All Browsers | E79: All Devices | F79: - | G79: PVT | H79: Content | I79: PVT --> Sub navigation menu wrap --> "Payements" & "Easy Bills Pay" tab | J79: Please ignore the bug if some cotent changes were decided and the current label is the updated content but if not, "Payements" & "Easy Bills Pay" tab need to named "Card Payment" & "Utility Bill Payment" as per the latest content file for Header & Footer. | K79: https://www.loom.com/i/f42c59343bb84b1dad754b394818912f | L79: - | M79: Sampreet | P79: 23/02/2026 - This Change was requested by Namita on 13th feb Call: - Card Payments - Payments - Utility Bill Payment - Easy Bill Pay | Q79: Resolved | R79: 23/02/2026 | S79: 23/02/2026 - As requested by Namita ma'am on call, the changes were made - "Card Payments" to "Payments" & "Utility Bill Payment" to "Easy Bill Pay". Therefore closing this issue
A80: UAT_HP_079 | B80: 16/02/2026 | C80: P2 | D80: All Browsers | E80: All Devices | F80: - | G80: PVT | H80: Content | I80: PVT --> Discover Our Cards --> Recent Launches & Featured Cards --> See Benefits CTA for each card | J80: The "See Benefits" CTA for each card needs to be changed to "Explore More" as per the content file. | K80: https://www.loom.com/i/bf53b35007be40c7bb9b54bba120ac0d | L80: - | M80: Sampreet | Q80: Resolved | R80: 18/02/2026 | S80: 18/02/2026 - As discussed with Namita ma'am on UAT Discussion Call. This doesn't need to be changed. Hencing closing the issue.
A81: UAT_HP_080 | B81: 16/02/2026 | C81: P2 | D81: All Browsers | E81: All Devices | F81: - | G81: PVT | H81: Content | I81: PVT --> Get more with SBI Card --> Credit Cards Interest Rate Icon | J81: The Icon appears incorrectly. Like all other icons, it should be in the center of a circle boundary with some gap from the circle's circumference. | K81: https://www.loom.com/i/c236a42fd1d64c47a4fc53c6240419ab | L81: - | M81: Sampreet | N81: Sampreet | P81: 23/02/2026 - fixed on pvt | Q81: Resolved | R81: 46145 | S81: 05/03/2026 - The issue is resolved on sbi-pvt - https://loom.com/i/95815d566db846729020fe7e24ad2448 23/02/2026 - The icon has been provided as confirmed by Arun sir. The issue is yet to be resolved on sbi-pvt - https://www.loom.com/i/15c210e93d6741bab642eea05d4ba1d6
A82: UAT_HP_081 | B82: 16/02/2026 | C82: P1 | D82: All Browsers | E82: Mobile Phones | F82: - | G82: PVT | H82: Content | I82: PVT --> Mobile Phones --> Get more with SBI Card --> Credit Card Usage & Credit Card Interest Rate Tab | J82: The Icons appear for the mentioned tabs are not for mobile phones because their sizes do not match with the rest of the 3 icons. | K82: https://www.loom.com/i/0e461c5a36954fda9a5dfcdb3a38a188 | L82: - | M82: Sampreet | N82: Neha Jain | P82: 25/02/2026 - Fixed and verified on PVT 23/02/2026 - fixed on pvt | Q82: Resolved | R82: 26/02/2026 | S82: 26/02/2026 - The issue is resolved on sbi-pvt - https://loom.com/i/bc52c9f685dc4a66af895626fd089348 23/02/2026 - The icons have been provided as confirmed by Arun sir just today. Therefore, the issue is still not resolved on sbi-pvt as also presented on call.
A83: UAT_HP_082 | B83: 16/02/2026 | C83: P3 | D83: All Browsers | E83: iPads / Tablets | F83: - | G83: HTML/CSS | H83: Layout | I83: PVT --> iPads / Tablets --> Get more with SBI Card --> Left side Tab icons. | J83: In case of iPads/Tablets, the icon border shape doesn't remain circle in case of "Card Eligibility Criteria". The size of the icon "Your Credit Score" & "Credit Card Interest Rates" is more than required as the gap from the icon to its outer circle boundary is close to 0. Check the actual result (pvt) and expected result - (devsit1) | K83: https://www.loom.com/i/99024be70ecd4e1daac64d3e8b899fd8 | L83: https://loom.com/i/750be550b91b49cc93073dac5406259a | M83: Sampreet | N83: Bharat | P83: 23/02/2026 - fixed on pvt | Q83: Open | R83: 46145 | S83: 05/03/2026 - This issue is not resolved on sbi-pvt and when checked on HTML/CSS with Bharat on call, found that this also occurs in HTML/CSS benchmark version 49 & 50 therefore changing it's stage column value from PVT to HTML/CSS and assigning in to Bharat. 02/03/2026 - The issue is still present on iPads / Tablets, borders do not appear in a circle shape, the gap between the icon in the center and the border is not the same for all icons. The icons are not center aligned - https://www.loom.com/i/67a0c14d6db8485a8a61a155f454bdea 23/02/2026 - The icons have been provided as confirmed by Arun sir just today. Therefore, the issue is still not resolved on sbi-pvt as also presented on call - https://www.loom.com/i/5cc49fb09eb94e1c883c1fca57bf6fd5
A84: UAT_HP_083 | B84: 17/02/2026 | C84: P3 | D84: All Browsers | E84: Mobile Devices | F84: - | G84: UAT | H84: Image Orientation | I84: Mobile Phones --> Discover Our Cards (Explore Our Cards) --> Card Image Orientation | J84: There are some images that need to be horizontal but currently all images are vertical. A solution discussed on call regarding this was to make all the images diagonal as they are in the desktop view. A request on call was given to log this as a separate issue not only because it's no longer related to UAT_036 that had this concern written in QA remark but also because it shouldn't get missed by any chance. | K84: https://www.loom.com/i/e3c702628cf343d19569f7ac21710879 | L84: - | M84: Sampreet | N84: Neha Jain | P84: 23/02/2026 - We will do that change post go live | Q84: Open | R84: 46056 | S84: 02/03/2026 - As confirmed by Namita ma'am. This will be picked in the next release therefore marking this issue as P3. 23/02/2026 - This needs to be discussed with Namita ma'am as the credit card images being used are go incorrect with their current orientation.
A85: UAT_HP_084 | B85: 17/02/2026 | C85: P2 | D85: All Browsers | E85: Mobile Devices | F85: - | G85: PVT | H85: Content | I85: PVT --> Mobile Phones --> Home Page --> Hero Section --> Cashback Slide | J85: The Banner Image (animation) Purple Background doesn't blend with the purple background of the slide | K85: https://www.loom.com/i/488bc5c5a7e942d1bf98f5730b2ac3e4 | L85: - | M85: Sampreet | N85: Sampreet | P85: 23/02/2026 - Need the image from the content team | Q85: Resolved | R85: 46359 | S85: 11/03/2026 - The issue is resolved on sbi-pvt - https://loom.com/i/b13aaff8f35143429a3adc71a48aa678 05/03/2026 - Arun sir has been informed to sent the images if not already. 23/02/2026 - Had a call with Arun sir and got a confirmation that he has now sent the required image
A86: UAT_HP_085 | B86: 26/02/2026 | C86: P2 | D86: All Browsers | E86: All Devices | F86: - | G86: PVT | H86: Link | I86: Home Page & Catalogue Page --> Any Apply Now CTA | J86: Clicking on any of the "Apply Now" button for any card on Home or Catalogue Page leads to error 404 page not found | K86: https://www.loom.com/share/48e73d1ce62e4bf5a68a6f43d2261b24 | L86: - | M86: Sampreet | N86: Sampreet | Q86: Resolved | R86: 46145 | S86: 05/03/2026 - This issue was already resolved on 2nd March 2026 02/03/2026 - As demonstrated on UAT Discussion call, Neha Laddha ma'am confirmed that as all the URL redirections are correct (land on the correct url) it doesn't matter if the URLs are currently not working. Therefore, this bug needs to be closed.
A87: UAT_HP_086 | B87: 26/02/2026 | C87: P2 | D87: All Browsers | E87: All Devices | F87: - | G87: PVT | H87: Style | I87: Explore Our Cards / Similar Cards Section --> Card CTAs | J87: The background fill (purple) should be the style of the main CTA that is "Apply Now" instead of "See Benefits" | K87: https://www.loom.com/i/b8f0a0016aa04aea8c65e59dca691b51 | L87: - | M87: Sampreet | N87: Neha Jain | Q87: Reopened | R87: 46145 | S87: 05/03/2026 - The issue is not resolved on sbi-pvt - https://www.loom.com/i/1f07bca7b6a042d2b7dea80cad053ea0
A88: UAT_HP_087 | B88: 46056 | C88: P2 | D88: All Browsers | E88: Mobile Phones | F88: - | G88: PVT | H88: Layout | I88: Home & Catalogue Page --> Mobile Phones --> Mobile Footer Menu --> Apply Now button | J88: The button shape is not circular | K88: https://www.loom.com/i/8405a475a8af429fb1d9ba6c43957244 | L88: https://www.loom.com/i/479b2fb3128d4747b9d674642b725757 | M88: Sampreet | N88: Neha Jain | Q88: Open
A89: UAT_HP_088 | B89: 46056 | C89: P3 | D89: All Browsers | E89: Mobile Phones | F89: - | G89: PVT | H89: Content | I89: Home & Catalogue Page --> Mobile Phones --> Mobile Footer Menu --> Apply Now button | J89: The button label - "Apply Now" needs to be capitalized - "APPLY NOW" | K89: https://www.loom.com/i/8405a475a8af429fb1d9ba6c43957244 | L89: https://www.loom.com/i/479b2fb3128d4747b9d674642b725757 | M89: Sampreet | N89: Neha Jain | Q89: Open
A90: UAT_HP_089 | B90: 46056 | C90: P2 | D90: All Browsers | E90: All Devices | F90: - | G90: PVT | H90: Loader | I90: All Pages --> Refresh the Page --> Check if the loader animation disappears even before the page loads completely | J90: When user refreshes any of the page in the entire platform, in case due to internet or device, the loader disappears even before the page complets loading. | K90: https://www.loom.com/share/827f43fdea79414f9b32d40b282f352f | L90: - | M90: Sampreet | N90: Neha Jain | Q90: Open
A91: UAT_HP_090 | B91: 46084 | C91: P2 | D91: All Browsers | E91: All Devices | F91: - | G91: PVT | H91: Content | I91: Explore Our Cards --> Recent Launches --> Indigo SBI Card Elite --> 1st Bullet point | J91: as Welcome at the end of the 1st Benefit sentence needs to be removed as it has a strike-through in the latest content file | K91: https://www.loom.com/i/2b56126a00c44267b5ab98e76e7643ef | L91: - | M91: Sampreet | N91: Neha Jain | Q91: Open
A92: UAT_HP_091 | B92: 46084 | C92: P2 | D92: All Browsers | E92: All Devices | F92: - | G92: PVT | H92: Content | I92: Explore Our Cards --> Recent Launches --> Indigo SBI Card Elite --> 2nd Bullet point | J92: Instead of "129 Lakhs", it should be "12 Lakhs" | K92: https://www.loom.com/i/7185f01309a04653b08bffd1d283582b | L92: - | M92: Sampreet | N92: Neha Jain | Q92: Open
A93: UAT_HP_092 | B93: 46084 | C93: P2 | D93: All Browsers | E93: All Devices | F93: - | G93: PVT | H93: Content | I93: Explore Our Cards --> Recent Launches --> Indigo SBI Card Elite --> 3rd Bullet Point | J93: 8 & 6 have strike-through in the latest content file, which means they should not be included in the sentence | K93: https://www.loom.com/i/5e76c5eeb7d04417814021df83aa4cef | L93: - | M93: Sampreet | N93: Neha Jain | Q93: Open
A94: UAT_HP_093 | B94: 46084 | C94: P2 | D94: All Browsers | E94: All Devices | F94: - | G94: PVT | H94: Content | I94: Explore Our Cards --> Recent Launches --> Indigo SBI Card --> 1st Bullet point | J94: The first bullet point needs to be "Welcome Gift of 2,500 IndiGo BluChips." as per the latest content file | K94: https://www.loom.com/i/74b1c08289694cdc92309d81369c1dd5 | L94: - | M94: Sampreet | N94: Neha Jain | Q94: Open
A95: UAT_HP_094 | B95: 46084 | C95: P2 | D95: All Browsers | E95: All Devices | F95: - | G95: PVT | H95: Content | I95: Explore Our Cards --> Recent Launches --> Indigo SBI Card --> 3rd Bullet point | J95: The word "complimentary" and "in a year" are strike-through in the latest content file. They need to be removed from the 3rd bullet point sentence | K95: https://www.loom.com/i/227c365c180a44f7baf93acab20edda3 | L95: - | M95: Sampreet | N95: Neha Jain | Q95: Open
A96: UAT_HP_095 | B96: 46084 | C96: P2 | D96: All Browsers | E96: All Devices | F96: - | G96: PVT | H96: Content | I96: Explore Our Cards --> Recent Launches --> Tata Neu Infinity SBI Card --> 1st Bullet Point | J96: The 1st Bullet point is incomplete. It should be "Lowest Foreign Currency Mark-up Charge of 1.99% on international usage" as per the latest content file | K96: https://www.loom.com/i/8df20cbb3d0b438ab6347f7c6366b7c0 | L96: - | M96: Sampreet | N96: Neha Jain | Q96: Open
A97: UAT_HP_096 | B97: 46084 | C97: P2 | D97: All Browsers | E97: All Devices | F97: - | G97: PVT | H97: Content | I97: Explore Our Cards --> Recent Launches --> Tata Neu Infinity SBI Card --> 2nd Bullet Point | J97: The 2nd Bullet Point is incomplete. As per the latest content file, it should be "Earn 5% NeuCoins on spends at the Tata Neu App/Website and partner Tata brands + 5% NeuCoins on select categories on the Tata Neu App/Website" | K97: https://www.loom.com/i/e803dc3247ef4f85abaa1044ace5b2f5 | L97: - | M97: Sampreet | N97: Neha Jain | Q97: Open
A98: UAT_HP_097 | B98: 46084 | C98: P2 | D98: All Browsers | E98: All Devices | F98: - | G98: PVT | H98: Content | I98: Explore Our Cards --> Recent Launches -->Tata Neu Infinity SBI Card --> 3rd Bullet Point | J98: It should be "8 Domestic" & "4 International" Airport Lounge Accesses as per the latest content file. | K98: https://www.loom.com/i/9d6f8ef9089446b0bbdaca98349b73b4 | L98: - | M98: Sampreet | N98: Neha Jain | Q98: Open
A99: UAT_HP_098 | B99: 46084 | C99: P3 | D99: All Browsers | E99: All Devices | F99: - | G99: PVT | H99: Content | I99: Explore Our Cards --> Recent Launches --> Tata Neu Plus SBI Card --> 2nd Bullet point | J99: The preposition "of" needs to be removed between "1 Lakh" & "annual spends" | K99: https://www.loom.com/i/a364af0e08e040e196b893f95699598f | L99: - | M99: Sampreet | N99: Neha Jain | Q99: Open
... A109: UAT_HP_108 | B109: 46084 | C109: P2 | D109: All Browsers | E109: iPads / Tablets | F109: - | G109: PVT | H109: Layout | I109: iPads Pro 11 inches (834px x 1194px) --> Landscape mode --> Explore Our Cards --> Check if more than 3 cards appear in each slide | J109: In case the devices' screen resolution is anywhere where between 1025px - 1201px, instead of only 3 cards appearing in each slide, 4 cards appear. As a result, due to less space available, the bullet points get truncated with 3 dots at the end and the CTA labels get word wrapped to next line increasing the height of the CTA buttons | K109: https://www.loom.com/i/21a5db17148e43e1ad7b3264d21d56cd | L109: https://www.loom.com/i/dd189fbc9c394819acd7190d4293fd0e | M109: Sampreet | N109: Neha Jain | Q109: Open
...

Sheet Product Details Page
A1: Defect No | B1: Date | C1: Priority | D1: Browser | E1: Device | F1: Font Size | G1: Stage | H1: Defect Type | I1: Steps to Reproduce | J1: Description | K1: Issue Screenshot/Recording | L1: Expected Result/ Design Reference | M1: Reported By | N1: Assigned To | O1: Dev Status | P1: Dev Remark | Q1: QA Status | R1: Last Updated | S1: QA Remark | T1: HTML Status
A2: UAT_PD_001 | B2: 30/12/2025 | C2: P3 | D2: All Browsers | E2: All Devices | G2: HTML/CSS | H2: Alignment | I2: Key Benefits --> All Containers --> Icon & Content Alignment. | J2: The Container icons & content get vertically unaligned when compared with each other This is especially the case when the font size is reduced to smallest | K2: https://www.loom.com/i/ce0f5b4506c54c1485193ac63386ac2a | L2: - | M2: Sampreet | N2: Bharat | P2: Open for discussion. Need to find a solution. But for now, no content should be beyond 3 lines. Each benefit content should be almost same character length for now. | Q2: Open | R2: 25/02/2026 | S2: 25/02/2026 - This issue is from HTML team and no solution has yet been found regarding it therefore it remains in HTML Teams bucket with priority P3 as this cannot be fixed in the current release. Issue also occurring in the HTML v50 | T2: Reopen
A3: UAT_PD_002 | B3: 30/12/2025 | C3: P1 | D3: All Browsers | E3: Mobile Phones | G3: UAT | H3: Image | I3: Elite Card Fee & Charges --> Fees & Charges Tab --> The Rupee Icons | J3: The rupee icon of the 1st Tab "Fee & Charges" gets streched. | K3: https://www.loom.com/i/2710ccd82d5140c3becbf753e4a1c986 | L3: - | M3: Sampreet | Q3: Resolved | R3: 14/01/2026
A4: UAT_PD_003 | B4: 31/12/2025 | C4: P1 | D4: All Browsers | E4: Desktops | G4: UAT | H4: Accessibility | I4: Extension - "Accessibility Insights for Web" --> FastPass | J4: The accessibility checker highlights 24 accessibility fails - https://accessibilityinsights.io/downloads/ | K4: https://loom.com/i/d21c7dc820e74a57a85afc2947a714be | L4: - | M4: Sampreet | Q4: Hold | R4: 30/01/2025 | S4: 30/01/2026 - As discussed on call, accessibility issues are to be kept on hold for now and to be picked in the next release. 06/01/2026 - When tested using the accessibility extention on 6th Jan, only 17 instances were failed. 2 of them were related to colour contrast. Screenshots of other failed instances are attached below - https://www.loom.com/i/fb68b53ce98d4c41a4e73123e7f49fbd https://loom.com/i/67a919f65fb345668bd77dd22dbfb576
A5: UAT_PD_004 | B5: 31/12/2025 | C5: P2 | D5: All Browsers | E5: Desktops | G5: UAT | H5: Link | I5: Explore Rewards --> Milestone Rewards/ Elite Rewards --> Extra Link inside the tab content | J5: The Extra link present inside each tab content has no differenciation from the normal text content in terms of style | K5: https://www.loom.com/i/f7242b36f7e747fe9f2e26a581065b54 | L5: https://www.loom.com/i/5e363939e5f9420abefb813cf5184527 | M5: Sampreet | Q5: Resolved | R5: 46357
A6: UAT_PD_005 | B6: 31/12/2025 | C6: P1 | D6: All Browsers | E6: Mobile Phones | G6: HTML/CSS | H6: Padding | I6: Mobile Phones --> Network Privileges --> Master Card --> Check the Bank Logo & the text content | J6: The text content overlaps with the bank logo present on the left. Also, in each tab, the gap between the bank logo and the text besides should be same. | K6: https://www.loom.com/i/5db587cfc97444a2bf6ed7928f2b2e23 | L6: https://www.loom.com/i/82ec423a054e4608805ba95517ebba8b | M6: Sampreet | N6: Bharat | Q6: Resolved | R6: 18/02/2026 | S6: 18/02/2026 - The issue is now resolved on devsit1 - https://loom.com/i/ef50b734ebb143e0b88b274b2dfcd528 https://loom.com/i/482e6c3110af4562b7959185334c7823 https://loom.com/i/730267527eb04860b5cd316008f1d6dd 13/02/2025 - This issue is resolved on HTML v50 - 1 29/01/2026 - Discussed on call with Namita ma'am this is always going to be an unordered list therefore overlapping issue wouldn't be there. But, the gap between the icon & the text content is still not uniform and differs in case of each tab and when font size is increased/decreased. Check the recording - https://www.loom.com/share/04f18b61353e49d8b6e9185edadad260 05/01/2026 - Issue also occurring in the HTML v50 (changing the element from ul to ol) | T6: Fixed
A7: UAT_PD_006 | B7: 31/12/2025 | C7: P2 | D7: All Browsers | E7: iPads / Tablets | G7: UAT | H7: Functionality | I7: iPads / Tablets --> Exclusive Privileges --> + button --> More Button | J7: For each card, after clicking on + button, clicking the more button that appears doesn't open the pop up model with more details in case of iPad /Tablet devices | K7: https://www.loom.com/share/b1dd03fac451491a8f344be5282e8de4 | L7: https://www.loom.com/share/9233a91f01474185879b2bc8fe67b67a | M7: Sampreet | Q7: Resolved | R7: 29/01/2026 | S7: 29/01/2026 - Issue no longer occuring hence closing. 14/01/2026 - Cannot verify and close this because for now the more button is not present in case of any card.
A8: UAT_PD_007 | B8: 31/12/2025 | C8: P1 | D8: All Browsers | E8: iPhone 14 Pro / iPhone X | F8: Small | G8: HTML/CSS | H8: Padding | I8: iPhone 14 Pro / iPhone X --> Font size smallest --> Key benefits | J8: For the mentioned devices, when the text size is smallest, the text goes very close to the card boundary. It should have some padding as margin. Check 2nd benefit - "Earn upto 50,000" in the screenshot | K8: https://www.loom.com/i/b4bfd9a7ec20430f9ce3a910c2459f62 | L8: https://www.loom.com/i/f43f3b8086e44a32b8cfc63861532677 | M8: Sampreet | N8: Bharat | P8: Same as HTML | Q8: Resolved | R8: 20/02/2026 | S8: 20/02/2026 - The issue is resolved on devsit1 - https://loom.com/i/bfdb8a3f91a14982888b3a6dc481e99d 13/02/2026 - The issue is not resolved on HTML v50 - 1 https://www.loom.com/i/1041104a67cf4fa8a7ca8100e73d75dc 21/01/2026 - Issue can be noticed in card details for example SBI PRIME Card - https://www.loom.com/i/eec322a98efa4eabaa9dd98b09ad93c0 14/01/2026 - Tata Neu Infinity SBI Card - https://www.loom.com/i/4cfd037008044c2b8130dce4582861b1 | T8: Reopen
A9: UAT_PD_008 | B9: 46143 | C9: P2 | D9: All Browsers | E9: All Devices | G9: UAT | H9: Style | I9: Explore Rewards --> Milestones Rewards & Elite Rewards tab --> Content Class | J9: Text Content's class need to be updated. | K9: https://www.loom.com/i/f7242b36f7e747fe9f2e26a581065b54 | L9: - | M9: Sampreet | Q9: Resolved | R9: 46357
A10: UAT_PD_009 | B10: 46143 | C10: P1 | D10: All Browsers | E10: Touch Screen Devices | F10: - | G10: UAT | H10: Interaction | I10: Open UAT url on a touch screen device --> Use the pinch gesture to zoom in or out on the page | J10: Touch screen users unable to zoom in or out on the page using the pinch gesture. | K10: https://www.loom.com/share/7ebb6a8eba124d14a7982e709aebabf5 | L10: - | M10: Sampreet | Q10: Resolved | R10: 14/01/2026 | S10: This is a universal issue therefore keeping it open on the home page but closing it here as per Neha Jain's instructions
A11: UAT_PD_010 | B11: 46357 | C11: P1 | D11: Chrome, Edge | E11: Desktops, iPads / Tablets | F11: - | G11: UAT | H11: Icons | I11: Exclusive Privileges --> Card icon on the top --> Check if it gets clipped from the top | J11: Each of the card icon in the exclusive privileges gets clipped from the top. Check the expected vs actual result. | K11: https://www.loom.com/i/9f6628bcf1eb428b941b2d641035bcaf | L11: https://www.loom.com/i/851da11be2e34f5798a9bf3bd460a785 | M11: Sampreet | Q11: Resolved | R11: 13/01/2026 | S11: Issue no longer appearing, hence closing.
A12: UAT_PD_011 | B12: 46357 | C12: P1 | D12: All Browsers | E12: Desktop, iPads / Tablets | F12: - | G12: UAT | H12: Label | I12: Exclusive Privileges --> Add button to flip the card --> More button label missing | J12: For each card, after it gets flipped, the add button is missing its label "More". Check the actual vs expected result. | K12: https://www.loom.com/i/ff8a2d7f78354ad4b3137415177fb97f | L12: https://www.loom.com/i/7f22cb56a24345839af3ee953b313651 | M12: Sampreet | O12: Fixed | Q12: Resolved | R12: 29/01/2026 | S12: 14/01/2026-Cannot verify and close this because for now the more button is not present in case of any card.
A13: UAT_PD_012 | B13: 46357 | C13: P1 | D13: All Browsers | E13: Desktops, iPads / Tablets | F13: - | G13: UAT | H13: Gap | I13: Exclusive Privileges --> Slider arrow on the left --> Left slide icon missing gap from the container. Both left & right slider button overlap with the container when focused on. | J13: The Exclusive Privileges's left slider button needs to have some gap from the container like it has on the right side. Also when focus on left or right slider button, it should not overlap with the container. Check the actual vs expected results screenshot. | K13: https://www.loom.com/i/47fbc335804b43069c94912e93f7702b | L13: https://www.loom.com/i/b763cc19ae664dddaf6eb02b27378ec5 | M13: Sampreet | Q13: Resolved | R13: 13/01/2026 | S13: Issue no longer appearing, hence closing.
A14: UAT_PD_013 | B14: 46357 | C14: P1 | D14: Firefox | E14: Desktops, iPads / Tablets | F14: - | G14: UAT | H14: Missing | I14: Firefox --> Exclusive Privileges --> Card icons are missing | J14: Only on firefox browser, the card icons do not appear on the top. | K14: https://www.loom.com/i/4c9b087ae68e45cc8266470a7ffeeef3 | L14: - | M14: Sampreet | Q14: Resolved | R14: 13/01/2026 | S14: Issue no longer appearing, hence closing.
A15: UAT_PD_014 | B15: 46357 | C15: P2 | D15: All Browsers | E15: All Devices | F15: - | G15: UAT | H15: Version | I15: All Slider sections (Exclusive Privileges, Product Videos, Similar Cards) --> Slider dot colours | J15: Exclusive Privileges, Product Videos, Similar Cards section slider dots no longer have the same colour they used to have. Instead of unselected and selected slides having - #636363 & #9f9494, they have #000000 & #007aff | K15: https://www.loom.com/i/0382d1eb779f497d80de6f9b4926d8c1 | L15: https://www.loom.com/i/ffeb59619f084c768c0a70dcfab731f5 | M15: Sampreet | Q15: Resolved | R15: 13/01/2026 | S15: Issue no longer appearing, hence closing.
A16: UAT_PD_015 | B16: 46357 | C16: P1 | D16: All Browsers | E16: Desktops, iPads / Tablets | F16: - | G16: UAT | H16: Version | I16: Product Videos --> Left & right slider button | J16: The left & right slider buttons are now appearing on top of the videos | K16: https://www.loom.com/i/56f2a00b07e042cb82b3f90fddec8bd3 | L16: https://www.loom.com/i/5ff7f628680e4550a058c25f91b8e58d | M16: Sampreet | Q16: Resolved | R16: 13/01/2026 | S16: Issue no longer appearing, hence closing.
A17: UAT_PD_016 | B17: 46357 | C17: P1 | D17: All Browsers | E17: Desktops, iPads / Tablets | F17: - | G17: UAT | H17: Version | I17: Similar Cards --> Left & right slider buttons | J17: The left & right slider buttons are now appearing on top of the cards | K17: https://www.loom.com/i/09c58f524e1343f89369d186dfd5f1e3 | L17: https://www.loom.com/i/f2c06935ebac4f3bb27f762bf7b4441e | M17: Sampreet | Q17: Resolved | R17: 13/01/2026 | S17: Issue no longer appearing, hence closing.
A18: UAT_PD_017 | B18: 46357 | C18: P2 | D18: All Browsers | E18: Desktops, iPads / Tablets | F18: - | G18: HTML/CSS | H18: Truncated Content | I18: Exclusive Privileges --> Card --> Bullet Points | J18: The content gets truncated with 3 dots (..) in the second line. | K18: https://www.loom.com/i/98603d40c9cc4e34922f256d7c004bb5 | L18: https://www.loom.com/i/182c4dab9450449fb92eda1a36c73d2a | M18: Sampreet | N18: Bharat | Q18: Resolved | R18: 14/01/2026
A19: UAT_PD_018 | B19: 46357 | C19: P1 | D19: All Browsers | E19: All Devices | F19: - | G19: UAT | H19: Version | I19: Other Features --> Drop down arrow position | J19: Each button's drop down arrow should be placed on the left (before its text) instead of being place on the right (after the text) | K19: https://www.loom.com/i/7b59151597464bdc9fab0998f92ab520 | L19: https://www.loom.com/i/812070c3a86b4f53baa7203406f22163 | M19: Sampreet | Q19: Resolved | R19: 14/01/2026 | S19: No longer occurring
A20: UAT_PD_019 | B20: 46357 | C20: P0 | D20: All Browsers | E20: All Devices | F20: - | G20: UAT | H20: Version | I20: Similar Cards --> Slider Layout | J20: The slider layout breaks. Check the actual vs expected result screenshots. | K20: https://www.loom.com/i/fe44fafb421d4c5196be4da9a4084431 | L20: https://www.loom.com/i/a75a7356576b4376947f8dc1d0377c90 | M20: Sampreet | Q20: Resolved | R20: 14/01/2026 | S20: No longer occurring
